{"Exp-3406":{"tree":["Lval",[["Var","count"],null]],"text":"count","abs_text":"X"},"Exp-3559":{"tree":["Lval",[["Var","__cil_tmp39"],null]],"text":"__cil_tmp39","abs_text":"X"},"Exp-3684":{"tree":["Lval",[["Var","buffer"],["Index",["OtherExp"],null]]],"text":"buffer[__cil_tmp21-1UL]","abs_text":"X"},"Exp-3974":{"tree":["OtherExp"],"text":"*p2==61","abs_text":"X==C"},"Exp-3871":{"tree":["Lval",[["Var","__cil_tmp75"],null]],"text":"__cil_tmp75","abs_text":"X"},"Exp-3452":{"tree":["Lval",[["Var","print_error"],null]],"text":"@print_error","abs_text":"X"},"Exp-3854":{"tree":["Lval",[["Var","size"],null]],"text":"size","abs_text":"X"},"Exp-3673":{"tree":["Lval",[["Var","__cil_tmp9"],null]],"text":"__cil_tmp9","abs_text":"X"},"Exp-3754":{"tree":["OtherExp"],"text":"ptrNewfile+1","abs_text":"X+C"},"Exp-3640":{"tree":["Lval",[["Var","lines"],null]],"text":"lines","abs_text":"X"},"Exp-3824":{"tree":["OtherExp"],"text":"!(*@ptrtag.genre<@genre_count)","abs_text":"!X<X"},"Exp-3961":{"tree":["OtherExp"],"text":"!(*tag.genre<@genre_count)","abs_text":"!X<X"},"Exp-3707":{"tree":["Lval",[["Var","__cil_tmp3"],null]],"text":"__cil_tmp3","abs_text":"X"},"Exp-3602":{"tree":["Lval",[["Var","path"],null]],"text":"path","abs_text":"X"},"Exp-3361":{"tree":["Const",0],"text":"1","abs_text":"C"},"Exp-3762":{"tree":["Lval",[["Var","__cil_tmp11"],null]],"text":"__cil_tmp11","abs_text":"X"},"Exp-3566":{"tree":["Lval",[["Var","check_num_args"],null]],"text":"@check_num_args","abs_text":"X"},"Exp-3776":{"tree":["OtherExp"],"text":"tcount+1","abs_text":"X+C"},"Exp-3371":{"tree":["Lval",[["Var","resize_tag_field"],null]],"text":"@resize_tag_field","abs_text":"X"},"Exp-3955":{"tree":["OtherExp"],"text":"SizeOfE(*tag.artist)-1UL","abs_text":"SizeOf-C"},"Exp-4001":{"tree":["OtherExp"],"text":"SizeOfE(*tag.artist)-1UL","abs_text":"SizeOf-C"},"Exp-3720":{"tree":["OtherExp"],"text":"argv+0","abs_text":"X+C"},"Exp-3467":{"tree":["Lval",[["Var","id3_write_file"],null]],"text":"@id3_write_file","abs_text":"X"},"Exp-3558":{"tree":["OtherExp"],"text":"StartOf(second)","abs_text":"X"},"Exp-3883":{"tree":["OtherExp"],"text":"!(*p2!=61)","abs_text":"!X!=C"},"Exp-3636":{"tree":["Lval",[["Var","fp"],null]],"text":"fp","abs_text":"X"},"Exp-3903":{"tree":["Lval",[["Var","__cil_tmp17"],null]],"text":"__cil_tmp17","abs_text":"X"},"Exp-3925":{"tree":["OtherExp"],"text":"@filename_template[tcount]==115","abs_text":"X==C"},"Exp-3384":{"tree":["Lval",[["Var","get_term_lines"],null]],"text":"@get_term_lines","abs_text":"X"},"Exp-3495":{"tree":["Lval",[["Var","check_arg"],null]],"text":"@check_arg","abs_text":"X"},"Exp-3842":{"tree":["Lval",[["Var","__cil_tmp18"],null]],"text":"__cil_tmp18","abs_text":"X"},"Exp-3823":{"tree":["Lval",[["Var","ask_tag"],null]],"text":"@ask_tag","abs_text":"X"},"Exp-3488":{"tree":["OtherExp"],"text":"__cil_tmp53+1UL","abs_text":"X+C"},"Exp-3509":{"tree":["Lval",[["Var","id3_write_tag"],null]],"text":"@id3_write_tag","abs_text":"X"},"Exp-3648":{"tree":["OtherExp"],"text":"field+i","abs_text":"X+X"},"Exp-3469":{"tree":["Lval",[["Var","tag"],null]],"text":"tag","abs_text":"X"},"Exp-3904":{"tree":["Lval",[["Var","__cil_tmp127"],null]],"text":"__cil_tmp127","abs_text":"X"},"Exp-3405":{"tree":["Lval",[["Var","check_option"],null]],"text":"@check_option","abs_text":"X"},"Exp-3882":{"tree":["Lval",[["Var","tag_file"],null]],"text":"@tag_file","abs_text":"X"},"Exp-3445":{"tree":["Lval",[["Var","stdin"],null]],"text":"@stdin","abs_text":"stdin"},"Exp-3611":{"tree":["OtherExp"],"text":"StartOf(*@ptrtag.tag)","abs_text":"X"},"Exp-3696":{"tree":["Lval",[["Var","__cil_tmp8"],null]],"text":"__cil_tmp8","abs_text":"X"},"Exp-3931":{"tree":["OtherExp"],"text":"StartOf(*tag.tag)","abs_text":"X"},"Exp-3722":{"tree":["OtherExp"],"text":"__cil_tmp16-__cil_tmp17","abs_text":"X-X"},"Exp-3973":{"tree":["OtherExp"],"text":"!(*p2==61)","abs_text":"!X==C"},"Exp-3580":{"tree":["Const",0],"text":"103","abs_text":"C"},"Exp-3839":{"tree":["OtherExp"],"text":"StartOf(first)","abs_text":"X"},"Exp-3358":{"tree":["Lval",[["Var","ptrtag"],null]],"text":"@ptrtag","abs_text":"X"},"Exp-3828":{"tree":["OtherExp"],"text":"&*@ptrtag.genre","abs_text":"&X"},"Exp-3935":{"tree":["OtherExp"],"text":"0!=@def_field","abs_text":"C!=X"},"Exp-3610":{"tree":["Lval",[["Var","id3_read_file"],null]],"text":"@id3_read_file","abs_text":"X"},"Exp-3944":{"tree":["Lval",[["Var","__cil_tmp2"],null]],"text":"__cil_tmp2","abs_text":"X"},"Exp-3505":{"tree":["Lval",[["Var","__cil_tmp51"],null]],"text":"__cil_tmp51","abs_text":"X"},"Exp-3381":{"tree":["Lval",[["Var","__cil_tmp123"],null]],"text":"__cil_tmp123","abs_text":"X"},"Exp-3391":{"tree":["Lval",[["Mem",["Lval",[["Var","ptrtag"],null]]],["Field","album",null]]],"text":"*@ptrtag.album","abs_text":"X"},"Exp-3738":{"tree":["OtherExp"],"text":"*genre>=0","abs_text":"X>=C"},"Exp-3780":{"tree":["Lval",[["Mem",["Lval",[["Var","tag"],null]]],["Field","album",null]]],"text":"*tag.album","abs_text":"X"},"Exp-3851":{"tree":["Lval",[["Mem",["Lval",[["Var","tag"],null]]],["Field","album",null]]],"text":"*tag.album","abs_text":"X"},"Exp-3404":{"tree":["Lval",[["Var","i"],null]],"text":"i","abs_text":"X"},"Exp-3414":{"tree":["Lval",[["Mem",["Lval",[["Var","p1"],null]]],null]],"text":"*p1","abs_text":"X"},"Exp-3576":{"tree":["OtherExp"],"text":"*p2!=0","abs_text":"X!=C"},"Exp-3977":{"tree":["Lval",[["Var","arg1"],null]],"text":"arg1","abs_text":"X"},"Exp-4020":{"tree":["Lval",[["Var","d"],null]],"text":"d","abs_text":"X"},"Exp-3886":{"tree":["OtherExp"],"text":"__cil_tmp67+1UL","abs_text":"X+C"},"Exp-3976":{"tree":["Lval",[["Var","strchr"],null]],"text":"@strchr","abs_text":"strchr"},"Exp-3926":{"tree":["Const",0],"text":"115","abs_text":"C"},"Exp-3999":{"tree":["Lval",[["Var","fn"],null]],"text":"fn","abs_text":"X"},"Exp-3583":{"tree":["Lval",[["Var","__cil_tmp44"],null]],"text":"__cil_tmp44","abs_text":"X"},"Exp-3899":{"tree":["Lval",[["Var","__cil_tmp16"],null]],"text":"__cil_tmp16","abs_text":"X"},"Exp-3365":{"tree":["Lval",[["Var","strlen"],null]],"text":"@strlen","abs_text":"strlen"},"Exp-3481":{"tree":["Lval",[["Var","alloc_string"],null]],"text":"@alloc_string","abs_text":"X"},"Exp-3663":{"tree":["OtherExp"],"text":"*p1!=35","abs_text":"X!=C"},"Exp-3972":{"tree":["Lval",[["Var","__cil_tmp94"],null]],"text":"__cil_tmp94","abs_text":"X"},"Exp-3480":{"tree":["Lval",[["Var","__cil_tmp55"],null]],"text":"__cil_tmp55","abs_text":"X"},"Exp-3422":{"tree":["Lval",[["Var","string"],null]],"text":"string","abs_text":"X"},"Exp-3379":{"tree":["OtherExp"],"text":"&@copyfp","abs_text":"&X"},"Exp-3409":{"tree":["Lval",[["Var","__cil_tmp119"],null]],"text":"__cil_tmp119","abs_text":"X"},"Exp-3729":{"tree":["OtherExp"],"text":"!(!(i<@genre_count))","abs_text":"!!X<X"},"Exp-3766":{"tree":["OtherExp"],"text":"!(!(i<__cil_tmp3))","abs_text":"!!X<X"},"Exp-3992":{"tree":["Lval",[["Var","__cil_tmp6"],null]],"text":"__cil_tmp6","abs_text":"X"},"Exp-4016":{"tree":["OtherExp"],"text":"!(!(i<__cil_tmp17))","abs_text":"!!X<X"},"Exp-3534":{"tree":["Lval",[["Mem",["Lval",[["Var","ptrtag"],null]]],["Field","songname",null]]],"text":"*@ptrtag.songname","abs_text":"X"},"Exp-3792":{"tree":["Lval",[["Mem",["Lval",[["Var","tag"],null]]],["Field","songname",null]]],"text":"*tag.songname","abs_text":"X"},"Exp-3805":{"tree":["Lval",[["Mem",["Lval",[["Var","tag"],null]]],["Field","songname",null]]],"text":"*tag.songname","abs_text":"X"},"Exp-3980":{"tree":["Lval",[["Var","__cil_tmp8"],null]],"text":"__cil_tmp8","abs_text":"X"},"Exp-3519":{"tree":["Lval",[["Var","fp"],null]],"text":"fp","abs_text":"X"},"Exp-4009":{"tree":["Lval",[["Var","__cil_tmp95"],null]],"text":"__cil_tmp95","abs_text":"X"},"Exp-4013":{"tree":["OtherExp"],"text":"!(@filename_template[tcount]==115)","abs_text":"!X==C"},"Exp-3830":{"tree":["OtherExp"],"text":"&@def_song","abs_text":"&X"},"Exp-3410":{"tree":["OtherExp"],"text":"&option","abs_text":"&X"},"Exp-3920":{"tree":["Lval",[["Var","__cil_tmp73"],null]],"text":"__cil_tmp73","abs_text":"X"},"Exp-3951":{"tree":["Lval",[["Var","__cil_tmp22"],null]],"text":"__cil_tmp22","abs_text":"X"},"Exp-3906":{"tree":["OtherExp"],"text":"StartOf(@filename_template)","abs_text":"X"},"Exp-3521":{"tree":["Lval",[["Var","option"],null]],"text":"option","abs_text":"X"},"Exp-3428":{"tree":["Lval",[["Var","genre_count"],null]],"text":"@genre_count","abs_text":"X"},"Exp-3592":{"tree":["Lval",[["Var","__cil_tmp12"],null]],"text":"__cil_tmp12","abs_text":"X"},"Exp-3598":{"tree":["Lval",[["Var","__cil_tmp56"],null]],"text":"__cil_tmp56","abs_text":"X"},"Exp-3508":{"tree":["Lval",[["Var","__cil_tmp76"],null]],"text":"__cil_tmp76","abs_text":"X"},"Exp-3453":{"tree":["Lval",[["Var","__cil_tmp8"],null]],"text":"__cil_tmp8","abs_text":"X"},"Exp-3482":{"tree":["OtherExp"],"text":"&@def_comment","abs_text":"&X"},"Exp-3425":{"tree":["OtherExp"],"text":"*tag.genre<@genre_count","abs_text":"X<X"},"Exp-3825":{"tree":["OtherExp"],"text":"*@ptrtag.genre<@genre_count","abs_text":"X<X"},"Exp-3609":{"tree":["Const",0],"text":"116","abs_text":"C"},"Exp-3965":{"tree":["Lval",[["Var","__cil_tmp118"],null]],"text":"__cil_tmp118","abs_text":"X"},"Exp-3457":{"tree":["Lval",[["Var","def_field"],null]],"text":"@def_field","abs_text":"X"},"Exp-3546":{"tree":["OtherExp"],"text":"SizeOfE(*@ptrtag.artist)","abs_text":"SizeOf"},"Exp-3658":{"tree":["OtherExp"],"text":"StartOf(buf)","abs_text":"X"},"Exp-3902":{"tree":["Lval",[["Var","__cil_tmp113"],null]],"text":"__cil_tmp113","abs_text":"X"},"Exp-3956":{"tree":["OtherExp"],"text":"SizeOfE(*tag.artist)","abs_text":"SizeOf"},"Exp-4002":{"tree":["OtherExp"],"text":"SizeOfE(*tag.artist)","abs_text":"SizeOf"},"Exp-3746":{"tree":["Lval",[["Var","__cil_tmp38"],null]],"text":"__cil_tmp38","abs_text":"X"},"Exp-3565":{"tree":["OtherExp"],"text":"*p2!=32","abs_text":"X!=C"},"Exp-3734":{"tree":["OtherExp"],"text":"SizeOfE(buffer)","abs_text":"SizeOf"},"Exp-3837":{"tree":["OtherExp"],"text":"&i","abs_text":"&X"},"Exp-3375":{"tree":["Lval",[["Var","fn"],null]],"text":"fn","abs_text":"X"},"Exp-3412":{"tree":["OtherExp"],"text":"!(*p1==32)","abs_text":"!X==C"},"Exp-3448":{"tree":["Lval",[["Var","atoi"],null]],"text":"@atoi","abs_text":"atoi"},"Exp-3694":{"tree":["OtherExp"],"text":"!(*p2==32)","abs_text":"!X==C"},"Exp-3812":{"tree":["OtherExp"],"text":"!(*genre<@genre_count)","abs_text":"!X<X"},"Exp-3492":{"tree":["Lval",[["Var","__cil_tmp49"],null]],"text":"__cil_tmp49","abs_text":"X"},"Exp-3615":{"tree":["Lval",[["Var","read_config"],null]],"text":"@read_config","abs_text":"X"},"Exp-3681":{"tree":["Lval",[["Var","__cil_tmp15"],null]],"text":"__cil_tmp15","abs_text":"X"},"Exp-3620":{"tree":["Lval",[["Var","__cil_tmp102"],null]],"text":"__cil_tmp102","abs_text":"X"},"Exp-3877":{"tree":["Lval",[["Var","__cil_tmp135"],null]],"text":"__cil_tmp135","abs_text":"X"},"Exp-3918":{"tree":["Lval",[["Var","__cil_tmp134"],null]],"text":"__cil_tmp134","abs_text":"X"},"Exp-3621":{"tree":["Lval",[["Var","__cil_tmp87"],null]],"text":"__cil_tmp87","abs_text":"X"},"Exp-3626":{"tree":["Lval",[["Var","apply_template"],null]],"text":"@apply_template","abs_text":"X"},"Exp-3661":{"tree":["Lval",[["Var","__cil_tmp139"],null]],"text":"__cil_tmp139","abs_text":"X"},"Exp-3433":{"tree":["OtherExp"],"text":"ptrNewfile+__cil_tmp14","abs_text":"X+X"},"Exp-3676":{"tree":["OtherExp"],"text":"ptrNewfile+__cil_tmp25","abs_text":"X+X"},"Exp-3740":{"tree":["Lval",[["Var","f"],null]],"text":"f","abs_text":"X"},"Exp-3953":{"tree":["Lval",[["Var","__cil_tmp40"],null]],"text":"__cil_tmp40","abs_text":"X"},"Exp-3366":{"tree":["OtherExp"],"text":"StartOf(buffer)","abs_text":"X"},"Exp-3856":{"tree":["OtherExp"],"text":"__cil_tmp7-1UL","abs_text":"X-C"},"Exp-3909":{"tree":["Lval",[["Var","filename_template"],null]],"text":"@filename_template","abs_text":"X"},"Exp-3968":{"tree":["Lval",[["Var","__cil_tmp131"],null]],"text":"__cil_tmp131","abs_text":"X"},"Exp-3394":{"tree":["Lval",[["Var","__cil_tmp49"],null]],"text":"__cil_tmp49","abs_text":"X"},"Exp-3570":{"tree":["OtherExp"],"text":"&@def_field","abs_text":"&X"},"Exp-3896":{"tree":["OtherExp"],"text":"fp==0","abs_text":"X==C"},"Exp-3479":{"tree":["OtherExp"],"text":"StartOf(*@ptrtag.u.v11.comment)","abs_text":"X"},"Exp-3591":{"tree":["OtherExp"],"text":"StartOf(*tag.u.v10.comment)","abs_text":"X"},"Exp-3750":{"tree":["OtherExp"],"text":"StartOf(*tag.u.v10.comment)","abs_text":"X"},"Exp-3863":{"tree":["OtherExp"],"text":"StartOf(*@ptrtag.u.v10.comment)","abs_text":"X"},"Exp-3979":{"tree":["Lval",[["Var","__cil_tmp80"],null]],"text":"__cil_tmp80","abs_text":"X"},"Exp-3983":{"tree":["OtherExp"],"text":"StartOf(*tag.u.v10.comment)","abs_text":"X"},"Exp-3975":{"tree":["Lval",[["Var","__cil_tmp26"],null]],"text":"__cil_tmp26","abs_text":"X"},"Exp-3551":{"tree":["Lval",[["Mem",["OtherExp"]],null]],"text":"*(argv+(i+1))","abs_text":"X"},"Exp-3859":{"tree":["Lval",[["Var","fgetc"],null]],"text":"@fgetc","abs_text":"fgetc"},"Exp-3582":{"tree":["Lval",[["Var","def_song"],null]],"text":"@def_song","abs_text":"X"},"Exp-3745":{"tree":["Lval",[["Var","__cil_tmp130"],null]],"text":"__cil_tmp130","abs_text":"X"},"Exp-3514":{"tree":["Lval",[["Var","__cil_tmp25"],null]],"text":"__cil_tmp25","abs_text":"X"},"Exp-3683":{"tree":["OtherExp"],"text":"buffer[__cil_tmp21-1UL]==10","abs_text":"X==C"},"Exp-3698":{"tree":["OtherExp"],"text":"buffer[__cil_tmp6-1UL]==10","abs_text":"X==C"},"Exp-3594":{"tree":["OtherExp"],"text":"*p2==39","abs_text":"X==C"},"Exp-3654":{"tree":["Lval",[["Var","add_to_log"],null]],"text":"@add_to_log","abs_text":"X"},"Exp-3801":{"tree":["Lval",[["Var","__cil_tmp116"],null]],"text":"__cil_tmp116","abs_text":"X"},"Exp-3449":{"tree":["Lval",[["Var","__cil_tmp20"],null]],"text":"__cil_tmp20","abs_text":"X"},"Exp-3672":{"tree":["Lval",[["Var","filename"],null]],"text":"filename","abs_text":"X"},"Exp-3628":{"tree":["Lval",[["Var","__cil_tmp7"],null]],"text":"__cil_tmp7","abs_text":"X"},"Exp-3538":{"tree":["Lval",[["Var","argc"],null]],"text":"argc","abs_text":"X"},"Exp-3408":{"tree":["Lval",[["Var","arg2"],null]],"text":"arg2","abs_text":"X"},"Exp-3599":{"tree":["Lval",[["Var","fn"],null]],"text":"fn","abs_text":"X"},"Exp-3578":{"tree":["Lval",[["Var","fn"],null]],"text":"fn","abs_text":"X"},"Exp-3945":{"tree":["Lval",[["Var","__cil_tmp3"],null]],"text":"__cil_tmp3","abs_text":"X"},"Exp-3377":{"tree":["OtherExp"],"text":"StartOf(@copytag.album)","abs_text":"X"},"Exp-3593":{"tree":["OtherExp"],"text":"StartOf(@copytag.year)","abs_text":"X"},"Exp-3606":{"tree":["Const",0],"text":"\\'_\\'","abs_text":"C"},"Exp-3624":{"tree":["OtherExp"],"text":"StartOf(@copytag.artist)","abs_text":"X"},"Exp-3749":{"tree":["OtherExp"],"text":"StartOf(@copytag.songname)","abs_text":"X"},"Exp-3818":{"tree":["OtherExp"],"text":"StartOf(@copytag.tag)","abs_text":"X"},"Exp-3728":{"tree":["Lval",[["Var","mode"],null]],"text":"mode","abs_text":"X"},"Exp-4006":{"tree":["OtherExp"],"text":"digit>=0","abs_text":"X>=C"},"Exp-3703":{"tree":["Lval",[["Var","i"],null]],"text":"i","abs_text":"X"},"Exp-3930":{"tree":["OtherExp"],"text":"digit<@genre_count","abs_text":"X<X"},"Exp-3417":{"tree":["OtherExp"],"text":"&fp","abs_text":"&X"},"Exp-4004":{"tree":["Lval",[["Var","__cil_tmp8"],null]],"text":"__cil_tmp8","abs_text":"X"},"Exp-3442":{"tree":["Lval",[["Var","fgets"],null]],"text":"@fgets","abs_text":"fgets"},"Exp-3561":{"tree":["OtherExp"],"text":"&fntag.genre","abs_text":"&X"},"Exp-3890":{"tree":["OtherExp"],"text":"&stmp","abs_text":"&X"},"Exp-4015":{"tree":["Lval",[["Var","__cil_tmp61"],null]],"text":"__cil_tmp61","abs_text":"X"},"Exp-4012":{"tree":["Lval",[["Var","__cil_tmp99"],null]],"text":"__cil_tmp99","abs_text":"X"},"Exp-3987":{"tree":["OtherExp"],"text":"*(*(argv+i)+0)==45","abs_text":"X==C"},"Exp-3579":{"tree":["OtherExp"],"text":"@filename_template[tcount]==103","abs_text":"X==C"},"Exp-3536":{"tree":["Lval",[["Var","__cil_tmp45"],null]],"text":"__cil_tmp45","abs_text":"X"},"Exp-3775":{"tree":["Lval",[["Var","__cil_tmp63"],null]],"text":"__cil_tmp63","abs_text":"X"},"Exp-3612":{"tree":["OtherExp"],"text":"SizeOfE(*@ptrtag.tag)-1UL","abs_text":"SizeOf-C"},"Exp-3932":{"tree":["OtherExp"],"text":"SizeOfE(*tag.tag)-1UL","abs_text":"SizeOf-C"},"Exp-3424":{"tree":["Lval",[["Var","__cil_tmp23"],null]],"text":"__cil_tmp23","abs_text":"X"},"Exp-3881":{"tree":["Lval",[["Var","__cil_tmp21"],null]],"text":"__cil_tmp21","abs_text":"X"},"Exp-3601":{"tree":["OtherExp"],"text":"path==0","abs_text":"X==C"},"Exp-3966":{"tree":["OtherExp"],"text":"def_genre___0>=0","abs_text":"X>=C"},"Exp-3436":{"tree":["Lval",[["Var","genre"],null]],"text":"genre","abs_text":"X"},"Exp-3996":{"tree":["Lval",[["Var","__cil_tmp3"],null]],"text":"__cil_tmp3","abs_text":"X"},"Exp-3396":{"tree":["Lval",[["Var","copyfp"],null]],"text":"@copyfp","abs_text":"X"},"Exp-3359":{"tree":["Const",0],"text":"0","abs_text":"C"},"Exp-3671":{"tree":["Const",0],"text":"-1","abs_text":"C"},"Exp-3919":{"tree":["OtherExp"],"text":"__cil_tmp73+1UL","abs_text":"X+C"},"Exp-3838":{"tree":["Lval",[["Var","tmp"],null]],"text":"tmp","abs_text":"X"},"Exp-3937":{"tree":["Lval",[["Var","__cil_tmp142"],null]],"text":"__cil_tmp142","abs_text":"X"},"Exp-3493":{"tree":["OtherExp"],"text":"StartOf(tempname)","abs_text":"X"},"Exp-3867":{"tree":["OtherExp"],"text":"__cil_tmp16+1","abs_text":"X+C"},"Exp-3816":{"tree":["Lval",[["Var","__cil_tmp140"],null]],"text":"__cil_tmp140","abs_text":"X"},"Exp-3419":{"tree":["Lval",[["Var","__cil_tmp4"],null]],"text":"__cil_tmp4","abs_text":"X"},"Exp-3988":{"tree":["Lval",[["Mem",["OtherExp"]],null]],"text":"*(*(argv+i)+0)","abs_text":"X"},"Exp-3486":{"tree":["Const",0],"text":"\\'\\\\000\\'","abs_text":"C"},"Exp-3719":{"tree":["Lval",[["Mem",["OtherExp"]],null]],"text":"*(argv+0)","abs_text":"X"},"Exp-3646":{"tree":["OtherExp"],"text":"!(*p2==39)","abs_text":"!X==C"},"Exp-3846":{"tree":["Lval",[["Var","__cil_tmp137"],null]],"text":"__cil_tmp137","abs_text":"X"},"Exp-3908":{"tree":["OtherExp"],"text":"SizeOfE(@filename_template)","abs_text":"SizeOf"},"Exp-3978":{"tree":["Const",0],"text":"\\'=\\'","abs_text":"C"},"Exp-3880":{"tree":["Lval",[["Var","__cil_tmp9"],null]],"text":"__cil_tmp9","abs_text":"X"},"Exp-3680":{"tree":["Lval",[["Var","__cil_tmp124"],null]],"text":"__cil_tmp124","abs_text":"X"},"Exp-3706":{"tree":["Lval",[["Var","__cil_tmp14"],null]],"text":"__cil_tmp14","abs_text":"X"},"Exp-3905":{"tree":["Lval",[["Var","__cil_tmp111"],null]],"text":"__cil_tmp111","abs_text":"X"},"Exp-3504":{"tree":["Lval",[["Var","__cil_tmp125"],null]],"text":"__cil_tmp125","abs_text":"X"},"Exp-3370":{"tree":["Const",0],"text":"\\']\\'","abs_text":"C"},"Exp-3691":{"tree":["OtherExp"],"text":"&@program_name","abs_text":"&X"},"Exp-3357":{"tree":["Lval",[["Mem",["Lval",[["Var","ptrtag"],null]]],["Field","genre",null]]],"text":"*@ptrtag.genre","abs_text":"X"},"Exp-3388":{"tree":["OtherExp"],"text":"StartOf(@applied_filename)","abs_text":"X"},"Exp-3426":{"tree":["Lval",[["Mem",["Lval",[["Var","tag"],null]]],["Field","genre",null]]],"text":"*tag.genre","abs_text":"X"},"Exp-3910":{"tree":["Lval",[["Var","__cil_tmp133"],null]],"text":"__cil_tmp133","abs_text":"X"},"Exp-3459":{"tree":["Lval",[["Var","__cil_tmp47"],null]],"text":"__cil_tmp47","abs_text":"X"},"Exp-3421":{"tree":["Lval",[["Var","__cil_tmp128"],null]],"text":"__cil_tmp128","abs_text":"X"},"Exp-3887":{"tree":["Lval",[["Var","__cil_tmp67"],null]],"text":"__cil_tmp67","abs_text":"X"},"Exp-3892":{"tree":["Lval",[["Var","__cil_tmp13"],null]],"text":"__cil_tmp13","abs_text":"X"},"Exp-3489":{"tree":["Lval",[["Var","__cil_tmp53"],null]],"text":"__cil_tmp53","abs_text":"X"},"Exp-3531":{"tree":["Lval",[["Var","filename_template"],["Index",["Lval",[["Var","tcount"],null]],null]]],"text":"@filename_template[tcount]","abs_text":"X"},"Exp-3462":{"tree":["Lval",[["Var","def_year"],null]],"text":"@def_year","abs_text":"X"},"Exp-3679":{"tree":["Const",0],"text":"99","abs_text":"C"},"Exp-3938":{"tree":["OtherExp"],"text":"&@remove_char","abs_text":"&X"},"Exp-3507":{"tree":["OtherExp"],"text":"__cil_tmp76+1UL","abs_text":"X+C"},"Exp-3939":{"tree":["OtherExp"],"text":"__cil_tmp50+1UL","abs_text":"X+C"},"Exp-3539":{"tree":["Lval",[["Var","argv"],null]],"text":"argv","abs_text":"X"},"Exp-3784":{"tree":["Lval",[["Var","__cil_tmp8"],null]],"text":"__cil_tmp8","abs_text":"X"},"Exp-3444":{"tree":["Lval",[["Var","buffer"],null]],"text":"buffer","abs_text":"X"},"Exp-3884":{"tree":["OtherExp"],"text":"*p2!=61","abs_text":"X!=C"},"Exp-3451":{"tree":["Lval",[["Var","digit"],null]],"text":"digit","abs_text":"X"},"Exp-3717":{"tree":["Lval",[["Var","__cil_tmp107"],null]],"text":"__cil_tmp107","abs_text":"X"},"Exp-3708":{"tree":["Lval",[["Var","__cil_tmp10"],null]],"text":"__cil_tmp10","abs_text":"X"},"Exp-3554":{"tree":["OtherExp"],"text":"p2+1","abs_text":"X+C"},"Exp-3397":{"tree":["Lval",[["Var","id3_read_tag"],null]],"text":"@id3_read_tag","abs_text":"X"},"Exp-3563":{"tree":["Lval",[["Var","dest"],null]],"text":"dest","abs_text":"X"},"Exp-3568":{"tree":["Lval",[["Var","count"],null]],"text":"count","abs_text":"X"},"Exp-3656":{"tree":["Lval",[["Var","__cil_tmp79"],null]],"text":"__cil_tmp79","abs_text":"X"},"Exp-3692":{"tree":["OtherExp"],"text":"__cil_tmp18+1UL","abs_text":"X+C"},"Exp-3645":{"tree":["Lval",[["Var","__cil_tmp11"],null]],"text":"__cil_tmp11","abs_text":"X"},"Exp-3378":{"tree":["Lval",[["Var","id3_open_file"],null]],"text":"@id3_open_file","abs_text":"X"},"Exp-3383":{"tree":["Lval",[["Var","sizelesstag"],null]],"text":"sizelesstag","abs_text":"X"},"Exp-3511":{"tree":["Lval",[["Var","strcat"],null]],"text":"@strcat","abs_text":"strcat"},"Exp-3686":{"tree":["Lval",[["Var","__cil_tmp21"],null]],"text":"__cil_tmp21","abs_text":"X"},"Exp-3829":{"tree":["Lval",[["Var","def_genre"],null]],"text":"@def_genre","abs_text":"X"},"Exp-3496":{"tree":["OtherExp"],"text":"&i","abs_text":"&X"},"Exp-3529":{"tree":["OtherExp"],"text":"option==0","abs_text":"X==C"},"Exp-3641":{"tree":["Lval",[["Var","__cil_tmp4"],null]],"text":"__cil_tmp4","abs_text":"X"},"Exp-3868":{"tree":["Lval",[["Var","__cil_tmp16"],null]],"text":"__cil_tmp16","abs_text":"X"},"Exp-3822":{"tree":["Lval",[["Var","__cil_tmp88"],null]],"text":"__cil_tmp88","abs_text":"X"},"Exp-3590":{"tree":["Lval",[["Var","__cil_tmp13"],null]],"text":"__cil_tmp13","abs_text":"X"},"Exp-3564":{"tree":["OtherExp"],"text":"!(*p2!=32)","abs_text":"!X!=C"},"Exp-3657":{"tree":["OtherExp"],"text":"!(@filename_template[tcount]==116)","abs_text":"!X==C"},"Exp-3747":{"tree":["Lval",[["Var","cfile"],null]],"text":"cfile","abs_text":"X"},"Exp-3440":{"tree":["Lval",[["Var","errcount"],null]],"text":"errcount","abs_text":"X"},"Exp-3989":{"tree":["OtherExp"],"text":"*(argv+i)+0","abs_text":"X+C"},"Exp-3427":{"tree":["Lval",[["Var","tag"],null]],"text":"tag","abs_text":"X"},"Exp-3782":{"tree":["OtherExp"],"text":"string+(__cil_tmp8-1UL)","abs_text":"X+X-C"},"Exp-3369":{"tree":["Lval",[["Var","i"],null]],"text":"i","abs_text":"X"},"Exp-3485":{"tree":["Lval",[["Var","p2"],null]],"text":"p2","abs_text":"X"},"Exp-3616":{"tree":["Lval",[["Var","__cil_tmp6"],null]],"text":"__cil_tmp6","abs_text":"X"},"Exp-3731":{"tree":["OtherExp"],"text":"i<@genre_count","abs_text":"X<X"},"Exp-3768":{"tree":["OtherExp"],"text":"i<__cil_tmp3","abs_text":"X<X"},"Exp-3836":{"tree":["OtherExp"],"text":"i<argc","abs_text":"X<X"},"Exp-4018":{"tree":["OtherExp"],"text":"i<__cil_tmp17","abs_text":"X<X"},"Exp-3438":{"tree":["Lval",[["Var","__cil_tmp52"],null]],"text":"__cil_tmp52","abs_text":"X"},"Exp-3464":{"tree":["Lval",[["Var","__cil_tmp50"],null]],"text":"__cil_tmp50","abs_text":"X"},"Exp-3781":{"tree":["Lval",[["Var","__cil_tmp20"],null]],"text":"__cil_tmp20","abs_text":"X"},"Exp-3741":{"tree":["Lval",[["Var","pfntmp"],null]],"text":"pfntmp","abs_text":"X"},"Exp-3537":{"tree":["Lval",[["Var","check_args"],null]],"text":"@check_args","abs_text":"X"},"Exp-4019":{"tree":["Lval",[["Var","__cil_tmp17"],null]],"text":"__cil_tmp17","abs_text":"X"},"Exp-3577":{"tree":["Lval",[["Var","__cil_tmp9"],null]],"text":"__cil_tmp9","abs_text":"X"},"Exp-3502":{"tree":["Lval",[["Var","tmp"],null]],"text":"tmp","abs_text":"X"},"Exp-3498":{"tree":["Lval",[["Mem",["OtherExp"]],null]],"text":"*(argv+i)","abs_text":"X"},"Exp-3833":{"tree":["OtherExp"],"text":"__cil_tmp13+1UL","abs_text":"X+C"},"Exp-3786":{"tree":["OtherExp"],"text":"!(!(@filename_template[tcount]!=0))","abs_text":"!!X!=C"},"Exp-3806":{"tree":["OtherExp"],"text":"!(!(tmpfile___0[tcount]!=0))","abs_text":"!!X!=C"},"Exp-3584":{"tree":["OtherExp"],"text":"!(@filename_template[tcount]==37)","abs_text":"!X==C"},"Exp-3769":{"tree":["Lval",[["Var","__cil_tmp3"],null]],"text":"__cil_tmp3","abs_text":"X"},"Exp-3810":{"tree":["Lval",[["Var","__cil_tmp22"],null]],"text":"__cil_tmp22","abs_text":"X"},"Exp-3364":{"tree":["Lval",[["Var","arg1"],null]],"text":"arg1","abs_text":"X"},"Exp-3411":{"tree":["OtherExp"],"text":"!(!(*p1==32))","abs_text":"!!X==C"},"Exp-3788":{"tree":["OtherExp"],"text":"@filename_template[tcount]!=0","abs_text":"X!=C"},"Exp-3739":{"tree":["OtherExp"],"text":"f-pfntmp","abs_text":"X-X"},"Exp-3870":{"tree":["OtherExp"],"text":"__cil_tmp75+1UL","abs_text":"X+C"},"Exp-3362":{"tree":["Lval",[["Var","__cil_tmp120"],null]],"text":"__cil_tmp120","abs_text":"X"},"Exp-3660":{"tree":["OtherExp"],"text":"StartOf(@copytag.u.v10.comment)","abs_text":"X"},"Exp-3770":{"tree":["Lval",[["Var","__cil_tmp18"],null]],"text":"__cil_tmp18","abs_text":"X"},"Exp-3682":{"tree":["Lval",[["Var","__cil_tmp16"],null]],"text":"__cil_tmp16","abs_text":"X"},"Exp-3572":{"tree":["Lval",[["Var","__cil_tmp24"],null]],"text":"__cil_tmp24","abs_text":"X"},"Exp-3783":{"tree":["OtherExp"],"text":"__cil_tmp8-1UL","abs_text":"X-C"},"Exp-3456":{"tree":["OtherExp"],"text":"@def_field!=0","abs_text":"X!=C"},"Exp-3688":{"tree":["OtherExp"],"text":"&@def_album","abs_text":"&X"},"Exp-3998":{"tree":["Lval",[["Var","__cil_tmp5"],null]],"text":"__cil_tmp5","abs_text":"X"},"Exp-3743":{"tree":["Lval",[["Var","__cil_tmp7"],null]],"text":"__cil_tmp7","abs_text":"X"},"Exp-3668":{"tree":["OtherExp"],"text":"!(*genre!=-1)","abs_text":"!X!=C"},"Exp-3759":{"tree":["OtherExp"],"text":"!(*p2!=0)","abs_text":"!X!=C"},"Exp-3866":{"tree":["OtherExp"],"text":"!(*p1!=0)","abs_text":"!X!=C"},"Exp-3461":{"tree":["Lval",[["Mem",["Lval",[["Var","ptrtag"],null]]],["Field","year",null]]],"text":"*@ptrtag.year","abs_text":"X"},"Exp-3472":{"tree":["Lval",[["Mem",["Lval",[["Var","tag"],null]]],["Field","year",null]]],"text":"*tag.year","abs_text":"X"},"Exp-3596":{"tree":["OtherExp"],"text":"fntag.genre==0","abs_text":"X==C"},"Exp-3635":{"tree":["Lval",[["Mem",["Lval",[["Var","tag"],null]]],["Field","year",null]]],"text":"*tag.year","abs_text":"X"},"Exp-3494":{"tree":["Lval",[["Var","__cil_tmp86"],null]],"text":"__cil_tmp86","abs_text":"X"},"Exp-3569":{"tree":["Lval",[["Var","argc"],null]],"text":"argc","abs_text":"X"},"Exp-3732":{"tree":["Lval",[["Var","__cil_tmp121"],null]],"text":"__cil_tmp121","abs_text":"X"},"Exp-3398":{"tree":["OtherExp"],"text":"&@copytag","abs_text":"&X"},"Exp-3922":{"tree":["Const",0],"text":"97","abs_text":"C"},"Exp-3772":{"tree":["OtherExp"],"text":"&@def_genre","abs_text":"&X"},"Exp-3643":{"tree":["OtherExp"],"text":"&@def_artist","abs_text":"&X"},"Exp-3742":{"tree":["Lval",[["Var","__cil_tmp96"],null]],"text":"__cil_tmp96","abs_text":"X"},"Exp-3632":{"tree":["Lval",[["Var","tag"],null]],"text":"tag","abs_text":"X"},"Exp-3764":{"tree":["Lval",[["Var","__cil_tmp115"],null]],"text":"__cil_tmp115","abs_text":"X"},"Exp-3847":{"tree":["Lval",[["Var","count"],null]],"text":"count","abs_text":"X"},"Exp-3574":{"tree":["Lval",[["Var","__cil_tmp82"],null]],"text":"__cil_tmp82","abs_text":"X"},"Exp-3669":{"tree":["OtherExp"],"text":"*genre!=-1","abs_text":"X!=C"},"Exp-3948":{"tree":["Lval",[["Var","__cil_tmp15"],null]],"text":"__cil_tmp15","abs_text":"X"},"Exp-3889":{"tree":["Lval",[["Var","__cil_tmp21"],null]],"text":"__cil_tmp21","abs_text":"X"},"Exp-3704":{"tree":["OtherExp"],"text":"StartOf(@replace_spacechar)","abs_text":"X"},"Exp-3629":{"tree":["Lval",[["Var","__cil_tmp23"],null]],"text":"__cil_tmp23","abs_text":"X"},"Exp-3470":{"tree":["OtherExp"],"text":"SizeOfE(*tag.year)-1UL","abs_text":"SizeOf-C"},"Exp-3633":{"tree":["OtherExp"],"text":"SizeOfE(*tag.year)-1UL","abs_text":"SizeOf-C"},"Exp-3655":{"tree":["OtherExp"],"text":"StartOf(buf)","abs_text":"X"},"Exp-3735":{"tree":["Lval",[["Var","buffer"],null]],"text":"buffer","abs_text":"X"},"Exp-3834":{"tree":["Lval",[["Var","__cil_tmp13"],null]],"text":"__cil_tmp13","abs_text":"X"},"Exp-3360":{"tree":["Lval",[["Var","user_message"],null]],"text":"@user_message","abs_text":"X"},"Exp-3936":{"tree":["Lval",[["Var","__cil_tmp112"],null]],"text":"__cil_tmp112","abs_text":"X"},"Exp-3958":{"tree":["Lval",[["Var","id3_show_tag"],null]],"text":"@id3_show_tag","abs_text":"X"},"Exp-3395":{"tree":["OtherExp"],"text":"@copyfp==0","abs_text":"X==C"},"Exp-3725":{"tree":["Lval",[["Var","fp"],null]],"text":"fp","abs_text":"X"},"Exp-3946":{"tree":["OtherExp"],"text":"p1+1","abs_text":"X+C"},"Exp-3853":{"tree":["Lval",[["Var","__cil_tmp14"],null]],"text":"__cil_tmp14","abs_text":"X"},"Exp-3586":{"tree":["Const",0],"text":"37","abs_text":"C"},"Exp-3800":{"tree":["Lval",[["Var","__cil_tmp37"],null]],"text":"__cil_tmp37","abs_text":"X"},"Exp-4005":{"tree":["Lval",[["Var","__cil_tmp78"],null]],"text":"__cil_tmp78","abs_text":"X"},"Exp-3515":{"tree":["Lval",[["Var","__cil_tmp104"],null]],"text":"__cil_tmp104","abs_text":"X"},"Exp-3894":{"tree":["Lval",[["Var","length"],null]],"text":"length","abs_text":"X"},"Exp-3844":{"tree":["Lval",[["Var","fn"],null]],"text":"fn","abs_text":"X"},"Exp-3474":{"tree":["Lval",[["Var","fp"],null]],"text":"fp","abs_text":"X"},"Exp-3736":{"tree":["Lval",[["Var","fp"],null]],"text":"fp","abs_text":"X"},"Exp-3518":{"tree":["Lval",[["Var","size"],null]],"text":"size","abs_text":"X"},"Exp-3651":{"tree":["OtherExp"],"text":"&cfile","abs_text":"&X"},"Exp-3653":{"tree":["Lval",[["Var","__cil_tmp15"],null]],"text":"__cil_tmp15","abs_text":"X"},"Exp-3774":{"tree":["OtherExp"],"text":"__cil_tmp63+1UL","abs_text":"X+C"},"Exp-3809":{"tree":["OtherExp"],"text":"!(@filename_template[tcount]==99)","abs_text":"!X==C"},"Exp-3608":{"tree":["OtherExp"],"text":"@filename_template[tcount]==116","abs_text":"X==C"},"Exp-3799":{"tree":["Lval",[["Var","__cil_tmp143"],null]],"text":"__cil_tmp143","abs_text":"X"},"Exp-4007":{"tree":["Lval",[["Var","__cil_tmp54"],null]],"text":"__cil_tmp54","abs_text":"X"},"Exp-3785":{"tree":["OtherExp"],"text":"(i+1)<argc","abs_text":"X+C<X"},"Exp-3530":{"tree":["OtherExp"],"text":"@filename_template[tcount]==110","abs_text":"X==C"},"Exp-3372":{"tree":["OtherExp"],"text":"StartOf(*@ptrtag.songname)","abs_text":"X"},"Exp-3533":{"tree":["OtherExp"],"text":"SizeOfE(*@ptrtag.songname)","abs_text":"SizeOf"},"Exp-3674":{"tree":["OtherExp"],"text":"StartOf(*tag.songname)","abs_text":"X"},"Exp-3789":{"tree":["OtherExp"],"text":"StartOf(*tag.songname)","abs_text":"X"},"Exp-3791":{"tree":["OtherExp"],"text":"SizeOfE(*tag.songname)","abs_text":"SizeOf"},"Exp-3802":{"tree":["OtherExp"],"text":"StartOf(*tag.songname)","abs_text":"X"},"Exp-3804":{"tree":["OtherExp"],"text":"SizeOfE(*tag.songname)","abs_text":"SizeOf"},"Exp-3993":{"tree":["Lval",[["Var","myname"],null]],"text":"myname","abs_text":"X"},"Exp-3387":{"tree":["OtherExp"],"text":"StartOf(arg)","abs_text":"X"},"Exp-3721":{"tree":["OtherExp"],"text":"(__cil_tmp16-__cil_tmp17)-1UL","abs_text":"X-X-C"},"Exp-3907":{"tree":["OtherExp"],"text":"SizeOfE(@filename_template)-1UL","abs_text":"SizeOf-C"},"Exp-3970":{"tree":["OtherExp"],"text":"__cil_tmp70+1UL","abs_text":"X+C"},"Exp-4014":{"tree":["OtherExp"],"text":"__cil_tmp61+1UL","abs_text":"X+C"},"Exp-3589":{"tree":["Lval",[["Var","__cil_tmp10"],null]],"text":"__cil_tmp10","abs_text":"X"},"Exp-3710":{"tree":["Lval",[["Var","__cil_tmp48"],null]],"text":"__cil_tmp48","abs_text":"X"},"Exp-3500":{"tree":["Lval",[["Var","argv"],null]],"text":"argv","abs_text":"X"},"Exp-3618":{"tree":["Lval",[["Var","program_path"],null]],"text":"@program_path","abs_text":"X"},"Exp-3827":{"tree":["Lval",[["Var","get_tag_genre"],null]],"text":"@get_tag_genre","abs_text":"X"},"Exp-3432":{"tree":["Const",0],"text":"(char)0","abs_text":"C"},"Exp-3562":{"tree":["OtherExp"],"text":"StartOf(genre)","abs_text":"X"},"Exp-3392":{"tree":["OtherExp"],"text":"StartOf(fntag.album)","abs_text":"X"},"Exp-3512":{"tree":["OtherExp"],"text":"StartOf(fntag.year)","abs_text":"X"},"Exp-3535":{"tree":["OtherExp"],"text":"StartOf(fntag.songname)","abs_text":"X"},"Exp-3555":{"tree":["OtherExp"],"text":"StartOf(fntag.artist)","abs_text":"X"},"Exp-3455":{"tree":["Lval",[["Var","__cil_tmp23"],null]],"text":"__cil_tmp23","abs_text":"X"},"Exp-3713":{"tree":["Lval",[["Var","__cil_tmp31"],null]],"text":"__cil_tmp31","abs_text":"X"},"Exp-3447":{"tree":["OtherExp"],"text":"string!=0","abs_text":"X!=C"},"Exp-3484":{"tree":["Lval",[["Var","__cil_tmp20"],null]],"text":"__cil_tmp20","abs_text":"X"},"Exp-3557":{"tree":["Lval",[["Var","strcpy"],null]],"text":"@strcpy","abs_text":"strcpy"},"Exp-3687":{"tree":["Const",0],"text":"10","abs_text":"C"},"Exp-3864":{"tree":["Lval",[["Var","__cil_tmp53"],null]],"text":"__cil_tmp53","abs_text":"X"},"Exp-3548":{"tree":["Lval",[["Var","def_artist"],null]],"text":"@def_artist","abs_text":"X"},"Exp-3587":{"tree":["Lval",[["Var","replace_char"],null]],"text":"@replace_char","abs_text":"X"},"Exp-3644":{"tree":["OtherExp"],"text":"__cil_tmp11+1UL","abs_text":"X+C"},"Exp-3627":{"tree":["Lval",[["Var","__cil_tmp45"],null]],"text":"__cil_tmp45","abs_text":"X"},"Exp-3497":{"tree":["Lval",[["Var","argc"],null]],"text":"argc","abs_text":"X"},"Exp-3787":{"tree":["OtherExp"],"text":"!(@filename_template[tcount]!=0)","abs_text":"!X!=C"},"Exp-3807":{"tree":["OtherExp"],"text":"!(tmpfile___0[tcount]!=0)","abs_text":"!X!=C"},"Exp-3891":{"tree":["OtherExp"],"text":"__cil_tmp13+2UL","abs_text":"X+C"},"Exp-3401":{"tree":["Lval",[["Var","i"],null]],"text":"i","abs_text":"X"},"Exp-3545":{"tree":["Lval",[["Var","fp"],null]],"text":"fp","abs_text":"X"},"Exp-3855":{"tree":["Lval",[["Var","__cil_tmp19"],null]],"text":"__cil_tmp19","abs_text":"X"},"Exp-3393":{"tree":["OtherExp"],"text":"StartOf(*@ptrtag.album)","abs_text":"X"},"Exp-3763":{"tree":["OtherExp"],"text":"StartOf(*tag.album)","abs_text":"X"},"Exp-3777":{"tree":["OtherExp"],"text":"StartOf(*tag.album)","abs_text":"X"},"Exp-3848":{"tree":["OtherExp"],"text":"StartOf(*tag.album)","abs_text":"X"},"Exp-3525":{"tree":["Lval",[["Mem",["Lval",[["Var","p2"],null]]],null]],"text":"*p2","abs_text":"X"},"Exp-3604":{"tree":["OtherExp"],"text":"@filename_template[tcount]==121","abs_text":"X==C"},"Exp-3716":{"tree":["Lval",[["Var","i"],null]],"text":"i","abs_text":"X"},"Exp-3376":{"tree":["Lval",[["Var","__cil_tmp24"],null]],"text":"__cil_tmp24","abs_text":"X"},"Exp-3917":{"tree":["Lval",[["Var","remove_char"],null]],"text":"@remove_char","abs_text":"X"},"Exp-3390":{"tree":["OtherExp"],"text":"SizeOfE(*@ptrtag.album)","abs_text":"SizeOf"},"Exp-3779":{"tree":["OtherExp"],"text":"SizeOfE(*tag.album)","abs_text":"SizeOf"},"Exp-3850":{"tree":["OtherExp"],"text":"SizeOfE(*tag.album)","abs_text":"SizeOf"},"Exp-3857":{"tree":["Lval",[["Var","__cil_tmp7"],null]],"text":"__cil_tmp7","abs_text":"X"},"Exp-3420":{"tree":["Lval",[["Var","__cil_tmp132"],null]],"text":"__cil_tmp132","abs_text":"X"},"Exp-3819":{"tree":["OtherExp"],"text":"SizeOfE(@copytag.tag)-1UL","abs_text":"SizeOf-C"},"Exp-3501":{"tree":["Lval",[["Var","i"],null]],"text":"i","abs_text":"X"},"Exp-3637":{"tree":["Lval",[["Var","fn"],null]],"text":"fn","abs_text":"X"},"Exp-3517":{"tree":["Lval",[["Var","dest"],null]],"text":"dest","abs_text":"X"},"Exp-3748":{"tree":["Lval",[["Var","def_genre___0"],null]],"text":"def_genre___0","abs_text":"X"},"Exp-3912":{"tree":["OtherExp"],"text":"__cil_tmp22-1UL","abs_text":"X-C"},"Exp-3927":{"tree":["Lval",[["Var","__cil_tmp3"],null]],"text":"__cil_tmp3","abs_text":"X"},"Exp-3726":{"tree":["Lval",[["Var","fopen"],null]],"text":"@fopen","abs_text":"fopen"},"Exp-3929":{"tree":["Lval",[["Var","__cil_tmp77"],null]],"text":"__cil_tmp77","abs_text":"X"},"Exp-3893":{"tree":["Const",0],"text":"2UL","abs_text":"C"},"Exp-3429":{"tree":["Lval",[["Var","ptrNewfile"],null]],"text":"ptrNewfile","abs_text":"X"},"Exp-3652":{"tree":["OtherExp"],"text":"__cil_tmp15+1UL","abs_text":"X+C"},"Exp-3947":{"tree":["OtherExp"],"text":"__cil_tmp15+1UL","abs_text":"X+C"},"Exp-3962":{"tree":["Lval",[["Var","__cil_tmp12"],null]],"text":"__cil_tmp12","abs_text":"X"},"Exp-3506":{"tree":["OtherExp"],"text":"&@def_year","abs_text":"&X"},"Exp-3434":{"tree":["Lval",[["Var","__cil_tmp14"],null]],"text":"__cil_tmp14","abs_text":"X"},"Exp-3483":{"tree":["OtherExp"],"text":"__cil_tmp20+1UL","abs_text":"X+C"},"Exp-3526":{"tree":["Const",0],"text":"34","abs_text":"C"},"Exp-3982":{"tree":["Lval",[["Var","__cil_tmp34"],null]],"text":"__cil_tmp34","abs_text":"X"},"Exp-3540":{"tree":["Lval",[["Var","__cil_tmp4"],null]],"text":"__cil_tmp4","abs_text":"X"},"Exp-3614":{"tree":["Lval",[["Mem",["Lval",[["Var","ptrtag"],null]]],["Field","tag",null]]],"text":"*@ptrtag.tag","abs_text":"X"},"Exp-3934":{"tree":["Lval",[["Mem",["Lval",[["Var","tag"],null]]],["Field","tag",null]]],"text":"*tag.tag","abs_text":"X"},"Exp-3995":{"tree":["Lval",[["Var","dest"],null]],"text":"dest","abs_text":"X"},"Exp-3714":{"tree":["OtherExp"],"text":"!(fntag.genre==0)","abs_text":"!X==C"},"Exp-3709":{"tree":["Lval",[["Var","def_album"],null]],"text":"@def_album","abs_text":"X"},"Exp-3874":{"tree":["OtherExp"],"text":"!(*genre>=0)","abs_text":"!X>=C"},"Exp-3950":{"tree":["Lval",[["Var","__cil_tmp11"],null]],"text":"__cil_tmp11","abs_text":"X"},"Exp-3439":{"tree":["Lval",[["Var","count"],null]],"text":"count","abs_text":"X"},"Exp-3607":{"tree":["Lval",[["Var","__cil_tmp106"],null]],"text":"__cil_tmp106","abs_text":"X"},"Exp-4010":{"tree":["Lval",[["Var","__cil_tmp14"],null]],"text":"__cil_tmp14","abs_text":"X"},"Exp-3441":{"tree":["OtherExp"],"text":"count+errcount","abs_text":"X+X"},"Exp-3550":{"tree":["Lval",[["Var","__cil_tmp46"],null]],"text":"__cil_tmp46","abs_text":"X"},"Exp-3490":{"tree":["OtherExp"],"text":"!(tmpfile___0[tcount]==32)","abs_text":"!X==C"},"Exp-3659":{"tree":["Lval",[["Var","def_comment"],null]],"text":"@def_comment","abs_text":"X"},"Exp-3737":{"tree":["Lval",[["Var","tmp___5"],null]],"text":"tmp___5","abs_text":"X"},"Exp-3869":{"tree":["Lval",[["Var","__cil_tmp5"],null]],"text":"__cil_tmp5","abs_text":"X"},"Exp-3477":{"tree":["Lval",[["Mem",["Lval",[["Var","ptrtag"],null]]],["Field","u",["Field","v11",["Field","comment",null]]]]],"text":"*@ptrtag.u.v11.comment","abs_text":"X"},"Exp-3667":{"tree":["Lval",[["Var","__cil_tmp93"],null]],"text":"__cil_tmp93","abs_text":"X"},"Exp-3753":{"tree":["Lval",[["Mem",["Lval",[["Var","tag"],null]]],["Field","u",["Field","v10",["Field","comment",null]]]]],"text":"*tag.u.v10.comment","abs_text":"X"},"Exp-3861":{"tree":["Lval",[["Mem",["Lval",[["Var","ptrtag"],null]]],["Field","u",["Field","v10",["Field","comment",null]]]]],"text":"*@ptrtag.u.v10.comment","abs_text":"X"},"Exp-3986":{"tree":["Lval",[["Mem",["Lval",[["Var","tag"],null]]],["Field","u",["Field","v10",["Field","comment",null]]]]],"text":"*tag.u.v10.comment","abs_text":"X"},"Exp-4011":{"tree":["Lval",[["Mem",["Lval",[["Var","tag"],null]]],["Field","u",["Field","v11",["Field","track",null]]]]],"text":"*tag.u.v11.track","abs_text":"X"},"Exp-3690":{"tree":["Lval",[["Var","__cil_tmp65"],null]],"text":"__cil_tmp65","abs_text":"X"},"Exp-3407":{"tree":["Lval",[["Var","argc"],null]],"text":"argc","abs_text":"X"},"Exp-3817":{"tree":["OtherExp"],"text":"!((i+1)<argc)","abs_text":"!X+C<X"},"Exp-3516":{"tree":["Lval",[["Var","fread"],null]],"text":"@fread","abs_text":"fread"},"Exp-3727":{"tree":["Lval",[["Var","fn"],null]],"text":"fn","abs_text":"X"},"Exp-3403":{"tree":["OtherExp"],"text":"i-1","abs_text":"X-C"},"Exp-3380":{"tree":["Lval",[["Var","option"],null]],"text":"option","abs_text":"X"},"Exp-3875":{"tree":["Lval",[["Var","__cil_tmp105"],null]],"text":"__cil_tmp105","abs_text":"X"},"Exp-3900":{"tree":["Lval",[["Var","__cil_tmp17"],null]],"text":"__cil_tmp17","abs_text":"X"},"Exp-3773":{"tree":["Lval",[["Var","__cil_tmp15"],null]],"text":"__cil_tmp15","abs_text":"X"},"Exp-3971":{"tree":["Lval",[["Var","__cil_tmp70"],null]],"text":"__cil_tmp70","abs_text":"X"},"Exp-3552":{"tree":["OtherExp"],"text":"argv+(i+1)","abs_text":"X+X+C"},"Exp-3385":{"tree":["Const",0],"text":"\\'-\\'","abs_text":"C"},"Exp-3374":{"tree":["Lval",[["Var","__cil_tmp27"],null]],"text":"__cil_tmp27","abs_text":"X"},"Exp-3402":{"tree":["Lval",[["Var","search_gen"],null]],"text":"search_gen","abs_text":"X"},"Exp-3841":{"tree":["OtherExp"],"text":"StartOf(tmpfile___0)","abs_text":"X"},"Exp-3923":{"tree":["Lval",[["Var","__cil_tmp10"],null]],"text":"__cil_tmp10","abs_text":"X"},"Exp-3921":{"tree":["OtherExp"],"text":"@filename_template[tcount]==97","abs_text":"X==C"},"Exp-3373":{"tree":["Const",0],"text":"\\'[\\'","abs_text":"C"},"Exp-3790":{"tree":["OtherExp"],"text":"SizeOfE(*tag.songname)-1UL","abs_text":"SizeOf-C"},"Exp-3803":{"tree":["OtherExp"],"text":"SizeOfE(*tag.songname)-1UL","abs_text":"SizeOf-C"},"Exp-3873":{"tree":["Lval",[["Var","name"],null]],"text":"name","abs_text":"X"},"Exp-3960":{"tree":["OtherExp"],"text":"!(0!=@def_field)","abs_text":"!C!=X"},"Exp-3437":{"tree":["Lval",[["Var","__cil_tmp28"],null]],"text":"__cil_tmp28","abs_text":"X"},"Exp-3795":{"tree":["Lval",[["Var","__cil_tmp36"],null]],"text":"__cil_tmp36","abs_text":"X"},"Exp-3532":{"tree":["Const",0],"text":"110","abs_text":"C"},"Exp-3677":{"tree":["Lval",[["Var","__cil_tmp25"],null]],"text":"__cil_tmp25","abs_text":"X"},"Exp-3771":{"tree":["Lval",[["Var","show_genres"],null]],"text":"@show_genres","abs_text":"X"},"Exp-3639":{"tree":["Lval",[["Var","__cil_tmp110"],null]],"text":"__cil_tmp110","abs_text":"X"},"Exp-3423":{"tree":["OtherExp"],"text":"&fp","abs_text":"&X"},"Exp-3798":{"tree":["OtherExp"],"text":"def_genre___0<@genre_count","abs_text":"X<X"},"Exp-3820":{"tree":["OtherExp"],"text":"SizeOfE(@copytag.tag)","abs_text":"SizeOf"},"Exp-3718":{"tree":["Lval",[["Var","strncpy"],null]],"text":"@strncpy","abs_text":"strncpy"},"Exp-4023":{"tree":["OtherExp"],"text":"@replace_char+(i+1)","abs_text":"X+X+C"},"Exp-3760":{"tree":["OtherExp"],"text":"StartOf(fntmp)","abs_text":"X"},"Exp-3778":{"tree":["OtherExp"],"text":"SizeOfE(*tag.album)-1UL","abs_text":"SizeOf-C"},"Exp-3849":{"tree":["OtherExp"],"text":"SizeOfE(*tag.album)-1UL","abs_text":"SizeOf-C"},"Exp-4021":{"tree":["Const",0],"text":"\\'/\\'","abs_text":"C"},"Exp-3356":{"tree":["OtherExp"],"text":"*@ptrtag.genre>=0","abs_text":"X>=C"},"Exp-3575":{"tree":["OtherExp"],"text":"*tag.genre>=0","abs_text":"X>=C"},"Exp-3630":{"tree":["Const",0],"text":"\\'%\\'","abs_text":"C"},"Exp-3702":{"tree":["OtherExp"],"text":"i+2","abs_text":"X+C"},"Exp-3685":{"tree":["OtherExp"],"text":"__cil_tmp21-1UL","abs_text":"X-C"},"Exp-3622":{"tree":["OtherExp"],"text":"&fp","abs_text":"&X"},"Exp-3605":{"tree":["Const",0],"text":"121","abs_text":"C"},"Exp-3756":{"tree":["Lval",[["Var","__cil_tmp83"],null]],"text":"__cil_tmp83","abs_text":"X"},"Exp-3454":{"tree":["Lval",[["Var","fn"],null]],"text":"fn","abs_text":"X"},"Exp-3793":{"tree":["Lval",[["Var","__cil_tmp108"],null]],"text":"__cil_tmp108","abs_text":"X"},"Exp-3619":{"tree":["Lval",[["Var","__cil_tmp44"],null]],"text":"__cil_tmp44","abs_text":"X"},"Exp-3758":{"tree":["OtherExp"],"text":"!(!(*p2!=0))","abs_text":"!!X!=C"},"Exp-3915":{"tree":["OtherExp"],"text":"*count+1","abs_text":"X+C"},"Exp-3613":{"tree":["OtherExp"],"text":"SizeOfE(*@ptrtag.tag)","abs_text":"SizeOf"},"Exp-3649":{"tree":["Lval",[["Var","field"],null]],"text":"field","abs_text":"X"},"Exp-3840":{"tree":["Lval",[["Var","tmp___0"],null]],"text":"tmp___0","abs_text":"X"},"Exp-3933":{"tree":["OtherExp"],"text":"SizeOfE(*tag.tag)","abs_text":"SizeOf"},"Exp-3443":{"tree":["OtherExp"],"text":"SizeOfE(buffer)","abs_text":"SizeOf"},"Exp-3446":{"tree":["OtherExp"],"text":"!(string!=0)","abs_text":"!X!=C"},"Exp-3542":{"tree":["OtherExp"],"text":"!(@def_field!=0)","abs_text":"!X!=C"},"Exp-4025":{"tree":["Lval",[["Var","__cil_tmp16"],null]],"text":"__cil_tmp16","abs_text":"X"},"Exp-3928":{"tree":["OtherExp"],"text":"__cil_tmp77+1UL","abs_text":"X+C"},"Exp-3522":{"tree":["Lval",[["Var","arg2"],null]],"text":"arg2","abs_text":"X"},"Exp-3699":{"tree":["Lval",[["Var","buffer"],["Index",["OtherExp"],null]]],"text":"buffer[__cil_tmp6-1UL]","abs_text":"X"},"Exp-3832":{"tree":["Lval",[["Var","__cil_tmp9"],null]],"text":"__cil_tmp9","abs_text":"X"},"Exp-3959":{"tree":["Lval",[["Var","__cil_tmp46"],null]],"text":"__cil_tmp46","abs_text":"X"},"Exp-3547":{"tree":["Lval",[["Mem",["Lval",[["Var","ptrtag"],null]]],["Field","artist",null]]],"text":"*@ptrtag.artist","abs_text":"X"},"Exp-3957":{"tree":["Lval",[["Mem",["Lval",[["Var","tag"],null]]],["Field","artist",null]]],"text":"*tag.artist","abs_text":"X"},"Exp-4003":{"tree":["Lval",[["Mem",["Lval",[["Var","tag"],null]]],["Field","artist",null]]],"text":"*tag.artist","abs_text":"X"},"Exp-3573":{"tree":["Lval",[["Var","__cil_tmp10"],null]],"text":"__cil_tmp10","abs_text":"X"},"Exp-3943":{"tree":["OtherExp"],"text":"filename==0","abs_text":"X==C"},"Exp-3430":{"tree":["Lval",[["Var","tmpfile___0"],["Index",["Lval",[["Var","tcount"],null]],null]]],"text":"tmpfile___0[tcount]","abs_text":"X"},"Exp-3940":{"tree":["Lval",[["Var","__cil_tmp50"],null]],"text":"__cil_tmp50","abs_text":"X"},"Exp-3476":{"tree":["OtherExp"],"text":"SizeOfE(*@ptrtag.u.v11.comment)","abs_text":"SizeOf"},"Exp-3752":{"tree":["OtherExp"],"text":"SizeOfE(*tag.u.v10.comment)","abs_text":"SizeOf"},"Exp-3831":{"tree":["OtherExp"],"text":"__cil_tmp9+1UL","abs_text":"X+C"},"Exp-3860":{"tree":["OtherExp"],"text":"SizeOfE(*@ptrtag.u.v10.comment)","abs_text":"SizeOf"},"Exp-3885":{"tree":["Const",0],"text":"61","abs_text":"C"},"Exp-3985":{"tree":["OtherExp"],"text":"SizeOfE(*tag.u.v10.comment)","abs_text":"SizeOf"},"Exp-3744":{"tree":["Lval",[["Var","p"],null]],"text":"p","abs_text":"X"},"Exp-3463":{"tree":["OtherExp"],"text":"StartOf(*@ptrtag.year)","abs_text":"X"},"Exp-3468":{"tree":["OtherExp"],"text":"StartOf(*tag.year)","abs_text":"X"},"Exp-3631":{"tree":["OtherExp"],"text":"StartOf(*tag.year)","abs_text":"X"},"Exp-3963":{"tree":["OtherExp"],"text":"StartOf(*tag.year)","abs_text":"X"},"Exp-3647":{"tree":["Lval",[["Var","__cil_tmp81"],null]],"text":"__cil_tmp81","abs_text":"X"},"Exp-3897":{"tree":["OtherExp"],"text":"(__cil_tmp16+__cil_tmp17)+2UL","abs_text":"X+X+C"},"Exp-3666":{"tree":["OtherExp"],"text":"!(*p2==34)","abs_text":"!X==C"},"Exp-3466":{"tree":["Const",0],"text":"\\';\\'","abs_text":"C"},"Exp-3553":{"tree":["OtherExp"],"text":"i+1","abs_text":"X+C"},"Exp-3642":{"tree":["OtherExp"],"text":"i+1","abs_text":"X+C"},"Exp-3665":{"tree":["OtherExp"],"text":"i+1","abs_text":"X+C"},"Exp-3715":{"tree":["OtherExp"],"text":"i+1","abs_text":"X+C"},"Exp-4024":{"tree":["OtherExp"],"text":"i+1","abs_text":"X+C"},"Exp-3389":{"tree":["Lval",[["Var","get_tag_string"],null]],"text":"@get_tag_string","abs_text":"X"},"Exp-3475":{"tree":["Lval",[["Var","fn"],null]],"text":"fn","abs_text":"X"},"Exp-3625":{"tree":["Lval",[["Var","__cil_tmp48"],null]],"text":"__cil_tmp48","abs_text":"X"},"Exp-3898":{"tree":["OtherExp"],"text":"__cil_tmp16+__cil_tmp17","abs_text":"X+X"},"Exp-3730":{"tree":["OtherExp"],"text":"!(i<@genre_count)","abs_text":"!X<X"},"Exp-3767":{"tree":["OtherExp"],"text":"!(i<__cil_tmp3)","abs_text":"!X<X"},"Exp-3835":{"tree":["OtherExp"],"text":"!(i<argc)","abs_text":"!X<X"},"Exp-4017":{"tree":["OtherExp"],"text":"!(i<__cil_tmp17)","abs_text":"!X<X"},"Exp-3826":{"tree":["Lval",[["Var","__cil_tmp10"],null]],"text":"__cil_tmp10","abs_text":"X"},"Exp-3418":{"tree":["OtherExp"],"text":"StartOf(@logfile)","abs_text":"X"},"Exp-3541":{"tree":["Lval",[["Var","__cil_tmp101"],null]],"text":"__cil_tmp101","abs_text":"X"},"Exp-3549":{"tree":["OtherExp"],"text":"StartOf(*@ptrtag.artist)","abs_text":"X"},"Exp-3924":{"tree":["OtherExp"],"text":"StartOf(*tag.artist)","abs_text":"X"},"Exp-3954":{"tree":["OtherExp"],"text":"StartOf(*tag.artist)","abs_text":"X"},"Exp-4000":{"tree":["OtherExp"],"text":"StartOf(*tag.artist)","abs_text":"X"},"Exp-3876":{"tree":["Lval",[["Var","__cil_tmp98"],null]],"text":"__cil_tmp98","abs_text":"X"},"Exp-3689":{"tree":["OtherExp"],"text":"__cil_tmp65+1UL","abs_text":"X+C"},"Exp-3865":{"tree":["Lval",[["Var","__cil_tmp85"],null]],"text":"__cil_tmp85","abs_text":"X"},"Exp-3623":{"tree":["Lval",[["Var","__cil_tmp16"],null]],"text":"__cil_tmp16","abs_text":"X"},"Exp-3664":{"tree":["Const",0],"text":"35","abs_text":"C"},"Exp-3355":{"tree":["OtherExp"],"text":"!(*@ptrtag.genre>=0)","abs_text":"!X>=C"},"Exp-3544":{"tree":["Lval",[["Var","id3_seek_header"],null]],"text":"@id3_seek_header","abs_text":"X"},"Exp-3796":{"tree":["OtherExp"],"text":"!(*tag.genre>=0)","abs_text":"!X>=C"},"Exp-3755":{"tree":["Lval",[["Var","__cil_tmp2"],null]],"text":"__cil_tmp2","abs_text":"X"},"Exp-3964":{"tree":["Lval",[["Var","__cil_tmp17"],null]],"text":"__cil_tmp17","abs_text":"X"},"Exp-3911":{"tree":["OtherExp"],"text":"!(@filename_template[tcount]==103)","abs_text":"!X==C"},"Exp-3858":{"tree":["Lval",[["Var","__cil_tmp129"],null]],"text":"__cil_tmp129","abs_text":"X"},"Exp-3797":{"tree":["Lval",[["Var","__cil_tmp91"],null]],"text":"__cil_tmp91","abs_text":"X"},"Exp-3941":{"tree":["Lval",[["Var","show_usage"],null]],"text":"@show_usage","abs_text":"X"},"Exp-3585":{"tree":["OtherExp"],"text":"@filename_template[tcount]==37","abs_text":"X==C"},"Exp-3808":{"tree":["OtherExp"],"text":"tmpfile___0[tcount]!=0","abs_text":"X!=C"},"Exp-3650":{"tree":["Lval",[["Var","__cil_tmp126"],null]],"text":"__cil_tmp126","abs_text":"X"},"Exp-3733":{"tree":["OtherExp"],"text":"StartOf(buffer)","abs_text":"X"},"Exp-3852":{"tree":["Lval",[["Var","__cil_tmp8"],null]],"text":"__cil_tmp8","abs_text":"X"},"Exp-3367":{"tree":["OtherExp"],"text":"string+i","abs_text":"X+X"},"Exp-3595":{"tree":["Const",0],"text":"39","abs_text":"C"},"Exp-3382":{"tree":["Lval",[["Var","id3_strip_tag"],null]],"text":"@id3_strip_tag","abs_text":"X"},"Exp-3597":{"tree":["Lval",[["Var","fntag"],["Field","genre",null]]],"text":"fntag.genre","abs_text":"X"},"Exp-3693":{"tree":["Lval",[["Var","__cil_tmp18"],null]],"text":"__cil_tmp18","abs_text":"X"},"Exp-3765":{"tree":["Lval",[["Var","size"],null]],"text":"size","abs_text":"X"},"Exp-3815":{"tree":["Lval",[["Var","__cil_tmp74"],null]],"text":"__cil_tmp74","abs_text":"X"},"Exp-3761":{"tree":["Lval",[["Var","__cil_tmp84"],null]],"text":"__cil_tmp84","abs_text":"X"},"Exp-3556":{"tree":["Lval",[["Var","__cil_tmp47"],null]],"text":"__cil_tmp47","abs_text":"X"},"Exp-3879":{"tree":["Lval",[["Var","__cil_tmp136"],null]],"text":"__cil_tmp136","abs_text":"X"},"Exp-3510":{"tree":["Lval",[["Var","copytag"],["Field","genre",null]]],"text":"@copytag.genre","abs_text":"X"},"Exp-3617":{"tree":["Lval",[["Var","__cil_tmp12"],null]],"text":"__cil_tmp12","abs_text":"X"},"Exp-3814":{"tree":["OtherExp"],"text":"__cil_tmp74+1UL","abs_text":"X+C"},"Exp-3821":{"tree":["Lval",[["Var","copytag"],["Field","tag",null]]],"text":"@copytag.tag","abs_text":"X"},"Exp-3400":{"tree":["Lval",[["Var","genre_table"],["Index",["Lval",[["Var","i"],null]],null]]],"text":"@genre_table[i]","abs_text":"X"},"Exp-3450":{"tree":["Lval",[["Var","genre_table"],["Index",["Lval",[["Var","digit"],null]],null]]],"text":"@genre_table[digit]","abs_text":"X"},"Exp-3638":{"tree":["Lval",[["Var","genre_table"],["Index",["Lval",[["Mem",["Lval",[["Var","ptrtag"],null]]],["Field","genre",null]]],null]]],"text":"@genre_table[*@ptrtag.genre]","abs_text":"X"},"Exp-3712":{"tree":["Lval",[["Var","genre_table"],["Index",["Lval",[["Mem",["Lval",[["Var","tag"],null]]],["Field","genre",null]]],null]]],"text":"@genre_table[*tag.genre]","abs_text":"X"},"Exp-3431":{"tree":["Lval",[["Var","tcount"],null]],"text":"tcount","abs_text":"X"},"Exp-3520":{"tree":["Lval",[["Var","__cil_tmp138"],null]],"text":"__cil_tmp138","abs_text":"X"},"Exp-3499":{"tree":["OtherExp"],"text":"argv+i","abs_text":"X+X"},"Exp-3513":{"tree":["Lval",[["Var","__cil_tmp51"],null]],"text":"__cil_tmp51","abs_text":"X"},"Exp-3399":{"tree":["Lval",[["Var","strcase_search"],null]],"text":"@strcase_search","abs_text":"X"},"Exp-3675":{"tree":["OtherExp"],"text":"*p1!=0","abs_text":"X!=C"},"Exp-3990":{"tree":["Const",0],"text":"45","abs_text":"C"},"Exp-3845":{"tree":["Lval",[["Var","__cil_tmp90"],null]],"text":"__cil_tmp90","abs_text":"X"},"Exp-4008":{"tree":["Lval",[["Var","__cil_tmp35"],null]],"text":"__cil_tmp35","abs_text":"X"},"Exp-3843":{"tree":["Lval",[["Var","__cil_tmp4"],null]],"text":"__cil_tmp4","abs_text":"X"},"Exp-3571":{"tree":["OtherExp"],"text":"__cil_tmp24+1UL","abs_text":"X+C"},"Exp-3878":{"tree":["Lval",[["Var","__cil_tmp92"],null]],"text":"__cil_tmp92","abs_text":"X"},"Exp-3465":{"tree":["Lval",[["Var","__cil_tmp13"],null]],"text":"__cil_tmp13","abs_text":"X"},"Exp-3473":{"tree":["Const",0],"text":"1UL","abs_text":"C"},"Exp-3543":{"tree":["Lval",[["Var","__cil_tmp11"],null]],"text":"__cil_tmp11","abs_text":"X"},"Exp-3415":{"tree":["Lval",[["Var","p1"],null]],"text":"p1","abs_text":"X"},"Exp-3487":{"tree":["OtherExp"],"text":"&@replace_char","abs_text":"&X"},"Exp-3997":{"tree":["OtherExp"],"text":"!(@filename_template[tcount]==97)","abs_text":"!X==C"},"Exp-3588":{"tree":["Lval",[["Var","__cil_tmp89"],null]],"text":"__cil_tmp89","abs_text":"X"},"Exp-3914":{"tree":["Lval",[["Var","__cil_tmp100"],null]],"text":"__cil_tmp100","abs_text":"X"},"Exp-3916":{"tree":["Lval",[["Var","__cil_tmp103"],null]],"text":"__cil_tmp103","abs_text":"X"},"Exp-3813":{"tree":["OtherExp"],"text":"*genre<@genre_count","abs_text":"X<X"},"Exp-3386":{"tree":["Lval",[["Var","__cil_tmp50"],null]],"text":"__cil_tmp50","abs_text":"X"},"Exp-3478":{"tree":["OtherExp"],"text":"StartOf(fntag.u.v11.comment)","abs_text":"X"},"Exp-3862":{"tree":["OtherExp"],"text":"StartOf(fntag.u.v10.comment)","abs_text":"X"},"Exp-3560":{"tree":["Const",0],"text":"2","abs_text":"C"},"Exp-3981":{"tree":["Lval",[["Var","fn"],null]],"text":"fn","abs_text":"X"},"Exp-3913":{"tree":["Lval",[["Var","__cil_tmp22"],null]],"text":"__cil_tmp22","abs_text":"X"},"Exp-4022":{"tree":["Lval",[["Mem",["OtherExp"]],null]],"text":"*(@replace_char+(i+1))","abs_text":"X"},"Exp-3435":{"tree":["Lval",[["Var","search_genre"],null]],"text":"@search_genre","abs_text":"X"},"Exp-3711":{"tree":["Lval",[["Var","__cil_tmp15"],null]],"text":"__cil_tmp15","abs_text":"X"},"Exp-3952":{"tree":["Const",0],"text":"\\\"rt\\\\242\\\\223?V\\\"","abs_text":"C"},"Exp-3523":{"tree":["Lval",[["Var","__cil_tmp97"],null]],"text":"__cil_tmp97","abs_text":"X"},"Exp-3967":{"tree":["Lval",[["Var","__cil_tmp117"],null]],"text":"__cil_tmp117","abs_text":"X"},"Exp-3416":{"tree":["Const",0],"text":"32","abs_text":"C"},"Exp-3567":{"tree":["Lval",[["Mem",["Lval",[["Var","count"],null]]],null]],"text":"*count","abs_text":"X"},"Exp-3581":{"tree":["Lval",[["Var","__cil_tmp109"],null]],"text":"__cil_tmp109","abs_text":"X"},"Exp-3700":{"tree":["OtherExp"],"text":"__cil_tmp6-1UL","abs_text":"X-C"},"Exp-3503":{"tree":["Lval",[["Var","sanitize"],null]],"text":"@sanitize","abs_text":"X"},"Exp-3872":{"tree":["Lval",[["Var","__cil_tmp15"],null]],"text":"__cil_tmp15","abs_text":"X"},"Exp-3757":{"tree":["Lval",[["Var","__cil_tmp5"],null]],"text":"__cil_tmp5","abs_text":"X"},"Exp-3723":{"tree":["Lval",[["Var","__cil_tmp16"],null]],"text":"__cil_tmp16","abs_text":"X"},"Exp-3949":{"tree":["Lval",[["Var","__cil_tmp12"],null]],"text":"__cil_tmp12","abs_text":"X"},"Exp-3969":{"tree":["Lval",[["Var","__cil_tmp52"],null]],"text":"__cil_tmp52","abs_text":"X"},"Exp-3994":{"tree":["OtherExp"],"text":"!(@filename_template[tcount]==110)","abs_text":"!X==C"},"Exp-3662":{"tree":["OtherExp"],"text":"!(*p1!=35)","abs_text":"!X!=C"},"Exp-3458":{"tree":["OtherExp"],"text":"!(@copyfp==0)","abs_text":"!X==C"},"Exp-3528":{"tree":["OtherExp"],"text":"!(option==0)","abs_text":"!X==C"},"Exp-3600":{"tree":["OtherExp"],"text":"!(path==0)","abs_text":"!X==C"},"Exp-3888":{"tree":["Lval",[["Var","__cil_tmp141"],null]],"text":"__cil_tmp141","abs_text":"X"},"Exp-3895":{"tree":["OtherExp"],"text":"!(fp==0)","abs_text":"!X==C"},"Exp-3942":{"tree":["OtherExp"],"text":"!(filename==0)","abs_text":"!X==C"},"Exp-3368":{"tree":["Lval",[["Var","string"],null]],"text":"string","abs_text":"X"},"Exp-3697":{"tree":["OtherExp"],"text":"!(buffer[__cil_tmp6-1UL]==10)","abs_text":"!X==C"},"Exp-3705":{"tree":["OtherExp"],"text":"!(buffer[__cil_tmp21-1UL]==10)","abs_text":"!X==C"},"Exp-3460":{"tree":["OtherExp"],"text":"SizeOfE(*@ptrtag.year)","abs_text":"SizeOf"},"Exp-3471":{"tree":["OtherExp"],"text":"SizeOfE(*tag.year)","abs_text":"SizeOf"},"Exp-3634":{"tree":["OtherExp"],"text":"SizeOfE(*tag.year)","abs_text":"SizeOf"},"Exp-3701":{"tree":["Lval",[["Var","__cil_tmp6"],null]],"text":"__cil_tmp6","abs_text":"X"},"Exp-3901":{"tree":["Lval",[["Var","__cil_tmp122"],null]],"text":"__cil_tmp122","abs_text":"X"},"Exp-3794":{"tree":["OtherExp"],"text":"StartOf(strack)","abs_text":"X"},"Exp-3524":{"tree":["OtherExp"],"text":"*p2==34","abs_text":"X==C"},"Exp-3491":{"tree":["OtherExp"],"text":"tmpfile___0[tcount]==32","abs_text":"X==C"},"Exp-3603":{"tree":["OtherExp"],"text":"!(@filename_template[tcount]==121)","abs_text":"!X==C"},"Exp-3695":{"tree":["OtherExp"],"text":"*p2==32","abs_text":"X==C"},"Exp-3811":{"tree":["Lval",[["Var","__cil_tmp114"],null]],"text":"__cil_tmp114","abs_text":"X"},"Exp-3527":{"tree":["Lval",[["Var","__cil_tmp16"],null]],"text":"__cil_tmp16","abs_text":"X"},"Exp-3751":{"tree":["OtherExp"],"text":"SizeOfE(*tag.u.v10.comment)-1UL","abs_text":"SizeOf-C"},"Exp-3984":{"tree":["OtherExp"],"text":"SizeOfE(*tag.u.v10.comment)-1UL","abs_text":"SizeOf-C"},"Exp-3724":{"tree":["Lval",[["Var","__cil_tmp17"],null]],"text":"__cil_tmp17","abs_text":"X"},"Exp-3363":{"tree":["Lval",[["Var","program_name"],null]],"text":"@program_name","abs_text":"X"},"Exp-3413":{"tree":["OtherExp"],"text":"*p1==32","abs_text":"X==C"},"Exp-3678":{"tree":["OtherExp"],"text":"@filename_template[tcount]==99","abs_text":"X==C"},"Exp-3670":{"tree":["Lval",[["Mem",["Lval",[["Var","genre"],null]]],null]],"text":"*genre","abs_text":"X"},"Exp-3991":{"tree":["OtherExp"],"text":"!(*(*(argv+i)+0)==45)","abs_text":"!X==C"}}