{"Exp-686":{"tree":["Lval",[["Var","i_"],null]],"text":"i_","abs_text":"X"},"Exp-677":{"tree":["Const",0],"text":"1","abs_text":"C"},"Exp-788":{"tree":["Const",0],"text":"4U","abs_text":"C"},"Exp-665":{"tree":["OtherExp"],"text":"argv+0","abs_text":"X+C"},"Exp-683":{"tree":["OtherExp"],"text":"*(*(argv+0)+i_)==98","abs_text":"X==C"},"Exp-789":{"tree":["OtherExp"],"text":"!*(argv+0)","abs_text":"!X"},"Exp-704":{"tree":["OtherExp"],"text":"(65535UL-a)*mask[l]","abs_text":"C-X*X"},"Exp-713":{"tree":["Lval",[["Mem",["OtherExp"]],null]],"text":"*(argv+1)","abs_text":"X"},"Exp-711":{"tree":["Lval",[["Var","tmp___0"],null]],"text":"tmp___0","abs_text":"X"},"Exp-680":{"tree":["OtherExp"],"text":"*(argv+0)+0","abs_text":"X+C"},"Exp-778":{"tree":["OtherExp"],"text":"l<3U","abs_text":"X<C"},"Exp-739":{"tree":["Const",0],"text":"3U","abs_text":"C"},"Exp-783":{"tree":["OtherExp"],"text":"StartOf(mask)","abs_text":"X"},"Exp-668":{"tree":["OtherExp"],"text":"!(!(j<rowlen))","abs_text":"!!X<X"},"Exp-727":{"tree":["OtherExp"],"text":"i+1UL","abs_text":"X+C"},"Exp-744":{"tree":["Const",0],"text":"113","abs_text":"C"},"Exp-690":{"tree":["OtherExp"],"text":"!*(*(argv+0)+(i_+1))","abs_text":"!X"},"Exp-768":{"tree":["Const",0],"text":"3UL","abs_text":"C"},"Exp-731":{"tree":["OtherExp"],"text":"!*(*(argv+0)+2)","abs_text":"!X"},"Exp-781":{"tree":["Lval",[["Var","parse_mask"],null]],"text":"@parse_mask","abs_text":"X"},"Exp-689":{"tree":["OtherExp"],"text":"!*(*(argv+0)+i_)","abs_text":"!X"},"Exp-701":{"tree":["OtherExp"],"text":"a*__cil_tmp39","abs_text":"X*X"},"Exp-666":{"tree":["Lval",[["Var","argv"],null]],"text":"argv","abs_text":"X"},"Exp-734":{"tree":["Lval",[["Var","__bswap_16"],null]],"text":"@__bswap_16","abs_text":"X"},"Exp-687":{"tree":["Const",0],"text":"98","abs_text":"C"},"Exp-719":{"tree":["OtherExp"],"text":"*(argv+0)+1","abs_text":"X+C"},"Exp-733":{"tree":["OtherExp"],"text":"*(argv+0)+2","abs_text":"X+C"},"Exp-748":{"tree":["OtherExp"],"text":"j+l","abs_text":"X+X"},"Exp-673":{"tree":["Lval",[["Var","sparrow_opt"],null]],"text":"@sparrow_opt","abs_text":"X"},"Exp-702":{"tree":["Lval",[["Var","a"],null]],"text":"a","abs_text":"X"},"Exp-771":{"tree":["Lval",[["Var","s"],null]],"text":"s","abs_text":"X"},"Exp-723":{"tree":["OtherExp"],"text":"StartOf(col)","abs_text":"X"},"Exp-770":{"tree":["Lval",[["Var","p"],null]],"text":"p","abs_text":"X"},"Exp-697":{"tree":["Lval",[["Var","k"],null]],"text":"k","abs_text":"X"},"Exp-685":{"tree":["OtherExp"],"text":"*(argv+0)+i_","abs_text":"X+X"},"Exp-724":{"tree":["OtherExp"],"text":"StartOf(col)+1","abs_text":"X+C"},"Exp-761":{"tree":["OtherExp"],"text":"SizeOfE(hdr)/SizeOfE(hdr[0])","abs_text":"SizeOf/SizeOf"},"Exp-703":{"tree":["Lval",[["Var","__cil_tmp39"],null]],"text":"__cil_tmp39","abs_text":"X"},"Exp-678":{"tree":["OtherExp"],"text":"*(*(argv+0)+0)==45","abs_text":"X==C"},"Exp-717":{"tree":["OtherExp"],"text":"*(*(argv+0)+1)==45","abs_text":"X==C"},"Exp-736":{"tree":["OtherExp"],"text":"row+(j+3U)","abs_text":"X+X+C"},"Exp-667":{"tree":["Const",0],"text":"0","abs_text":"C"},"Exp-712":{"tree":["Lval",[["Var","tmp"],null]],"text":"tmp","abs_text":"X"},"Exp-679":{"tree":["Lval",[["Mem",["OtherExp"]],null]],"text":"*(*(argv+0)+0)","abs_text":"X"},"Exp-664":{"tree":["Lval",[["Mem",["OtherExp"]],null]],"text":"*(argv+0)","abs_text":"X"},"Exp-777":{"tree":["OtherExp"],"text":"!(l<3U)","abs_text":"!X<C"},"Exp-762":{"tree":["OtherExp"],"text":"SizeOfE(hdr)","abs_text":"SizeOf"},"Exp-698":{"tree":["Lval",[["Var","l"],null]],"text":"l","abs_text":"X"},"Exp-735":{"tree":["Lval",[["Mem",["OtherExp"]],null]],"text":"*(row+(j+3U))","abs_text":"X"},"Exp-757":{"tree":["Lval",[["Var","stdin"],null]],"text":"@stdin","abs_text":"stdin"},"Exp-671":{"tree":["Lval",[["Var","j"],null]],"text":"j","abs_text":"X"},"Exp-715":{"tree":["Lval",[["Var","__cil_tmp38"],null]],"text":"__cil_tmp38","abs_text":"X"},"Exp-765":{"tree":["OtherExp"],"text":"!(!(i<3UL))","abs_text":"!!X<C"},"Exp-776":{"tree":["OtherExp"],"text":"!(!(l<3U))","abs_text":"!!X<C"},"Exp-769":{"tree":["Lval",[["Var","fread"],null]],"text":"@fread","abs_text":"fread"},"Exp-785":{"tree":["OtherExp"],"text":"&width","abs_text":"&X"},"Exp-750":{"tree":["OtherExp"],"text":"mask+i","abs_text":"X+X"},"Exp-725":{"tree":["OtherExp"],"text":"StartOf(col)+2","abs_text":"X+C"},"Exp-759":{"tree":["OtherExp"],"text":"SizeOfE(hdr[0])","abs_text":"SizeOf"},"Exp-709":{"tree":["OtherExp"],"text":"*(*(argv+0)+i_)==111","abs_text":"X==C"},"Exp-672":{"tree":["Lval",[["Var","rowlen"],null]],"text":"rowlen","abs_text":"X"},"Exp-721":{"tree":["Lval",[["Var","s"],null]],"text":"s","abs_text":"X"},"Exp-708":{"tree":["Const",0],"text":"16842495UL","abs_text":"C"},"Exp-766":{"tree":["OtherExp"],"text":"!(i<3UL)","abs_text":"!X<C"},"Exp-676":{"tree":["OtherExp"],"text":"argv+1","abs_text":"X+C"},"Exp-740":{"tree":["Lval",[["Var","__builtin_bswap16"],null]],"text":"@__builtin_bswap16","abs_text":"X"},"Exp-699":{"tree":["OtherExp"],"text":"((a*__cil_tmp39)+((65535UL-a)*mask[l]))/16842495UL","abs_text":"X*X+C-X*X/C"},"Exp-670":{"tree":["OtherExp"],"text":"j<rowlen","abs_text":"X<X"},"Exp-693":{"tree":["OtherExp"],"text":"i_+1","abs_text":"X+C"},"Exp-692":{"tree":["OtherExp"],"text":"*(argv+0)+(i_+1)","abs_text":"X+X+C"},"Exp-674":{"tree":["Lval",[["Var","optind"],null]],"text":"@optind","abs_text":"X"},"Exp-767":{"tree":["OtherExp"],"text":"i<3UL","abs_text":"X<C"},"Exp-730":{"tree":["OtherExp"],"text":"!(!*(*(argv+0)+2))","abs_text":"!!X"},"Exp-741":{"tree":["Lval",[["Var","__bsx"],null]],"text":"__bsx","abs_text":"X"},"Exp-786":{"tree":["OtherExp"],"text":"&height","abs_text":"&X"},"Exp-682":{"tree":["OtherExp"],"text":"!(*(*(argv+0)+i_)==98)","abs_text":"!X==C"},"Exp-732":{"tree":["Lval",[["Mem",["OtherExp"]],null]],"text":"*(*(argv+0)+2)","abs_text":"X"},"Exp-718":{"tree":["Lval",[["Mem",["OtherExp"]],null]],"text":"*(*(argv+0)+1)","abs_text":"X"},"Exp-784":{"tree":["Lval",[["Var","ff_read_header"],null]],"text":"@ff_read_header","abs_text":"X"},"Exp-738":{"tree":["OtherExp"],"text":"j+3U","abs_text":"X+C"},"Exp-675":{"tree":["Lval",[["Var","optarg"],null]],"text":"@optarg","abs_text":"X"},"Exp-753":{"tree":["Lval",[["Var","col"],["Index",["Lval",[["Var","i"],null]],null]]],"text":"col[i]","abs_text":"X"},"Exp-763":{"tree":["Lval",[["Var","hdr"],null]],"text":"hdr","abs_text":"X"},"Exp-774":{"tree":["Lval",[["Var","sparrow_arg"],null]],"text":"@sparrow_arg","abs_text":"X"},"Exp-714":{"tree":["OtherExp"],"text":"!(*(*(argv+0)+i_)==111)","abs_text":"!X==C"},"Exp-720":{"tree":["Lval",[["Var","sscanf"],null]],"text":"@sscanf","abs_text":"sscanf"},"Exp-695":{"tree":["Lval",[["Var","rowout"],null]],"text":"rowout","abs_text":"X"},"Exp-710":{"tree":["Const",0],"text":"111","abs_text":"C"},"Exp-775":{"tree":["Lval",[["Var","argc"],null]],"text":"argc","abs_text":"X"},"Exp-706":{"tree":["Const",0],"text":"65535UL","abs_text":"C"},"Exp-707":{"tree":["Lval",[["Var","mask"],["Index",["Lval",[["Var","l"],null]],null]]],"text":"mask[l]","abs_text":"X"},"Exp-780":{"tree":["Const",0],"text":"1U","abs_text":"C"},"Exp-751":{"tree":["Lval",[["Var","mask"],null]],"text":"mask","abs_text":"X"},"Exp-754":{"tree":["Lval",[["Var","colfac"],null]],"text":"colfac","abs_text":"X"},"Exp-700":{"tree":["OtherExp"],"text":"(a*__cil_tmp39)+((65535UL-a)*mask[l])","abs_text":"X*X+C-X*X"},"Exp-684":{"tree":["Lval",[["Mem",["OtherExp"]],null]],"text":"*(*(argv+0)+i_)","abs_text":"X"},"Exp-691":{"tree":["Lval",[["Mem",["OtherExp"]],null]],"text":"*(*(argv+0)+(i_+1))","abs_text":"X"},"Exp-705":{"tree":["OtherExp"],"text":"65535UL-a","abs_text":"C-X"},"Exp-782":{"tree":["Lval",[["Var","tmp___1"],null]],"text":"tmp___1","abs_text":"X"},"Exp-669":{"tree":["OtherExp"],"text":"!(j<rowlen)","abs_text":"!X<X"},"Exp-760":{"tree":["Lval",[["Var","hdr"],["Index",["Const",0],null]]],"text":"hdr[0]","abs_text":"X"},"Exp-688":{"tree":["OtherExp"],"text":"!(!*(*(argv+0)+i_))","abs_text":"!!X"},"Exp-743":{"tree":["OtherExp"],"text":"*(*(argv+0)+i_)==113","abs_text":"X==C"},"Exp-742":{"tree":["OtherExp"],"text":"!(*(*(argv+0)+i_)==113)","abs_text":"!X==C"},"Exp-746":{"tree":["Lval",[["Mem",["OtherExp"]],null]],"text":"*(row+(j+l))","abs_text":"X"},"Exp-755":{"tree":["Lval",[["Var","efread"],null]],"text":"@efread","abs_text":"X"},"Exp-694":{"tree":["OtherExp"],"text":"rowout+(k+l)","abs_text":"X+X+X"},"Exp-747":{"tree":["OtherExp"],"text":"row+(j+l)","abs_text":"X+X+X"},"Exp-758":{"tree":["OtherExp"],"text":"StartOf(hdr)","abs_text":"X"},"Exp-779":{"tree":["OtherExp"],"text":"l+1U","abs_text":"X+C"},"Exp-722":{"tree":["OtherExp"],"text":"StartOf(fmt)","abs_text":"X"},"Exp-728":{"tree":["Lval",[["Var","i"],null]],"text":"i","abs_text":"X"},"Exp-681":{"tree":["Const",0],"text":"45","abs_text":"C"},"Exp-749":{"tree":["OtherExp"],"text":"k+3U","abs_text":"X+C"},"Exp-729":{"tree":["Const",0],"text":"1UL","abs_text":"C"},"Exp-772":{"tree":["Lval",[["Var","n"],null]],"text":"n","abs_text":"X"},"Exp-696":{"tree":["OtherExp"],"text":"k+l","abs_text":"X+X"},"Exp-737":{"tree":["Lval",[["Var","row"],null]],"text":"row","abs_text":"X"},"Exp-726":{"tree":["Const",0],"text":"2","abs_text":"C"},"Exp-787":{"tree":["OtherExp"],"text":"j+4U","abs_text":"X+C"},"Exp-756":{"tree":["OtherExp"],"text":"SizeOf(uint16_t )","abs_text":"SizeOf"},"Exp-764":{"tree":["Lval",[["Var","tmp___0"],null]],"text":"tmp___0","abs_text":"X"},"Exp-745":{"tree":["Lval",[["Var","__cil_tmp2"],null]],"text":"__cil_tmp2","abs_text":"X"},"Exp-752":{"tree":["OtherExp"],"text":"col[i]*colfac","abs_text":"X*X"},"Exp-773":{"tree":["Lval",[["Var","f"],null]],"text":"f","abs_text":"X"},"Exp-716":{"tree":["OtherExp"],"text":"!(*(*(argv+0)+1)==45)","abs_text":"!X==C"}}