{"Exp-124403":{"tree":["OtherExp"],"text":"*stream.outputBuffer!=0","abs_text":"X!=C"},"Exp-124242":{"tree":["OtherExp"],"text":"value<<8","abs_text":"X<<C"},"Exp-124470":{"tree":["OtherExp"],"text":"value<<8","abs_text":"X<<C"},"Exp-124661":{"tree":["OtherExp"],"text":"(period*speed)/(1.f-speed)","abs_text":"X*X/C-X"},"Exp-124296":{"tree":["Lval",[["Var","stream"],null]],"text":"stream","abs_text":"X"},"Exp-124563":{"tree":["OtherExp"],"text":"*stream.pitchBuffer==0","abs_text":"X==C"},"Exp-124611":{"tree":["OtherExp"],"text":"*stream.pitchBuffer==0","abs_text":"X==C"},"Exp-124432":{"tree":["Lval",[["Var","numChannels"],null]],"text":"numChannels","abs_text":"X"},"Exp-124359":{"tree":["OtherExp"],"text":"*stream.outputBuffer+(originalNumOutputSamples**stream.numChannels)","abs_text":"X+X*X"},"Exp-124481":{"tree":["OtherExp"],"text":"(position+period)-newPeriod","abs_text":"X+X-X"},"Exp-124697":{"tree":["OtherExp"],"text":"*stream.outputBuffer+(numSamples**stream.numChannels)","abs_text":"X+X*X"},"Exp-124050":{"tree":["Lval",[["Var","sampleRate"],null]],"text":"sampleRate","abs_text":"X"},"Exp-124532":{"tree":["OtherExp"],"text":"*stream.downSampleBuffer==0","abs_text":"X==C"},"Exp-124476":{"tree":["OtherExp"],"text":"!(skip==1)","abs_text":"!X==C"},"Exp-124602":{"tree":["Const",0],"text":"0.999990000001","abs_text":"C"},"Exp-124224":{"tree":["OtherExp"],"text":"position+newSamples","abs_text":"X+X"},"Exp-124437":{"tree":["OtherExp"],"text":"position+period","abs_text":"X+X"},"Exp-124152":{"tree":["OtherExp"],"text":"period-(skip<<2)","abs_text":"X-X<<C"},"Exp-123987":{"tree":["OtherExp"],"text":"*stream.speed/*stream.pitch","abs_text":"X/X"},"Exp-124244":{"tree":["OtherExp"],"text":"*stream.speed/*stream.pitch","abs_text":"X/X"},"Exp-123986":{"tree":["Const",0],"text":"1.f","abs_text":"C"},"Exp-123924":{"tree":["Const",0],"text":"1","abs_text":"C"},"Exp-124400":{"tree":["Lval",[["Var","changeSpeed"],null]],"text":"@changeSpeed","abs_text":"X"},"Exp-123988":{"tree":["Lval",[["Mem",["Lval",[["Var","stream"],null]]],["Field","speed",null]]],"text":"*stream.speed","abs_text":"X"},"Exp-124245":{"tree":["Lval",[["Mem",["Lval",[["Var","stream"],null]]],["Field","speed",null]]],"text":"*stream.speed","abs_text":"X"},"Exp-124241":{"tree":["Lval",[["Mem",["Lval",[["Var","stream"],null]]],["Field","maxPeriod",null]]],"text":"*stream.maxPeriod","abs_text":"X"},"Exp-124433":{"tree":["Lval",[["Var","out"],null]],"text":"out","abs_text":"X"},"Exp-124390":{"tree":["OtherExp"],"text":"2048/numChannels","abs_text":"C/X"},"Exp-124365":{"tree":["Lval",[["Var","enlargeInputBufferIfNeeded"],null]],"text":"@enlargeInputBufferIfNeeded","abs_text":"X"},"Exp-124493":{"tree":["Lval",[["Var","source"],null]],"text":"source","abs_text":"X"},"Exp-124499":{"tree":["OtherExp"],"text":"((*d*(numSamples-t))+(*u*(t-separation)))/numSamples","abs_text":"X*X-X+X*X-X/X"},"Exp-123935":{"tree":["OtherExp"],"text":"*stream.remainingInputToCopy-numSamples","abs_text":"X-X"},"Exp-124715":{"tree":["OtherExp"],"text":"s+1","abs_text":"X+C"},"Exp-124071":{"tree":["Lval",[["Var","__cil_tmp12"],null]],"text":"__cil_tmp12","abs_text":"X"},"Exp-124170":{"tree":["OtherExp"],"text":"sample|(bytes[__cil_tmp12]<<8)","abs_text":"X|X<<C"},"Exp-124327":{"tree":["OtherExp"],"text":"rightPosition-position","abs_text":"X-X"},"Exp-124398":{"tree":["OtherExp"],"text":"rightPosition-leftPosition","abs_text":"X-X"},"Exp-124342":{"tree":["Lval",[["Var","i"],null]],"text":"i","abs_text":"X"},"Exp-124539":{"tree":["OtherExp"],"text":"2.f-speed","abs_text":"C-X"},"Exp-124117":{"tree":["OtherExp"],"text":"maxRequired*(SizeOf(short )*numChannels)","abs_text":"X*SizeOf*X"},"Exp-124162":{"tree":["Lval",[["Var","out"],null]],"text":"out","abs_text":"X"},"Exp-124604":{"tree":["OtherExp"],"text":"!(sVal>=pVal)","abs_text":"!X>=X"},"Exp-124016":{"tree":["OtherExp"],"text":"!(*stream.inputBuffer==0)","abs_text":"!X==C"},"Exp-124355":{"tree":["OtherExp"],"text":"!(*stream.outputBuffer==0)","abs_text":"!X==C"},"Exp-124540":{"tree":["OtherExp"],"text":"!(*stream.inputBuffer==0)","abs_text":"!X==C"},"Exp-124633":{"tree":["OtherExp"],"text":"!(*stream.outputBuffer==0)","abs_text":"!X==C"},"Exp-124658":{"tree":["OtherExp"],"text":"!(*stream.pitchBuffer==0)","abs_text":"!X==C"},"Exp-124675":{"tree":["OtherExp"],"text":"!(*stream.pitchBuffer==0)","abs_text":"!X==C"},"Exp-124689":{"tree":["OtherExp"],"text":"!(*stream.prevPeriod==0)","abs_text":"!X==C"},"Exp-124713":{"tree":["OtherExp"],"text":"!(*stream.downSampleBuffer==0)","abs_text":"!X==C"},"Exp-124358":{"tree":["Lval",[["Var","scaleSamples"],null]],"text":"@scaleSamples","abs_text":"X"},"Exp-124583":{"tree":["OtherExp"],"text":"rampDown+i","abs_text":"X+X"},"Exp-124691":{"tree":["OtherExp"],"text":"rampDown+i","abs_text":"X+X"},"Exp-124523":{"tree":["Lval",[["Var","bytes"],null]],"text":"bytes","abs_text":"X"},"Exp-124098":{"tree":["Lval",[["Var","volume"],null]],"text":"volume","abs_text":"X"},"Exp-124109":{"tree":["Lval",[["Var","stream"],null]],"text":"stream","abs_text":"X"},"Exp-124032":{"tree":["Lval",[["Var","stream"],null]],"text":"stream","abs_text":"X"},"Exp-123962":{"tree":["Lval",[["Var","rate"],null]],"text":"rate","abs_text":"X"},"Exp-124373":{"tree":["Lval",[["Var","file"],null]],"text":"file","abs_text":"X"},"Exp-124186":{"tree":["OtherExp"],"text":"!(!(position<(*stream.numPitchSamples-1)))","abs_text":"!!X<X-C"},"Exp-123952":{"tree":["Lval",[["Mem",["Lval",[["Var","stream"],null]]],["Field","numChannels",null]]],"text":"*stream.numChannels","abs_text":"X"},"Exp-124001":{"tree":["Lval",[["Mem",["Lval",[["Var","stream"],null]]],["Field","numChannels",null]]],"text":"*stream.numChannels","abs_text":"X"},"Exp-124035":{"tree":["Lval",[["Mem",["Lval",[["Var","stream"],null]]],["Field","numChannels",null]]],"text":"*stream.numChannels","abs_text":"X"},"Exp-124094":{"tree":["Lval",[["Mem",["Lval",[["Var","stream"],null]]],["Field","numChannels",null]]],"text":"*stream.numChannels","abs_text":"X"},"Exp-124208":{"tree":["Lval",[["Mem",["Lval",[["Var","stream"],null]]],["Field","numChannels",null]]],"text":"*stream.numChannels","abs_text":"X"},"Exp-124249":{"tree":["Lval",[["Mem",["Lval",[["Var","stream"],null]]],["Field","numChannels",null]]],"text":"*stream.numChannels","abs_text":"X"},"Exp-124278":{"tree":["Lval",[["Mem",["Lval",[["Var","stream"],null]]],["Field","numChannels",null]]],"text":"*stream.numChannels","abs_text":"X"},"Exp-124298":{"tree":["Lval",[["Mem",["Lval",[["Var","stream"],null]]],["Field","numChannels",null]]],"text":"*stream.numChannels","abs_text":"X"},"Exp-124362":{"tree":["Lval",[["Mem",["Lval",[["Var","stream"],null]]],["Field","numChannels",null]]],"text":"*stream.numChannels","abs_text":"X"},"Exp-124429":{"tree":["Lval",[["Mem",["Lval",[["Var","stream"],null]]],["Field","numChannels",null]]],"text":"*stream.numChannels","abs_text":"X"},"Exp-124459":{"tree":["Lval",[["Mem",["Lval",[["Var","stream"],null]]],["Field","numChannels",null]]],"text":"*stream.numChannels","abs_text":"X"},"Exp-124556":{"tree":["Lval",[["Mem",["Lval",[["Var","stream"],null]]],["Field","numChannels",null]]],"text":"*stream.numChannels","abs_text":"X"},"Exp-124603":{"tree":["Lval",[["Mem",["Lval",[["Var","stream"],null]]],["Field","numChannels",null]]],"text":"*stream.numChannels","abs_text":"X"},"Exp-124620":{"tree":["Lval",[["Mem",["Lval",[["Var","stream"],null]]],["Field","numChannels",null]]],"text":"*stream.numChannels","abs_text":"X"},"Exp-124621":{"tree":["Lval",[["Mem",["Lval",[["Var","stream"],null]]],["Field","numChannels",null]]],"text":"*stream.numChannels","abs_text":"X"},"Exp-124681":{"tree":["Lval",[["Mem",["Lval",[["Var","stream"],null]]],["Field","numChannels",null]]],"text":"*stream.numChannels","abs_text":"X"},"Exp-124699":{"tree":["Lval",[["Mem",["Lval",[["Var","stream"],null]]],["Field","numChannels",null]]],"text":"*stream.numChannels","abs_text":"X"},"Exp-124703":{"tree":["Lval",[["Mem",["Lval",[["Var","stream"],null]]],["Field","numChannels",null]]],"text":"*stream.numChannels","abs_text":"X"},"Exp-124064":{"tree":["Lval",[["Var","maxSamples"],null]],"text":"maxSamples","abs_text":"X"},"Exp-124422":{"tree":["Lval",[["Var","__cil_tmp5"],null]],"text":"__cil_tmp5","abs_text":"X"},"Exp-124506":{"tree":["OtherExp"],"text":"t-separation","abs_text":"X-X"},"Exp-124369":{"tree":["Lval",[["Var","downSampleInput"],null]],"text":"@downSampleInput","abs_text":"X"},"Exp-124590":{"tree":["Lval",[["Var","retPeriod"],null]],"text":"retPeriod","abs_text":"X"},"Exp-123937":{"tree":["Lval",[["Var","numSamples"],null]],"text":"numSamples","abs_text":"X"},"Exp-124357":{"tree":["OtherExp"],"text":"!(*stream.numChannels==1)","abs_text":"!X==C"},"Exp-123964":{"tree":["Lval",[["Var","sonicDestroyStream"],null]],"text":"@sonicDestroyStream","abs_text":"X"},"Exp-124062":{"tree":["OtherExp"],"text":"numSamples>maxSamples","abs_text":"X>X"},"Exp-124353":{"tree":["OtherExp"],"text":"&minDiff","abs_text":"&X"},"Exp-123969":{"tree":["OtherExp"],"text":"period+newSamples","abs_text":"X+X"},"Exp-124068":{"tree":["Lval",[["Var","sampleRate"],null]],"text":"sampleRate","abs_text":"X"},"Exp-124679":{"tree":["OtherExp"],"text":"speed>1.","abs_text":"X>C"},"Exp-124653":{"tree":["Lval",[["Var","file"],null]],"text":"file","abs_text":"X"},"Exp-124660":{"tree":["Lval",[["Var","interpolate"],null]],"text":"@interpolate","abs_text":"X"},"Exp-123991":{"tree":["OtherExp"],"text":"*stream.pitchBufferSize*SizeOf(short )","abs_text":"X*SizeOf"},"Exp-124027":{"tree":["Lval",[["Mem",["Lval",[["Var","stream"],null]]],["Field","numPitchSamples",null]]],"text":"*stream.numPitchSamples","abs_text":"X"},"Exp-124147":{"tree":["Lval",[["Mem",["Lval",[["Var","stream"],null]]],["Field","numPitchSamples",null]]],"text":"*stream.numPitchSamples","abs_text":"X"},"Exp-124168":{"tree":["Lval",[["Mem",["Lval",[["Var","stream"],null]]],["Field","numPitchSamples",null]]],"text":"*stream.numPitchSamples","abs_text":"X"},"Exp-124190":{"tree":["Lval",[["Mem",["Lval",[["Var","stream"],null]]],["Field","numPitchSamples",null]]],"text":"*stream.numPitchSamples","abs_text":"X"},"Exp-124282":{"tree":["Lval",[["Mem",["Lval",[["Var","stream"],null]]],["Field","numPitchSamples",null]]],"text":"*stream.numPitchSamples","abs_text":"X"},"Exp-124521":{"tree":["OtherExp"],"text":"(*stream.numOutputSamples+period)*numChannels","abs_text":"X+X*X"},"Exp-124528":{"tree":["OtherExp"],"text":"4096/(*file.numChannels*2)","abs_text":"C/X*C"},"Exp-124303":{"tree":["Lval",[["Var","speed"],null]],"text":"speed","abs_text":"X"},"Exp-124591":{"tree":["Lval",[["Var","retMaxDiff"],null]],"text":"retMaxDiff","abs_text":"X"},"Exp-124613":{"tree":["Lval",[["Var","__cil_tmp13"],null]],"text":"__cil_tmp13","abs_text":"X"},"Exp-124232":{"tree":["Lval",[["Mem",["Lval",[["Var","u"],null]]],null]],"text":"*u","abs_text":"X"},"Exp-124006":{"tree":["OtherExp"],"text":"(ratio*left)+((width-ratio)*right)","abs_text":"X*X+X-X*X"},"Exp-124037":{"tree":["OtherExp"],"text":"(numSamples*SizeOf(short ))**stream.numChannels","abs_text":"X*SizeOf*X"},"Exp-124158":{"tree":["Lval",[["Var","numChannels"],null]],"text":"numChannels","abs_text":"X"},"Exp-124460":{"tree":["OtherExp"],"text":"(remainingSamples*SizeOf(short ))**stream.numChannels","abs_text":"X*SizeOf*X"},"Exp-124558":{"tree":["OtherExp"],"text":"(numSamples*SizeOf(short ))**stream.numChannels","abs_text":"X*SizeOf*X"},"Exp-124700":{"tree":["OtherExp"],"text":"(remainingSamples*SizeOf(short ))**stream.numChannels","abs_text":"X*SizeOf*X"},"Exp-124047":{"tree":["Lval",[["Var","__cil_tmp9"],null]],"text":"__cil_tmp9","abs_text":"X"},"Exp-124338":{"tree":["OtherExp"],"text":"!((*stream.numOutputSamples+numSamples)>*stream.outputBufferSize)","abs_text":"!X+X>X"},"Exp-124416":{"tree":["OtherExp"],"text":"!((*stream.numPitchSamples+numSamples)>*stream.pitchBufferSize)","abs_text":"!X+X>X"},"Exp-124549":{"tree":["OtherExp"],"text":"!((*stream.numInputSamples+numSamples)>*stream.inputBufferSize)","abs_text":"!X+X>X"},"Exp-124174":{"tree":["Lval",[["Var","__cil_tmp12"],null]],"text":"__cil_tmp12","abs_text":"X"},"Exp-124121":{"tree":["Lval",[["Var","__cil_tmp7"],null]],"text":"__cil_tmp7","abs_text":"X"},"Exp-124082":{"tree":["Lval",[["Mem",["Lval",[["Var","stream"],null]]],["Field","sampleRate",null]]],"text":"*stream.sampleRate","abs_text":"X"},"Exp-124588":{"tree":["Lval",[["Mem",["Lval",[["Var","stream"],null]]],["Field","sampleRate",null]]],"text":"*stream.sampleRate","abs_text":"X"},"Exp-124216":{"tree":["Lval",[["Var","i"],null]],"text":"i","abs_text":"X"},"Exp-123938":{"tree":["OtherExp"],"text":"!(!(t<numSamples))","abs_text":"!!X<X"},"Exp-124213":{"tree":["OtherExp"],"text":"!(!(i<numChannels))","abs_text":"!!X<X"},"Exp-124423":{"tree":["OtherExp"],"text":"!(!(i<numChannels))","abs_text":"!!X<X"},"Exp-124045":{"tree":["Lval",[["Mem",["Lval",[["Var","stream"],null]]],["Field","oldRatePosition",null]]],"text":"*stream.oldRatePosition","abs_text":"X"},"Exp-124253":{"tree":["Lval",[["Mem",["Lval",[["Var","stream"],null]]],["Field","oldRatePosition",null]]],"text":"*stream.oldRatePosition","abs_text":"X"},"Exp-123990":{"tree":["OtherExp"],"text":"(*stream.pitchBufferSize*SizeOf(short ))*numChannels","abs_text":"X*SizeOf*X"},"Exp-124340":{"tree":["OtherExp"],"text":"!(i>=0)","abs_text":"!X>=C"},"Exp-124434":{"tree":["OtherExp"],"text":"samples+(period*numChannels)","abs_text":"X+X*X"},"Exp-124512":{"tree":["OtherExp"],"text":"!(i>=0)","abs_text":"!X>=C"},"Exp-124630":{"tree":["OtherExp"],"text":"samples+(period*numChannels)","abs_text":"X+X*X"},"Exp-124212":{"tree":["Lval",[["Var","__cil_tmp10"],null]],"text":"__cil_tmp10","abs_text":"X"},"Exp-124444":{"tree":["OtherExp"],"text":"soundFile==0","abs_text":"X==C"},"Exp-124210":{"tree":["Lval",[["Var","value"],null]],"text":"value","abs_text":"X"},"Exp-124354":{"tree":["OtherExp"],"text":"&maxDiff","abs_text":"&X"},"Exp-124173":{"tree":["Lval",[["Var","bytes"],["Index",["Lval",[["Var","__cil_tmp12"],null]],null]]],"text":"bytes[__cil_tmp12]","abs_text":"X"},"Exp-124348":{"tree":["Lval",[["Var","bytes"],["Index",["Lval",[["Var","__cil_tmp11"],null]],null]]],"text":"bytes[__cil_tmp11]","abs_text":"X"},"Exp-124240":{"tree":["Lval",[["Var","maxPeriod"],null]],"text":"maxPeriod","abs_text":"X"},"Exp-124297":{"tree":["OtherExp"],"text":"*stream.numChannels==1","abs_text":"X==C"},"Exp-124529":{"tree":["Const",0],"text":"4096","abs_text":"C"},"Exp-124021":{"tree":["Lval",[["Mem",["Lval",[["Var","stream"],null]]],["Field","maxRequired",null]]],"text":"*stream.maxRequired","abs_text":"X"},"Exp-124283":{"tree":["Lval",[["Mem",["Lval",[["Var","stream"],null]]],["Field","maxRequired",null]]],"text":"*stream.maxRequired","abs_text":"X"},"Exp-124415":{"tree":["OtherExp"],"text":"*stream.newRatePosition!=newSampleRate","abs_text":"X!=X"},"Exp-124452":{"tree":["OtherExp"],"text":"!(pitch>=1.f)","abs_text":"!X>=C"},"Exp-124562":{"tree":["Lval",[["Mem",["Lval",[["Var","stream"],null]]],["Field","maxRequired",null]]],"text":"*stream.maxRequired","abs_text":"X"},"Exp-124622":{"tree":["Lval",[["Mem",["Lval",[["Var","stream"],null]]],["Field","maxRequired",null]]],"text":"*stream.maxRequired","abs_text":"X"},"Exp-124368":{"tree":["Lval",[["Var","rate"],null]],"text":"rate","abs_text":"X"},"Exp-124524":{"tree":["Lval",[["Var","length"],null]],"text":"length","abs_text":"X"},"Exp-124178":{"tree":["Const",0],"text":"32767","abs_text":"C"},"Exp-124722":{"tree":["Lval",[["Var","__cil_tmp17"],null]],"text":"__cil_tmp17","abs_text":"X"},"Exp-123973":{"tree":["OtherExp"],"text":"numSamples==0","abs_text":"X==C"},"Exp-124409":{"tree":["OtherExp"],"text":"numSamples==0","abs_text":"X==C"},"Exp-124695":{"tree":["OtherExp"],"text":"numSamples==0","abs_text":"X==C"},"Exp-124205":{"tree":["OtherExp"],"text":"*stream.inputBufferSize*SizeOf(short )","abs_text":"X*SizeOf"},"Exp-124235":{"tree":["OtherExp"],"text":"2*maxRequired","abs_text":"C*X"},"Exp-124326":{"tree":["OtherExp"],"text":"!(speed>1.00001000001)","abs_text":"!X>C"},"Exp-124066":{"tree":["Lval",[["Var","stream"],null]],"text":"stream","abs_text":"X"},"Exp-124674":{"tree":["Const",0],"text":"\\\"wb\\\"","abs_text":"C"},"Exp-124175":{"tree":["Const",0],"text":"8","abs_text":"C"},"Exp-124547":{"tree":["Lval",[["Var","sonicSetVolume"],null]],"text":"@sonicSetVolume","abs_text":"X"},"Exp-124086":{"tree":["Lval",[["Var","numSamples"],null]],"text":"numSamples","abs_text":"X"},"Exp-124450":{"tree":["Lval",[["Var","tmp"],null]],"text":"tmp","abs_text":"X"},"Exp-124366":{"tree":["OtherExp"],"text":"remainingSamples+(2*maxRequired)","abs_text":"X+C*X"},"Exp-124041":{"tree":["Lval",[["Var","file"],null]],"text":"file","abs_text":"X"},"Exp-124331":{"tree":["Lval",[["Var","file"],null]],"text":"file","abs_text":"X"},"Exp-124222":{"tree":["Lval",[["Var","period"],null]],"text":"period","abs_text":"X"},"Exp-124061":{"tree":["OtherExp"],"text":"!(numSamples>maxSamples)","abs_text":"!X>X"},"Exp-124510":{"tree":["Lval",[["Var","bytes"],["Index",["Lval",[["Var","i"],null]],null]]],"text":"bytes[i]","abs_text":"X"},"Exp-123984":{"tree":["OtherExp"],"text":"*stream.volume!=1.f","abs_text":"X!=C"},"Exp-124092":{"tree":["Lval",[["Var","expectedString"],null]],"text":"expectedString","abs_text":"X"},"Exp-124351":{"tree":["Lval",[["Var","samples"],null]],"text":"samples","abs_text":"X"},"Exp-124494":{"tree":["OtherExp"],"text":"((*stream.numPitchSamples-numSamples)*SizeOf(short ))*numChannels","abs_text":"X-X*SizeOf*X"},"Exp-124399":{"tree":["Lval",[["Var","leftPosition"],null]],"text":"leftPosition","abs_text":"X"},"Exp-124662":{"tree":["OtherExp"],"text":"period*speed","abs_text":"X*X"},"Exp-124593":{"tree":["Lval",[["Var","maxDiff"],null]],"text":"maxDiff","abs_text":"X"},"Exp-124187":{"tree":["OtherExp"],"text":"!(position<(*stream.numPitchSamples-1))","abs_text":"!X<X-C"},"Exp-124502":{"tree":["Lval",[["Mem",["Lval",[["Var","d"],null]]],null]],"text":"*d","abs_text":"X"},"Exp-124592":{"tree":["OtherExp"],"text":"maxDiff/worstPeriod","abs_text":"X/X"},"Exp-124339":{"tree":["OtherExp"],"text":"!(!(i>=0))","abs_text":"!!X>=C"},"Exp-124511":{"tree":["OtherExp"],"text":"!(!(i>=0))","abs_text":"!!X>=C"},"Exp-124690":{"tree":["Lval",[["Var","__cil_tmp7"],null]],"text":"__cil_tmp7","abs_text":"X"},"Exp-124209":{"tree":["OtherExp"],"text":"value+*__cil_tmp10","abs_text":"X+X"},"Exp-124196":{"tree":["Lval",[["Var","stream"],null]],"text":"stream","abs_text":"X"},"Exp-123926":{"tree":["Lval",[["Var","d"],null]],"text":"d","abs_text":"X"},"Exp-124133":{"tree":["OtherExp"],"text":"*stream.pitchBuffer+position","abs_text":"X+X"},"Exp-124281":{"tree":["OtherExp"],"text":"*stream.numPitchSamples-position","abs_text":"X-X"},"Exp-124301":{"tree":["OtherExp"],"text":"position+1","abs_text":"X+C"},"Exp-124171":{"tree":["Lval",[["Var","sample"],null]],"text":"sample","abs_text":"X"},"Exp-124386":{"tree":["OtherExp"],"text":"speed>=2.f","abs_text":"X>=C"},"Exp-124451":{"tree":["Lval",[["Var","minPeriod"],null]],"text":"minPeriod","abs_text":"X"},"Exp-123925":{"tree":["OtherExp"],"text":"d+numChannels","abs_text":"X+X"},"Exp-124346":{"tree":["OtherExp"],"text":"d+numChannels","abs_text":"X+X"},"Exp-124155":{"tree":["OtherExp"],"text":"*stream.pitchBuffer+(position*numChannels)","abs_text":"X+X*X"},"Exp-124570":{"tree":["OtherExp"],"text":"*stream.pitchBuffer+(numSamples*numChannels)","abs_text":"X+X*X"},"Exp-124636":{"tree":["OtherExp"],"text":"*stream.outputBuffer+(originalNumOutputSamples*numChannels)","abs_text":"X+X*X"},"Exp-124058":{"tree":["Lval",[["Var","in"],null]],"text":"in","abs_text":"X"},"Exp-123963":{"tree":["Lval",[["Var","originalNumOutputSamples"],null]],"text":"originalNumOutputSamples","abs_text":"X"},"Exp-124290":{"tree":["OtherExp"],"text":"!(t<(numSamples+separation))","abs_text":"!X<X+X"},"Exp-124002":{"tree":["Lval",[["Var","p"],null]],"text":"p","abs_text":"X"},"Exp-124104":{"tree":["Lval",[["Var","file"],null]],"text":"file","abs_text":"X"},"Exp-124377":{"tree":["OtherExp"],"text":"*stream.numOutputSamples+newPeriod","abs_text":"X+X"},"Exp-124568":{"tree":["OtherExp"],"text":"maxSamples**file.numChannels","abs_text":"X*X"},"Exp-123948":{"tree":["OtherExp"],"text":"*stream.inputBuffer+(position**stream.numChannels)","abs_text":"X+X*X"},"Exp-123998":{"tree":["OtherExp"],"text":"*stream.inputBuffer+(position**stream.numChannels)","abs_text":"X+X*X"},"Exp-124457":{"tree":["OtherExp"],"text":"*stream.inputBuffer+(position**stream.numChannels)","abs_text":"X+X*X"},"Exp-124204":{"tree":["OtherExp"],"text":"(*stream.inputBufferSize*SizeOf(short ))**stream.numChannels","abs_text":"X*SizeOf*X"},"Exp-124276":{"tree":["OtherExp"],"text":"(*stream.outputBufferSize*SizeOf(short ))**stream.numChannels","abs_text":"X*SizeOf*X"},"Exp-124584":{"tree":["Lval",[["Var","rampDown"],null]],"text":"rampDown","abs_text":"X"},"Exp-124097":{"tree":["Lval",[["Var","stream"],null]],"text":"stream","abs_text":"X"},"Exp-124028":{"tree":["Lval",[["Var","numSamples"],null]],"text":"numSamples","abs_text":"X"},"Exp-124051":{"tree":["Lval",[["Var","numChannels"],null]],"text":"numChannels","abs_text":"X"},"Exp-124182":{"tree":["Lval",[["Var","findPitchPeriod"],null]],"text":"@findPitchPeriod","abs_text":"X"},"Exp-124435":{"tree":["Lval",[["Var","samples"],null]],"text":"samples","abs_text":"X"},"Exp-124607":{"tree":["Const",0],"text":"4096.f","abs_text":"C"},"Exp-123968":{"tree":["Lval",[["Var","position"],null]],"text":"position","abs_text":"X"},"Exp-124226":{"tree":["OtherExp"],"text":"((*d*(numSamples-t))+(*u*t))/numSamples","abs_text":"X*X-X+X*X/X"},"Exp-124295":{"tree":["Lval",[["Var","freeStreamBuffers"],null]],"text":"@freeStreamBuffers","abs_text":"X"},"Exp-124294":{"tree":["OtherExp"],"text":"*stream.numPitchSamples-numSamples","abs_text":"X-X"},"Exp-124515":{"tree":["Lval",[["Var","bytesRead"],null]],"text":"bytesRead","abs_text":"X"},"Exp-124472":{"tree":["OtherExp"],"text":"*stream.prevPeriod==0","abs_text":"X==C"},"Exp-124299":{"tree":["Lval",[["Var","stream"],null]],"text":"stream","abs_text":"X"},"Exp-124487":{"tree":["Lval",[["Var","sampleRate"],null]],"text":"sampleRate","abs_text":"X"},"Exp-124686":{"tree":["Lval",[["Var","volume"],null]],"text":"volume","abs_text":"X"},"Exp-124260":{"tree":["Lval",[["Var","overlapAddWithSeparation"],null]],"text":"@overlapAddWithSeparation","abs_text":"X"},"Exp-124543":{"tree":["OtherExp"],"text":"t+1","abs_text":"X+C"},"Exp-124671":{"tree":["OtherExp"],"text":"t+1","abs_text":"X+C"},"Exp-124288":{"tree":["Lval",[["Var","numSamples"],null]],"text":"numSamples","abs_text":"X"},"Exp-124238":{"tree":["OtherExp"],"text":"!(maxPeriod>*stream.maxPeriod)","abs_text":"!X>X"},"Exp-124234":{"tree":["OtherExp"],"text":"*stream.numInputSamples+(2*maxRequired)","abs_text":"X+C*X"},"Exp-123976":{"tree":["OtherExp"],"text":"*stream.numInputSamples<maxRequired","abs_text":"X<X"},"Exp-124580":{"tree":["OtherExp"],"text":"!(length>10)","abs_text":"!X>C"},"Exp-124184":{"tree":["OtherExp"],"text":"!(*stream.pitch!=1.f)","abs_text":"!X!=C"},"Exp-124382":{"tree":["OtherExp"],"text":"!(*stream.volume!=1.f)","abs_text":"!X!=C"},"Exp-124505":{"tree":["Lval",[["Mem",["Lval",[["Var","u"],null]]],null]],"text":"*u","abs_text":"X"},"Exp-124649":{"tree":["Lval",[["Var","numChannels"],null]],"text":"numChannels","abs_text":"X"},"Exp-123961":{"tree":["Lval",[["Var","stream"],null]],"text":"stream","abs_text":"X"},"Exp-124043":{"tree":["Const",0],"text":"4","abs_text":"C"},"Exp-124157":{"tree":["OtherExp"],"text":"position*numChannels","abs_text":"X*X"},"Exp-124132":{"tree":["OtherExp"],"text":"newSamples==0","abs_text":"X==C"},"Exp-124625":{"tree":["Lval",[["Var","numChannels"],null]],"text":"numChannels","abs_text":"X"},"Exp-124711":{"tree":["Lval",[["Var","__cil_tmp10"],null]],"text":"__cil_tmp10","abs_text":"X"},"Exp-124266":{"tree":["OtherExp"],"text":"*stream.numOutputSamples==originalNumOutputSamples","abs_text":"X==X"},"Exp-124418":{"tree":["OtherExp"],"text":"*stream.numOutputSamples==originalNumOutputSamples","abs_text":"X==X"},"Exp-123983":{"tree":["Lval",[["Var","skip"],null]],"text":"skip","abs_text":"X"},"Exp-124167":{"tree":["OtherExp"],"text":"numSamples!=*stream.numPitchSamples","abs_text":"X!=X"},"Exp-124335":{"tree":["Const",0],"text":"4000","abs_text":"C"},"Exp-123979":{"tree":["Lval",[["Var","maxRequired"],null]],"text":"maxRequired","abs_text":"X"},"Exp-124587":{"tree":["OtherExp"],"text":"inFile==0","abs_text":"X==C"},"Exp-123957":{"tree":["OtherExp"],"text":"value<-32767","abs_text":"X<C"},"Exp-123930":{"tree":["Lval",[["Var","newPeriod"],null]],"text":"newPeriod","abs_text":"X"},"Exp-124106":{"tree":["OtherExp"],"text":"speed<0.5f","abs_text":"X<C"},"Exp-123934":{"tree":["Lval",[["Var","stream"],null]],"text":"stream","abs_text":"X"},"Exp-124594":{"tree":["Lval",[["Var","worstPeriod"],null]],"text":"worstPeriod","abs_text":"X"},"Exp-123970":{"tree":["Lval",[["Var","period"],null]],"text":"period","abs_text":"X"},"Exp-124055":{"tree":["Lval",[["Var","separation"],null]],"text":"separation","abs_text":"X"},"Exp-123975":{"tree":["OtherExp"],"text":"!(*stream.numInputSamples<maxRequired)","abs_text":"!X<X"},"Exp-124508":{"tree":["Lval",[["Var","downSamples"],null]],"text":"downSamples","abs_text":"X"},"Exp-124402":{"tree":["Lval",[["Mem",["Lval",[["Var","stream"],null]]],["Field","rate",null]]],"text":"*stream.rate","abs_text":"X"},"Exp-124527":{"tree":["Lval",[["Mem",["Lval",[["Var","stream"],null]]],["Field","rate",null]]],"text":"*stream.rate","abs_text":"X"},"Exp-124498":{"tree":["Lval",[["Var","o"],null]],"text":"o","abs_text":"X"},"Exp-124388":{"tree":["Lval",[["Var","readFromWaveFile"],null]],"text":"@readFromWaveFile","abs_text":"X"},"Exp-124375":{"tree":["Lval",[["Var","out"],null]],"text":"out","abs_text":"X"},"Exp-124608":{"tree":["OtherExp"],"text":"2*maxPeriod","abs_text":"C*X"},"Exp-124341":{"tree":["OtherExp"],"text":"i>=0","abs_text":"X>=C"},"Exp-124513":{"tree":["OtherExp"],"text":"i>=0","abs_text":"X>=C"},"Exp-124461":{"tree":["OtherExp"],"text":"remainingSamples*SizeOf(short )","abs_text":"X*SizeOf"},"Exp-124701":{"tree":["OtherExp"],"text":"remainingSamples*SizeOf(short )","abs_text":"X*SizeOf"},"Exp-124258":{"tree":["Lval",[["Var","samplesPerValue"],null]],"text":"samplesPerValue","abs_text":"X"},"Exp-124345":{"tree":["Lval",[["Var","__cil_tmp9"],null]],"text":"__cil_tmp9","abs_text":"X"},"Exp-124081":{"tree":["Lval",[["Var","position"],null]],"text":"position","abs_text":"X"},"Exp-124122":{"tree":["Lval",[["Var","buffer"],null]],"text":"buffer","abs_text":"X"},"Exp-123933":{"tree":["Lval",[["Var","samplesRead"],null]],"text":"samplesRead","abs_text":"X"},"Exp-124115":{"tree":["Const",0],"text":"2.f","abs_text":"C"},"Exp-124150":{"tree":["OtherExp"],"text":"sampleRate/400","abs_text":"X/C"},"Exp-124381":{"tree":["Lval",[["Var","expectedOutputSamples"],null]],"text":"expectedOutputSamples","abs_text":"X"},"Exp-123958":{"tree":["Lval",[["Var","value"],null]],"text":"value","abs_text":"X"},"Exp-123951":{"tree":["Lval",[["Var","position"],null]],"text":"position","abs_text":"X"},"Exp-124044":{"tree":["OtherExp"],"text":"*stream.oldRatePosition==oldSampleRate","abs_text":"X==X"},"Exp-124145":{"tree":["Lval",[["Var","remainingSamples"],null]],"text":"remainingSamples","abs_text":"X"},"Exp-123931":{"tree":["Const",0],"text":"0","abs_text":"C"},"Exp-123980":{"tree":["Lval",[["Var","stream"],null]],"text":"stream","abs_text":"X"},"Exp-124101":{"tree":["OtherExp"],"text":"SizeOf(char )","abs_text":"SizeOf"},"Exp-124463":{"tree":["OtherExp"],"text":"in+1","abs_text":"X+C"},"Exp-124538":{"tree":["OtherExp"],"text":"period*(2.f-speed)","abs_text":"X*C-X"},"Exp-124141":{"tree":["OtherExp"],"text":"(((remainingSamples/speed)+*stream.numPitchSamples)/rate)+0.5f","abs_text":"X/X+X/X+C"},"Exp-124462":{"tree":["Lval",[["Var","readShort"],null]],"text":"@readShort","abs_text":"X"},"Exp-124530":{"tree":["OtherExp"],"text":"*stream.outputBuffer+(*stream.numOutputSamples*numChannels)","abs_text":"X+X*X"},"Exp-124598":{"tree":["OtherExp"],"text":"*stream.outputBuffer+(*stream.numOutputSamples*numChannels)","abs_text":"X+X*X"},"Exp-124626":{"tree":["OtherExp"],"text":"*stream.outputBuffer+(*stream.numOutputSamples*numChannels)","abs_text":"X+X*X"},"Exp-124646":{"tree":["OtherExp"],"text":"*stream.outputBuffer+(*stream.numOutputSamples*numChannels)","abs_text":"X+X*X"},"Exp-124200":{"tree":["Const",0],"text":"\\'\\\\000\\'","abs_text":"C"},"Exp-124581":{"tree":["OtherExp"],"text":"length>10","abs_text":"X>C"},"Exp-124255":{"tree":["OtherExp"],"text":"*stream.numOutputSamples-originalNumOutputSamples","abs_text":"X-X"},"Exp-124364":{"tree":["OtherExp"],"text":"*stream.numOutputSamples-originalNumOutputSamples","abs_text":"X-X"},"Exp-124376":{"tree":["Lval",[["Var","i"],null]],"text":"i","abs_text":"X"},"Exp-124264":{"tree":["Lval",[["Var","rampUp"],null]],"text":"rampUp","abs_text":"X"},"Exp-124706":{"tree":["OtherExp"],"text":"samplesRead>0","abs_text":"X>C"},"Exp-124057":{"tree":["Lval",[["Mem",["Lval",[["Var","in"],null]]],null]],"text":"*in","abs_text":"X"},"Exp-124724":{"tree":["OtherExp"],"text":"sampleRate>4000","abs_text":"X>C"},"Exp-124135":{"tree":["Lval",[["Var","position"],null]],"text":"position","abs_text":"X"},"Exp-124120":{"tree":["Lval",[["Var","numChannels"],null]],"text":"numChannels","abs_text":"X"},"Exp-124414":{"tree":["OtherExp"],"text":"!(*stream.newRatePosition!=newSampleRate)","abs_text":"!X!=X"},"Exp-124438":{"tree":["OtherExp"],"text":"pVal-sVal","abs_text":"X-X"},"Exp-124693":{"tree":["OtherExp"],"text":"maxRequired*SizeOf(short )","abs_text":"X*SizeOf"},"Exp-124548":{"tree":["Lval",[["Var","volume"],null]],"text":"volume","abs_text":"X"},"Exp-124218":{"tree":["OtherExp"],"text":"*stream.outputBuffer==0","abs_text":"X==C"},"Exp-124453":{"tree":["OtherExp"],"text":"*stream.outputBuffer==0","abs_text":"X==C"},"Exp-124687":{"tree":["Lval",[["Var","emulateChordPitch"],null]],"text":"emulateChordPitch","abs_text":"X"},"Exp-124659":{"tree":["Lval",[["Var","__cil_tmp13"],null]],"text":"__cil_tmp13","abs_text":"X"},"Exp-124616":{"tree":["Lval",[["Var","minDiff"],null]],"text":"minDiff","abs_text":"X"},"Exp-123959":{"tree":["Const",0],"text":"-32767","abs_text":"C"},"Exp-123932":{"tree":["OtherExp"],"text":"samplesRead==0","abs_text":"X==C"},"Exp-124605":{"tree":["OtherExp"],"text":"volume*4096.f","abs_text":"X*C"},"Exp-124723":{"tree":["Lval",[["Var","skipPitchPeriod"],null]],"text":"@skipPitchPeriod","abs_text":"X"},"Exp-124192":{"tree":["Lval",[["Var","readInt"],null]],"text":"@readInt","abs_text":"X"},"Exp-123944":{"tree":["Lval",[["Var","sampleRate"],null]],"text":"sampleRate","abs_text":"X"},"Exp-124670":{"tree":["OtherExp"],"text":"newPeriod-period","abs_text":"X-X"},"Exp-124491":{"tree":["Lval",[["Var","speed"],null]],"text":"speed","abs_text":"X"},"Exp-124546":{"tree":["OtherExp"],"text":"oldSampleRate>>1","abs_text":"X>>C"},"Exp-124449":{"tree":["OtherExp"],"text":"diff+tmp","abs_text":"X+X"},"Exp-124480":{"tree":["OtherExp"],"text":"((position+period)-newPeriod)*numChannels","abs_text":"X+X-X*X"},"Exp-124251":{"tree":["OtherExp"],"text":"(*stream.oldRatePosition+1)*newSampleRate","abs_text":"X+C*X"},"Exp-124042":{"tree":["OtherExp"],"text":"StartOf(bytes)","abs_text":"X"},"Exp-124329":{"tree":["Lval",[["Var","position"],null]],"text":"position","abs_text":"X"},"Exp-124644":{"tree":["OtherExp"],"text":"*stream.pitchBufferSize>>1","abs_text":"X>>C"},"Exp-124717":{"tree":["Lval",[["Var","rampUp"],null]],"text":"rampUp","abs_text":"X"},"Exp-123995":{"tree":["Lval",[["Var","numChannels"],null]],"text":"numChannels","abs_text":"X"},"Exp-124285":{"tree":["OtherExp"],"text":"*stream.inputBufferSize+((*stream.inputBufferSize>>1)+numSamples)","abs_text":"X+X>>C+X"},"Exp-124419":{"tree":["OtherExp"],"text":"*stream.outputBufferSize+((*stream.outputBufferSize>>1)+numSamples)","abs_text":"X+X>>C+X"},"Exp-124642":{"tree":["OtherExp"],"text":"*stream.pitchBufferSize+((*stream.pitchBufferSize>>1)+numSamples)","abs_text":"X+X>>C+X"},"Exp-124474":{"tree":["Lval",[["Var","stream"],null]],"text":"stream","abs_text":"X"},"Exp-124632":{"tree":["OtherExp"],"text":"downSamples+1","abs_text":"X+C"},"Exp-124215":{"tree":["OtherExp"],"text":"i<numChannels","abs_text":"X<X"},"Exp-124425":{"tree":["OtherExp"],"text":"i<numChannels","abs_text":"X<X"},"Exp-123967":{"tree":["OtherExp"],"text":"position+(period+newSamples)","abs_text":"X+X+X"},"Exp-124473":{"tree":["Lval",[["Mem",["Lval",[["Var","stream"],null]]],["Field","prevPeriod",null]]],"text":"*stream.prevPeriod","abs_text":"X"},"Exp-124708":{"tree":["Lval",[["Mem",["Lval",[["Var","stream"],null]]],["Field","prevPeriod",null]]],"text":"*stream.prevPeriod","abs_text":"X"},"Exp-124277":{"tree":["OtherExp"],"text":"*stream.outputBufferSize*SizeOf(short )","abs_text":"X*SizeOf"},"Exp-123929":{"tree":["Lval",[["Var","stream"],null]],"text":"stream","abs_text":"X"},"Exp-124125":{"tree":["OtherExp"],"text":"(*samples*fixedPointVolume)>>12","abs_text":"X*X>>C"},"Exp-124704":{"tree":["OtherExp"],"text":"!(!(samplesRead>0))","abs_text":"!!X>C"},"Exp-124610":{"tree":["OtherExp"],"text":"(*u*(t-separation))/numSamples","abs_text":"X*X-X/X"},"Exp-124619":{"tree":["OtherExp"],"text":"(*d*(numSamples-t))/numSamples","abs_text":"X*X-X/X"},"Exp-124698":{"tree":["OtherExp"],"text":"numSamples**stream.numChannels","abs_text":"X*X"},"Exp-124385":{"tree":["OtherExp"],"text":"!(speed>=2.f)","abs_text":"!X>=C"},"Exp-124391":{"tree":["Const",0],"text":"2048","abs_text":"C"},"Exp-124475":{"tree":["OtherExp"],"text":"!(remainingSamples>0)","abs_text":"!X>C"},"Exp-124705":{"tree":["OtherExp"],"text":"!(samplesRead>0)","abs_text":"!X>C"},"Exp-124710":{"tree":["OtherExp"],"text":"!(remainingSamples>0)","abs_text":"!X>C"},"Exp-124363":{"tree":["OtherExp"],"text":"(*stream.numOutputSamples-originalNumOutputSamples)**stream.numChannels","abs_text":"X-X*X"},"Exp-124557":{"tree":["Lval",[["Var","samples"],null]],"text":"samples","abs_text":"X"},"Exp-124307":{"tree":["Lval",[["Var","stream"],null]],"text":"stream","abs_text":"X"},"Exp-124497":{"tree":["Lval",[["Var","removeInputSamples"],null]],"text":"@removeInputSamples","abs_text":"X"},"Exp-124119":{"tree":["OtherExp"],"text":"SizeOf(short )*numChannels","abs_text":"SizeOf*X"},"Exp-124654":{"tree":["OtherExp"],"text":"StartOf(buf)","abs_text":"X"},"Exp-124682":{"tree":["Lval",[["Var","runSonic"],null]],"text":"@runSonic","abs_text":"X"},"Exp-124003":{"tree":["Lval",[["Var","moveNewSamplesToPitchBuffer"],null]],"text":"@moveNewSamplesToPitchBuffer","abs_text":"X"},"Exp-124166":{"tree":["OtherExp"],"text":"!(numSamples!=*stream.numPitchSamples)","abs_text":"!X!=X"},"Exp-124128":{"tree":["Lval",[["Var","samples"],null]],"text":"samples","abs_text":"X"},"Exp-124426":{"tree":["OtherExp"],"text":"skip!=1","abs_text":"X!=C"},"Exp-124496":{"tree":["Lval",[["Var","numChannels"],null]],"text":"numChannels","abs_text":"X"},"Exp-124023":{"tree":["Lval",[["Var","position"],null]],"text":"position","abs_text":"X"},"Exp-124300":{"tree":["Lval",[["Var","pitch"],null]],"text":"pitch","abs_text":"X"},"Exp-124500":{"tree":["OtherExp"],"text":"(*d*(numSamples-t))+(*u*(t-separation))","abs_text":"X*X-X+X*X-X"},"Exp-124161":{"tree":["OtherExp"],"text":"out+1","abs_text":"X+C"},"Exp-124105":{"tree":["OtherExp"],"text":"!(speed<0.5f)","abs_text":"!X<C"},"Exp-124225":{"tree":["Lval",[["Var","o"],null]],"text":"o","abs_text":"X"},"Exp-124010":{"tree":["OtherExp"],"text":"(width-ratio)*right","abs_text":"X-X*X"},"Exp-124667":{"tree":["Lval",[["Var","file"],null]],"text":"file","abs_text":"X"},"Exp-123955":{"tree":["Lval",[["Var","period"],null]],"text":"period","abs_text":"X"},"Exp-124007":{"tree":["OtherExp"],"text":"ratio*left","abs_text":"X*X"},"Exp-124149":{"tree":["Lval",[["Var","__cil_tmp4"],null]],"text":"__cil_tmp4","abs_text":"X"},"Exp-124136":{"tree":["OtherExp"],"text":"*stream.downSampleBuffer!=0","abs_text":"X!=C"},"Exp-124038":{"tree":["OtherExp"],"text":"numSamples*SizeOf(short )","abs_text":"X*SizeOf"},"Exp-124559":{"tree":["OtherExp"],"text":"numSamples*SizeOf(short )","abs_text":"X*SizeOf"},"Exp-124640":{"tree":["OtherExp"],"text":"numSamples*SizeOf(short )","abs_text":"X*SizeOf"},"Exp-124142":{"tree":["OtherExp"],"text":"((remainingSamples/speed)+*stream.numPitchSamples)/rate","abs_text":"X/X+X/X"},"Exp-124193":{"tree":["OtherExp"],"text":"(*stream.numOutputSamples+numSamples)>*stream.outputBufferSize","abs_text":"X+X>X"},"Exp-124059":{"tree":["OtherExp"],"text":"sampleRate/65","abs_text":"X/C"},"Exp-124076":{"tree":["Const",0],"text":"14","abs_text":"C"},"Exp-124411":{"tree":["OtherExp"],"text":"*stream.numOutputSamples+(period+newSamples)","abs_text":"X+X+X"},"Exp-124471":{"tree":["Lval",[["Var","value"],null]],"text":"value","abs_text":"X"},"Exp-124139":{"tree":["OtherExp"],"text":"*stream.numOutputSamples+((((remainingSamples/speed)+*stream.numPitchSamples)/rate)+0.5f)","abs_text":"X+X/X+X/X+C"},"Exp-123953":{"tree":["OtherExp"],"text":"samples+period","abs_text":"X+X"},"Exp-124199":{"tree":["Lval",[["Var","length"],null]],"text":"length","abs_text":"X"},"Exp-124203":{"tree":["Lval",[["Var","remainingSamples"],null]],"text":"remainingSamples","abs_text":"X"},"Exp-124091":{"tree":["Lval",[["Var","strlen"],null]],"text":"@strlen","abs_text":"strlen"},"Exp-124344":{"tree":["OtherExp"],"text":"StartOf(inBuffer)","abs_text":"X"},"Exp-124638":{"tree":["OtherExp"],"text":"originalNumOutputSamples*numChannels","abs_text":"X*X"},"Exp-124107":{"tree":["Lval",[["Var","speed"],null]],"text":"speed","abs_text":"X"},"Exp-124169":{"tree":["Lval",[["Var","stream"],null]],"text":"stream","abs_text":"X"},"Exp-124519":{"tree":["OtherExp"],"text":"*stream.outputBuffer+((*stream.numOutputSamples+period)*numChannels)","abs_text":"X+X+X*X"},"Exp-123949":{"tree":["Lval",[["Mem",["Lval",[["Var","stream"],null]]],["Field","inputBuffer",null]]],"text":"*stream.inputBuffer","abs_text":"X"},"Exp-123999":{"tree":["Lval",[["Mem",["Lval",[["Var","stream"],null]]],["Field","inputBuffer",null]]],"text":"*stream.inputBuffer","abs_text":"X"},"Exp-124018":{"tree":["Lval",[["Mem",["Lval",[["Var","stream"],null]]],["Field","inputBuffer",null]]],"text":"*stream.inputBuffer","abs_text":"X"},"Exp-124031":{"tree":["Lval",[["Mem",["Lval",[["Var","stream"],null]]],["Field","inputBuffer",null]]],"text":"*stream.inputBuffer","abs_text":"X"},"Exp-124123":{"tree":["Lval",[["Mem",["Lval",[["Var","stream"],null]]],["Field","inputBuffer",null]]],"text":"*stream.inputBuffer","abs_text":"X"},"Exp-124323":{"tree":["Lval",[["Mem",["Lval",[["Var","stream"],null]]],["Field","inputBuffer",null]]],"text":"*stream.inputBuffer","abs_text":"X"},"Exp-124456":{"tree":["Lval",[["Mem",["Lval",[["Var","stream"],null]]],["Field","inputBuffer",null]]],"text":"*stream.inputBuffer","abs_text":"X"},"Exp-124542":{"tree":["Lval",[["Mem",["Lval",[["Var","stream"],null]]],["Field","inputBuffer",null]]],"text":"*stream.inputBuffer","abs_text":"X"},"Exp-124293":{"tree":["Lval",[["Var","numSamples"],null]],"text":"numSamples","abs_text":"X"},"Exp-123942":{"tree":["Lval",[["Var","numSamples"],null]],"text":"numSamples","abs_text":"X"},"Exp-124084":{"tree":["Lval",[["Var","stream"],null]],"text":"stream","abs_text":"X"},"Exp-124374":{"tree":["OtherExp"],"text":"out+i","abs_text":"X+X"},"Exp-124383":{"tree":["OtherExp"],"text":"out+i","abs_text":"X+X"},"Exp-124180":{"tree":["OtherExp"],"text":"*stream.newRatePosition+1","abs_text":"X+C"},"Exp-124330":{"tree":["Lval",[["Var","diff"],null]],"text":"diff","abs_text":"X"},"Exp-124651":{"tree":["Lval",[["Mem",["Lval",[["Var","__cil_tmp18"],null]]],null]],"text":"*__cil_tmp18","abs_text":"X"},"Exp-124569":{"tree":["Lval",[["Var","maxSamples"],null]],"text":"maxSamples","abs_text":"X"},"Exp-124236":{"tree":["Lval",[["Var","maxRequired"],null]],"text":"maxRequired","abs_text":"X"},"Exp-124144":{"tree":["OtherExp"],"text":"remainingSamples/speed","abs_text":"X/X"},"Exp-124618":{"tree":["Lval",[["Var","__cil_tmp13"],null]],"text":"__cil_tmp13","abs_text":"X"},"Exp-124025":{"tree":["OtherExp"],"text":"(*stream.numPitchSamples+numSamples)>*stream.pitchBufferSize","abs_text":"X+X>X"},"Exp-124029":{"tree":["Lval",[["Var","memcpy"],null]],"text":"@memcpy","abs_text":"memcpy"},"Exp-124560":{"tree":["OtherExp"],"text":"bytePos+1","abs_text":"X+C"},"Exp-124720":{"tree":["Lval",[["Var","oldSampleRate"],null]],"text":"oldSampleRate","abs_text":"X"},"Exp-124440":{"tree":["Lval",[["Var","__cil_tmp5"],null]],"text":"__cil_tmp5","abs_text":"X"},"Exp-123941":{"tree":["Lval",[["Var","t"],null]],"text":"t","abs_text":"X"},"Exp-124545":{"tree":["OtherExp"],"text":"!(!((*stream.numPitchSamples-position)>=*stream.maxRequired))","abs_text":"!!X-X>=X"},"Exp-124468":{"tree":["Lval",[["Mem",["Lval",[["Var","file"],null]]],["Field","numChannels",null]]],"text":"*file.numChannels","abs_text":"X"},"Exp-124517":{"tree":["Lval",[["Mem",["Lval",[["Var","file"],null]]],["Field","numChannels",null]]],"text":"*file.numChannels","abs_text":"X"},"Exp-124596":{"tree":["Lval",[["Var","sonicFlushStream"],null]],"text":"@sonicFlushStream","abs_text":"X"},"Exp-124148":{"tree":["Lval",[["Var","rate"],null]],"text":"rate","abs_text":"X"},"Exp-124172":{"tree":["OtherExp"],"text":"bytes[__cil_tmp12]<<8","abs_text":"X<<C"},"Exp-124263":{"tree":["Lval",[["Var","rampDown"],null]],"text":"rampDown","abs_text":"X"},"Exp-124537":{"tree":["OtherExp"],"text":"(period*(2.f-speed))/(speed-1.f)","abs_text":"X*C-X/X-C"},"Exp-124138":{"tree":["Lval",[["Var","stream"],null]],"text":"stream","abs_text":"X"},"Exp-124026":{"tree":["OtherExp"],"text":"*stream.numPitchSamples+numSamples","abs_text":"X+X"},"Exp-124103":{"tree":["Lval",[["Mem",["Lval",[["Var","file"],null]]],["Field","soundFile",null]]],"text":"*file.soundFile","abs_text":"X"},"Exp-124525":{"tree":["Lval",[["Mem",["Lval",[["Var","file"],null]]],["Field","soundFile",null]]],"text":"*file.soundFile","abs_text":"X"},"Exp-124579":{"tree":["Lval",[["Var","speed"],null]],"text":"speed","abs_text":"X"},"Exp-124126":{"tree":["OtherExp"],"text":"*samples*fixedPointVolume","abs_text":"X*X"},"Exp-124367":{"tree":["OtherExp"],"text":"*stream.sampleRate/rate","abs_text":"X/X"},"Exp-124321":{"tree":["Lval",[["Var","numChannels"],null]],"text":"numChannels","abs_text":"X"},"Exp-124189":{"tree":["OtherExp"],"text":"*stream.numPitchSamples-1","abs_text":"X-C"},"Exp-124070":{"tree":["OtherExp"],"text":"rate!=1.f","abs_text":"X!=C"},"Exp-124550":{"tree":["OtherExp"],"text":"(*stream.numInputSamples+numSamples)>*stream.inputBufferSize","abs_text":"X+X>X"},"Exp-124401":{"tree":["OtherExp"],"text":"*stream.rate**stream.pitch","abs_text":"X*X"},"Exp-124672":{"tree":["Lval",[["Var","fopen"],null]],"text":"@fopen","abs_text":"fopen"},"Exp-124466":{"tree":["Lval",[["Mem",["Lval",[["Var","stream"],null]]],["Field","minPeriod",null]]],"text":"*stream.minPeriod","abs_text":"X"},"Exp-124578":{"tree":["Lval",[["Var","stream"],null]],"text":"stream","abs_text":"X"},"Exp-124102":{"tree":["Lval",[["Var","length"],null]],"text":"length","abs_text":"X"},"Exp-124617":{"tree":["Lval",[["Var","bestPeriod"],null]],"text":"bestPeriod","abs_text":"X"},"Exp-124455":{"tree":["Lval",[["Var","memmove"],null]],"text":"@memmove","abs_text":"memmove"},"Exp-124056":{"tree":["Lval",[["Var","adjustPitch"],null]],"text":"@adjustPitch","abs_text":"X"},"Exp-124371":{"tree":["Lval",[["Var","newSamples"],null]],"text":"newSamples","abs_text":"X"},"Exp-124467":{"tree":["Lval",[["Var","numChannels"],null]],"text":"numChannels","abs_text":"X"},"Exp-124721":{"tree":["Lval",[["Mem",["Lval",[["Var","__cil_tmp17"],null]]],null]],"text":"*__cil_tmp17","abs_text":"X"},"Exp-124181":{"tree":["Lval",[["Mem",["Lval",[["Var","stream"],null]]],["Field","newRatePosition",null]]],"text":"*stream.newRatePosition","abs_text":"X"},"Exp-124719":{"tree":["Lval",[["Mem",["Lval",[["Var","stream"],null]]],["Field","newRatePosition",null]]],"text":"*stream.newRatePosition","abs_text":"X"},"Exp-124726":{"tree":["Lval",[["Var","bytes"],["Index",["Lval",[["Var","i"],null]],null]]],"text":"bytes[i]","abs_text":"X"},"Exp-124191":{"tree":["Lval",[["Var","file"],null]],"text":"file","abs_text":"X"},"Exp-124311":{"tree":["Lval",[["Var","openOutputWaveFile"],null]],"text":"@openOutputWaveFile","abs_text":"X"},"Exp-124332":{"tree":["OtherExp"],"text":"StartOf(bytes)","abs_text":"X"},"Exp-124183":{"tree":["Lval",[["Var","samples"],null]],"text":"samples","abs_text":"X"},"Exp-124004":{"tree":["Lval",[["Var","originalNumOutputSamples"],null]],"text":"originalNumOutputSamples","abs_text":"X"},"Exp-124072":{"tree":["OtherExp"],"text":"!(newSampleRate>(1<<14))","abs_text":"!X>C<<C"},"Exp-124305":{"tree":["OtherExp"],"text":"!(oldSampleRate>(1<<14))","abs_text":"!X>C<<C"},"Exp-124211":{"tree":["Lval",[["Mem",["Lval",[["Var","__cil_tmp10"],null]]],null]],"text":"*__cil_tmp10","abs_text":"X"},"Exp-124165":{"tree":["Lval",[["Var","outFile"],null]],"text":"outFile","abs_text":"X"},"Exp-124054":{"tree":["Lval",[["Var","t"],null]],"text":"t","abs_text":"X"},"Exp-124015":{"tree":["Lval",[["Var","i"],null]],"text":"i","abs_text":"X"},"Exp-124582":{"tree":["Const",0],"text":"10","abs_text":"C"},"Exp-124284":{"tree":["Lval",[["Var","overlapAdd"],null]],"text":"@overlapAdd","abs_text":"X"},"Exp-124555":{"tree":["OtherExp"],"text":"*stream.numOutputSamples**stream.numChannels","abs_text":"X*X"},"Exp-124270":{"tree":["OtherExp"],"text":"*stream.remainingInputToCopy>0","abs_text":"X>C"},"Exp-124609":{"tree":["Lval",[["Var","maxPeriod"],null]],"text":"maxPeriod","abs_text":"X"},"Exp-124393":{"tree":["OtherExp"],"text":"period+(skip<<2)","abs_text":"X+X<<C"},"Exp-124669":{"tree":["Lval",[["Var","speed"],null]],"text":"speed","abs_text":"X"},"Exp-124033":{"tree":["OtherExp"],"text":"*stream.numInputSamples**stream.numChannels","abs_text":"X*X"},"Exp-124514":{"tree":["OtherExp"],"text":"bytesRead/(*file.numChannels*2)","abs_text":"X/X*C"},"Exp-123977":{"tree":["Lval",[["Mem",["Lval",[["Var","stream"],null]]],["Field","numInputSamples",null]]],"text":"*stream.numInputSamples","abs_text":"X"},"Exp-124034":{"tree":["Lval",[["Mem",["Lval",[["Var","stream"],null]]],["Field","numInputSamples",null]]],"text":"*stream.numInputSamples","abs_text":"X"},"Exp-124065":{"tree":["Lval",[["Mem",["Lval",[["Var","stream"],null]]],["Field","numInputSamples",null]]],"text":"*stream.numInputSamples","abs_text":"X"},"Exp-124079":{"tree":["Lval",[["Mem",["Lval",[["Var","stream"],null]]],["Field","numInputSamples",null]]],"text":"*stream.numInputSamples","abs_text":"X"},"Exp-124124":{"tree":["Lval",[["Mem",["Lval",[["Var","stream"],null]]],["Field","numInputSamples",null]]],"text":"*stream.numInputSamples","abs_text":"X"},"Exp-124552":{"tree":["Lval",[["Mem",["Lval",[["Var","stream"],null]]],["Field","numInputSamples",null]]],"text":"*stream.numInputSamples","abs_text":"X"},"Exp-124247":{"tree":["Lval",[["Mem",["OtherExp"]],null]],"text":"*(in+*stream.numChannels)","abs_text":"X"},"Exp-124185":{"tree":["OtherExp"],"text":"*stream.pitch!=1.f","abs_text":"X!=C"},"Exp-124664":{"tree":["OtherExp"],"text":"!(minPeriod<*stream.minPeriod)","abs_text":"!X<X"},"Exp-124005":{"tree":["OtherExp"],"text":"((ratio*left)+((width-ratio)*right))/width","abs_text":"X*X+X-X*X/X"},"Exp-124108":{"tree":["Const",0],"text":"0.5f","abs_text":"C"},"Exp-124227":{"tree":["OtherExp"],"text":"(*d*(numSamples-t))+(*u*t)","abs_text":"X*X-X+X*X"},"Exp-124188":{"tree":["OtherExp"],"text":"position<(*stream.numPitchSamples-1)","abs_text":"X<X-C"},"Exp-124318":{"tree":["OtherExp"],"text":"!(*stream.pitchBuffer!=0)","abs_text":"!X!=C"},"Exp-124447":{"tree":["Lval",[["Var","rampUp"],null]],"text":"rampUp","abs_text":"X"},"Exp-124534":{"tree":["OtherExp"],"text":"!(*stream.downSampleBuffer!=0)","abs_text":"!X!=C"},"Exp-124589":{"tree":["OtherExp"],"text":"!(*stream.inputBuffer!=0)","abs_text":"!X!=C"},"Exp-124709":{"tree":["OtherExp"],"text":"!(*stream.outputBuffer!=0)","abs_text":"!X!=C"},"Exp-124201":{"tree":["Lval",[["Var","__cil_tmp13"],null]],"text":"__cil_tmp13","abs_text":"X"},"Exp-124333":{"tree":["OtherExp"],"text":"sampleRate/4000","abs_text":"X/C"},"Exp-124008":{"tree":["Lval",[["Var","ratio"],null]],"text":"ratio","abs_text":"X"},"Exp-124601":{"tree":["OtherExp"],"text":"speed<0.999990000001","abs_text":"X<C"},"Exp-123954":{"tree":["Lval",[["Var","samples"],null]],"text":"samples","abs_text":"X"},"Exp-124265":{"tree":["OtherExp"],"text":"!(*stream.numOutputSamples==originalNumOutputSamples)","abs_text":"!X==X"},"Exp-124417":{"tree":["OtherExp"],"text":"!(*stream.numOutputSamples==originalNumOutputSamples)","abs_text":"!X==X"},"Exp-124197":{"tree":["Lval",[["Var","numSamples"],null]],"text":"numSamples","abs_text":"X"},"Exp-124680":{"tree":["Const",0],"text":"1.","abs_text":"C"},"Exp-124688":{"tree":["Lval",[["Var","quality"],null]],"text":"quality","abs_text":"X"},"Exp-124304":{"tree":["Const",0],"text":"1.00001000001","abs_text":"C"},"Exp-124575":{"tree":["OtherExp"],"text":"period<=maxPeriod","abs_text":"X<=X"},"Exp-124657":{"tree":["Lval",[["Var","preferNewPeriod"],null]],"text":"preferNewPeriod","abs_text":"X"},"Exp-124678":{"tree":["OtherExp"],"text":"!(speed>1.)","abs_text":"!X>C"},"Exp-124112":{"tree":["Lval",[["Var","period"],null]],"text":"period","abs_text":"X"},"Exp-124606":{"tree":["Lval",[["Var","volume"],null]],"text":"volume","abs_text":"X"},"Exp-124324":{"tree":["Lval",[["Var","samples"],null]],"text":"samples","abs_text":"X"},"Exp-124615":{"tree":["OtherExp"],"text":"minDiff/bestPeriod","abs_text":"X/X"},"Exp-124269":{"tree":["OtherExp"],"text":"!(*stream.remainingInputToCopy>0)","abs_text":"!X>C"},"Exp-123928":{"tree":["Lval",[["Var","enlargeOutputBufferIfNeeded"],null]],"text":"@enlargeOutputBufferIfNeeded","abs_text":"X"},"Exp-123943":{"tree":["Lval",[["Var","stream"],null]],"text":"stream","abs_text":"X"},"Exp-124380":{"tree":["OtherExp"],"text":"*stream.numOutputSamples>expectedOutputSamples","abs_text":"X>X"},"Exp-124623":{"tree":["Lval",[["Var","file"],null]],"text":"file","abs_text":"X"},"Exp-124292":{"tree":["OtherExp"],"text":"numSamples+separation","abs_text":"X+X"},"Exp-124262":{"tree":["Lval",[["Var","out"],null]],"text":"out","abs_text":"X"},"Exp-124665":{"tree":["OtherExp"],"text":"minPeriod<*stream.minPeriod","abs_text":"X<X"},"Exp-124243":{"tree":["Lval",[["Var","value"],null]],"text":"value","abs_text":"X"},"Exp-124692":{"tree":["Lval",[["Var","rampDown"],null]],"text":"rampDown","abs_text":"X"},"Exp-123981":{"tree":["OtherExp"],"text":"period*skip","abs_text":"X*X"},"Exp-124436":{"tree":["OtherExp"],"text":"period*numChannels","abs_text":"X*X"},"Exp-124631":{"tree":["OtherExp"],"text":"period*numChannels","abs_text":"X*X"},"Exp-124083":{"tree":["Lval",[["Var","addShortSamplesToInputBuffer"],null]],"text":"@addShortSamplesToInputBuffer","abs_text":"X"},"Exp-124111":{"tree":["OtherExp"],"text":"period*((2.f*speed)-1.f)","abs_text":"X*C*X-C"},"Exp-124509":{"tree":["OtherExp"],"text":"value|bytes[i]","abs_text":"X|X"},"Exp-124725":{"tree":["OtherExp"],"text":"value|bytes[i]","abs_text":"X|X"},"Exp-124030":{"tree":["OtherExp"],"text":"*stream.inputBuffer+(*stream.numInputSamples**stream.numChannels)","abs_text":"X+X*X"},"Exp-124319":{"tree":["OtherExp"],"text":"u+numChannels","abs_text":"X+X"},"Exp-124410":{"tree":["OtherExp"],"text":"u+numChannels","abs_text":"X+X"},"Exp-124464":{"tree":["Lval",[["Var","in"],null]],"text":"in","abs_text":"X"},"Exp-123950":{"tree":["OtherExp"],"text":"position**stream.numChannels","abs_text":"X*X"},"Exp-124000":{"tree":["OtherExp"],"text":"position**stream.numChannels","abs_text":"X*X"},"Exp-124458":{"tree":["OtherExp"],"text":"position**stream.numChannels","abs_text":"X*X"},"Exp-124113":{"tree":["OtherExp"],"text":"(2.f*speed)-1.f","abs_text":"C*X-C"},"Exp-124629":{"tree":["Lval",[["Var","samples"],null]],"text":"samples","abs_text":"X"},"Exp-124254":{"tree":["Lval",[["Var","newSampleRate"],null]],"text":"newSampleRate","abs_text":"X"},"Exp-124407":{"tree":["OtherExp"],"text":"sVal-pVal","abs_text":"X-X"},"Exp-124217":{"tree":["OtherExp"],"text":"rate**stream.pitch","abs_text":"X*X"},"Exp-124566":{"tree":["OtherExp"],"text":"StartOf(bytes)","abs_text":"X"},"Exp-124465":{"tree":["OtherExp"],"text":"o+numChannels","abs_text":"X+X"},"Exp-124561":{"tree":["OtherExp"],"text":"o+numChannels","abs_text":"X+X"},"Exp-124014":{"tree":["OtherExp"],"text":"i-1","abs_text":"X-C"},"Exp-124585":{"tree":["OtherExp"],"text":"i-1","abs_text":"X-C"},"Exp-124567":{"tree":["OtherExp"],"text":"(maxSamples**file.numChannels)*2","abs_text":"X*X*C"},"Exp-124650":{"tree":["Lval",[["Var","__cil_tmp5"],null]],"text":"__cil_tmp5","abs_text":"X"},"Exp-124067":{"tree":["Lval",[["Var","sonicCreateStream"],null]],"text":"@sonicCreateStream","abs_text":"X"},"Exp-124446":{"tree":["OtherExp"],"text":"rampUp+i","abs_text":"X+X"},"Exp-124716":{"tree":["OtherExp"],"text":"rampUp+i","abs_text":"X+X"},"Exp-124676":{"tree":["OtherExp"],"text":"minPeriod/skip","abs_text":"X/X"},"Exp-124207":{"tree":["Lval",[["Var","stream"],null]],"text":"stream","abs_text":"X"},"Exp-124652":{"tree":["Lval",[["Var","__cil_tmp18"],null]],"text":"__cil_tmp18","abs_text":"X"},"Exp-124372":{"tree":["Lval",[["Var","closeFile"],null]],"text":"@closeFile","abs_text":"X"},"Exp-124485":{"tree":["Lval",[["Var","sonicReadShortFromStream"],null]],"text":"@sonicReadShortFromStream","abs_text":"X"},"Exp-124077":{"tree":["Lval",[["Var","bytePos"],null]],"text":"bytePos","abs_text":"X"},"Exp-124272":{"tree":["OtherExp"],"text":"sVal>=pVal","abs_text":"X>=X"},"Exp-124287":{"tree":["OtherExp"],"text":"*stream.inputBufferSize>>1","abs_text":"X>>C"},"Exp-124048":{"tree":["Lval",[["Var","allocateStreamBuffers"],null]],"text":"@allocateStreamBuffers","abs_text":"X"},"Exp-123985":{"tree":["Lval",[["Mem",["Lval",[["Var","stream"],null]]],["Field","volume",null]]],"text":"*stream.volume","abs_text":"X"},"Exp-124022":{"tree":["Lval",[["Var","removePitchSamples"],null]],"text":"@removePitchSamples","abs_text":"X"},"Exp-124099":{"tree":["Lval",[["Var","fread"],null]],"text":"@fread","abs_text":"fread"},"Exp-124194":{"tree":["OtherExp"],"text":"*stream.numOutputSamples+numSamples","abs_text":"X+X"},"Exp-124395":{"tree":["OtherExp"],"text":"*stream.numOutputSamples+numSamples","abs_text":"X+X"},"Exp-124036":{"tree":["Lval",[["Var","samples"],null]],"text":"samples","abs_text":"X"},"Exp-124483":{"tree":["Lval",[["Var","period"],null]],"text":"period","abs_text":"X"},"Exp-124314":{"tree":["Lval",[["Var","numChannels"],null]],"text":"numChannels","abs_text":"X"},"Exp-124343":{"tree":["OtherExp"],"text":"pitch>=1.f","abs_text":"X>=C"},"Exp-124677":{"tree":["OtherExp"],"text":"maxPeriod/skip","abs_text":"X/X"},"Exp-124087":{"tree":["Lval",[["Var","stream"],null]],"text":"stream","abs_text":"X"},"Exp-124116":{"tree":["OtherExp"],"text":"1.f-speed","abs_text":"C-X"},"Exp-124421":{"tree":["OtherExp"],"text":"*stream.outputBufferSize>>1","abs_text":"X>>C"},"Exp-124248":{"tree":["OtherExp"],"text":"in+*stream.numChannels","abs_text":"X+X"},"Exp-124614":{"tree":["Lval",[["Var","retMinDiff"],null]],"text":"retMinDiff","abs_text":"X"},"Exp-124237":{"tree":["OtherExp"],"text":"*stream.numInputSamples+numSamples","abs_text":"X+X"},"Exp-124551":{"tree":["OtherExp"],"text":"*stream.numInputSamples+numSamples","abs_text":"X+X"},"Exp-124137":{"tree":["Lval",[["Mem",["Lval",[["Var","stream"],null]]],["Field","downSampleBuffer",null]]],"text":"*stream.downSampleBuffer","abs_text":"X"},"Exp-124522":{"tree":["OtherExp"],"text":"*stream.numOutputSamples+period","abs_text":"X+X"},"Exp-124533":{"tree":["Lval",[["Mem",["Lval",[["Var","stream"],null]]],["Field","downSampleBuffer",null]]],"text":"*stream.downSampleBuffer","abs_text":"X"},"Exp-124544":{"tree":["Lval",[["Mem",["Lval",[["Var","stream"],null]]],["Field","downSampleBuffer",null]]],"text":"*stream.downSampleBuffer","abs_text":"X"},"Exp-124663":{"tree":["Lval",[["Mem",["Lval",[["Var","stream"],null]]],["Field","downSampleBuffer",null]]],"text":"*stream.downSampleBuffer","abs_text":"X"},"Exp-123997":{"tree":["Lval",[["Var","rate"],null]],"text":"rate","abs_text":"X"},"Exp-124063":{"tree":["Lval",[["Var","numSamples"],null]],"text":"numSamples","abs_text":"X"},"Exp-124177":{"tree":["OtherExp"],"text":"value>32767","abs_text":"X>C"},"Exp-124387":{"tree":["Lval",[["Var","speed"],null]],"text":"speed","abs_text":"X"},"Exp-124334":{"tree":["Lval",[["Var","sampleRate"],null]],"text":"sampleRate","abs_text":"X"},"Exp-124013":{"tree":["Lval",[["Var","right"],null]],"text":"right","abs_text":"X"},"Exp-124666":{"tree":["Lval",[["Var","__cil_tmp6"],null]],"text":"__cil_tmp6","abs_text":"X"},"Exp-123993":{"tree":["Lval",[["Var","stream"],null]],"text":"stream","abs_text":"X"},"Exp-124134":{"tree":["Lval",[["Mem",["Lval",[["Var","stream"],null]]],["Field","pitchBuffer",null]]],"text":"*stream.pitchBuffer","abs_text":"X"},"Exp-124156":{"tree":["Lval",[["Mem",["Lval",[["Var","stream"],null]]],["Field","pitchBuffer",null]]],"text":"*stream.pitchBuffer","abs_text":"X"},"Exp-124160":{"tree":["Lval",[["Mem",["Lval",[["Var","stream"],null]]],["Field","pitchBuffer",null]]],"text":"*stream.pitchBuffer","abs_text":"X"},"Exp-124492":{"tree":["Lval",[["Mem",["Lval",[["Var","stream"],null]]],["Field","pitchBuffer",null]]],"text":"*stream.pitchBuffer","abs_text":"X"},"Exp-124564":{"tree":["Lval",[["Mem",["Lval",[["Var","stream"],null]]],["Field","pitchBuffer",null]]],"text":"*stream.pitchBuffer","abs_text":"X"},"Exp-124612":{"tree":["Lval",[["Mem",["Lval",[["Var","stream"],null]]],["Field","pitchBuffer",null]]],"text":"*stream.pitchBuffer","abs_text":"X"},"Exp-124275":{"tree":["OtherExp"],"text":"samples+1","abs_text":"X+C"},"Exp-124571":{"tree":["OtherExp"],"text":"numSamples*numChannels","abs_text":"X*X"},"Exp-124714":{"tree":["OtherExp"],"text":"samples+1","abs_text":"X+C"},"Exp-124019":{"tree":["OtherExp"],"text":"!(numSamples>*stream.maxRequired)","abs_text":"!X>X"},"Exp-124118":{"tree":["Lval",[["Var","maxRequired"],null]],"text":"maxRequired","abs_text":"X"},"Exp-124310":{"tree":["Lval",[["Var","newSamples"],null]],"text":"newSamples","abs_text":"X"},"Exp-124445":{"tree":["Lval",[["Var","soundFile"],null]],"text":"soundFile","abs_text":"X"},"Exp-124230":{"tree":["OtherExp"],"text":"numSamples-t","abs_text":"X-X"},"Exp-124315":{"tree":["OtherExp"],"text":"numSamples-maxSamples","abs_text":"X-X"},"Exp-124384":{"tree":["Lval",[["Var","out"],null]],"text":"out","abs_text":"X"},"Exp-124503":{"tree":["OtherExp"],"text":"numSamples-t","abs_text":"X-X"},"Exp-124020":{"tree":["OtherExp"],"text":"numSamples>*stream.maxRequired","abs_text":"X>X"},"Exp-124176":{"tree":["OtherExp"],"text":"!(value>32767)","abs_text":"!X>C"},"Exp-124100":{"tree":["Lval",[["Var","bytes"],null]],"text":"bytes","abs_text":"X"},"Exp-124302":{"tree":["OtherExp"],"text":"speed>1.00001000001","abs_text":"X>C"},"Exp-124153":{"tree":["OtherExp"],"text":"skip<<2","abs_text":"X<<C"},"Exp-123947":{"tree":["Lval",[["Var","copyToOutput"],null]],"text":"@copyToOutput","abs_text":"X"},"Exp-124130":{"tree":["Const",0],"text":"12","abs_text":"C"},"Exp-123960":{"tree":["Lval",[["Var","adjustRate"],null]],"text":"@adjustRate","abs_text":"X"},"Exp-124488":{"tree":["Lval",[["Mem",["Lval",[["Var","file"],null]]],["Field","sampleRate",null]]],"text":"*file.sampleRate","abs_text":"X"},"Exp-124518":{"tree":["Lval",[["Var","file"],null]],"text":"file","abs_text":"X"},"Exp-124635":{"tree":["OtherExp"],"text":"*stream.numPitchSamples*numChannels","abs_text":"X*X"},"Exp-124198":{"tree":["Lval",[["Mem",["Lval",[["Var","stream"],null]]],["Field","outputBufferSize",null]]],"text":"*stream.outputBufferSize","abs_text":"X"},"Exp-124223":{"tree":["Lval",[["Var","pitch"],null]],"text":"pitch","abs_text":"X"},"Exp-124379":{"tree":["OtherExp"],"text":"!(*stream.numOutputSamples>expectedOutputSamples)","abs_text":"!X>X"},"Exp-124641":{"tree":["OtherExp"],"text":"newSampleRate>>1","abs_text":"X>>C"},"Exp-124431":{"tree":["Lval",[["Var","s"],null]],"text":"s","abs_text":"X"},"Exp-124442":{"tree":["Lval",[["Var","__cil_tmp12"],null]],"text":"__cil_tmp12","abs_text":"X"},"Exp-123966":{"tree":["Lval",[["Var","remainingSamples"],null]],"text":"remainingSamples","abs_text":"X"},"Exp-124220":{"tree":["OtherExp"],"text":"p+1","abs_text":"X+C"},"Exp-124427":{"tree":["Lval",[["Var","inFile"],null]],"text":"inFile","abs_text":"X"},"Exp-124489":{"tree":["Lval",[["Var","__cil_tmp14"],null]],"text":"__cil_tmp14","abs_text":"X"},"Exp-123971":{"tree":["Lval",[["Var","newSamples"],null]],"text":"newSamples","abs_text":"X"},"Exp-124114":{"tree":["OtherExp"],"text":"2.f*speed","abs_text":"C*X"},"Exp-124143":{"tree":["OtherExp"],"text":"(remainingSamples/speed)+*stream.numPitchSamples","abs_text":"X/X+X"},"Exp-124486":{"tree":["OtherExp"],"text":"StartOf(outBuffer)","abs_text":"X"},"Exp-124448":{"tree":["OtherExp"],"text":"period+1","abs_text":"X+C"},"Exp-124361":{"tree":["OtherExp"],"text":"originalNumOutputSamples**stream.numChannels","abs_text":"X*X"},"Exp-124577":{"tree":["Lval",[["Var","__cil_tmp12"],null]],"text":"__cil_tmp12","abs_text":"X"},"Exp-124313":{"tree":["Lval",[["Var","sampleRate"],null]],"text":"sampleRate","abs_text":"X"},"Exp-124394":{"tree":["Lval",[["Var","stream"],null]],"text":"stream","abs_text":"X"},"Exp-124683":{"tree":["Lval",[["Var","speed"],null]],"text":"speed","abs_text":"X"},"Exp-124228":{"tree":["OtherExp"],"text":"*d*(numSamples-t)","abs_text":"X*X-X"},"Exp-124501":{"tree":["OtherExp"],"text":"*d*(numSamples-t)","abs_text":"X*X-X"},"Exp-124504":{"tree":["OtherExp"],"text":"*u*(t-separation)","abs_text":"X*X-X"},"Exp-124535":{"tree":["OtherExp"],"text":"(period*SizeOf(short ))*numChannels","abs_text":"X*SizeOf*X"},"Exp-124639":{"tree":["OtherExp"],"text":"(numSamples*SizeOf(short ))*numChannels","abs_text":"X*SizeOf*X"},"Exp-124110":{"tree":["OtherExp"],"text":"(period*((2.f*speed)-1.f))/(1.f-speed)","abs_text":"X*C*X-C/C-X"},"Exp-124350":{"tree":["Lval",[["Var","findPitchPeriodInRange"],null]],"text":"@findPitchPeriodInRange","abs_text":"X"},"Exp-124336":{"tree":["Lval",[["Var","__cil_tmp8"],null]],"text":"__cil_tmp8","abs_text":"X"},"Exp-124478":{"tree":["OtherExp"],"text":"i+1","abs_text":"X+C"},"Exp-124507":{"tree":["OtherExp"],"text":"i+1","abs_text":"X+C"},"Exp-124441":{"tree":["Lval",[["Var","expectString"],null]],"text":"@expectString","abs_text":"X"},"Exp-124089":{"tree":["Lval",[["Var","stream"],null]],"text":"stream","abs_text":"X"},"Exp-124280":{"tree":["OtherExp"],"text":"(*stream.numPitchSamples-position)>=*stream.maxRequired","abs_text":"X-X>=X"},"Exp-124526":{"tree":["Lval",[["Var","file"],null]],"text":"file","abs_text":"X"},"Exp-124080":{"tree":["Lval",[["Var","stream"],null]],"text":"stream","abs_text":"X"},"Exp-124316":{"tree":["Lval",[["Var","sonicSetPitch"],null]],"text":"@sonicSetPitch","abs_text":"X"},"Exp-124214":{"tree":["OtherExp"],"text":"!(i<numChannels)","abs_text":"!X<X"},"Exp-124250":{"tree":["Lval",[["Var","stream"],null]],"text":"stream","abs_text":"X"},"Exp-124424":{"tree":["OtherExp"],"text":"!(i<numChannels)","abs_text":"!X<X"},"Exp-124702":{"tree":["Lval",[["Var","copyInputToOutput"],null]],"text":"@copyInputToOutput","abs_text":"X"},"Exp-124221":{"tree":["OtherExp"],"text":"period/pitch","abs_text":"X/X"},"Exp-124291":{"tree":["OtherExp"],"text":"t<(numSamples+separation)","abs_text":"X<X+X"},"Exp-124482":{"tree":["OtherExp"],"text":"period/(speed-1.f)","abs_text":"X/X-C"},"Exp-124039":{"tree":["Lval",[["Var","numSamples"],null]],"text":"numSamples","abs_text":"X"},"Exp-124308":{"tree":["OtherExp"],"text":"*stream.numOutputSamples+newSamples","abs_text":"X+X"},"Exp-124406":{"tree":["Lval",[["Var","rate"],null]],"text":"rate","abs_text":"X"},"Exp-124151":{"tree":["Const",0],"text":"400","abs_text":"C"},"Exp-124718":{"tree":["OtherExp"],"text":"*stream.newRatePosition*oldSampleRate","abs_text":"X*X"},"Exp-123989":{"tree":["Lval",[["Mem",["Lval",[["Var","stream"],null]]],["Field","pitch",null]]],"text":"*stream.pitch","abs_text":"X"},"Exp-124246":{"tree":["Lval",[["Mem",["Lval",[["Var","stream"],null]]],["Field","pitch",null]]],"text":"*stream.pitch","abs_text":"X"},"Exp-124356":{"tree":["Lval",[["Var","closeWaveFile"],null]],"text":"@closeWaveFile","abs_text":"X"},"Exp-124624":{"tree":["Lval",[["Mem",["Lval",[["Var","stream"],null]]],["Field","pitch",null]]],"text":"*stream.pitch","abs_text":"X"},"Exp-124017":{"tree":["OtherExp"],"text":"*stream.inputBuffer==0","abs_text":"X==C"},"Exp-124320":{"tree":["Lval",[["Var","u"],null]],"text":"u","abs_text":"X"},"Exp-124479":{"tree":["OtherExp"],"text":"*stream.pitchBuffer+(((position+period)-newPeriod)*numChannels)","abs_text":"X+X+X-X*X"},"Exp-124541":{"tree":["OtherExp"],"text":"*stream.inputBuffer==0","abs_text":"X==C"},"Exp-124179":{"tree":["Lval",[["Var","__cil_tmp12"],null]],"text":"__cil_tmp12","abs_text":"X"},"Exp-124289":{"tree":["OtherExp"],"text":"!(!(t<(numSamples+separation)))","abs_text":"!!X<X+X"},"Exp-124428":{"tree":["OtherExp"],"text":"*stream.oldRatePosition*newSampleRate","abs_text":"X*X"},"Exp-123945":{"tree":["Lval",[["Mem",["Lval",[["Var","stream"],null]]],["Field","numOutputSamples",null]]],"text":"*stream.numOutputSamples","abs_text":"X"},"Exp-124024":{"tree":["Lval",[["Mem",["Lval",[["Var","stream"],null]]],["Field","numOutputSamples",null]]],"text":"*stream.numOutputSamples","abs_text":"X"},"Exp-124060":{"tree":["Const",0],"text":"65","abs_text":"C"},"Exp-124140":{"tree":["Lval",[["Mem",["Lval",[["Var","stream"],null]]],["Field","numOutputSamples",null]]],"text":"*stream.numOutputSamples","abs_text":"X"},"Exp-124195":{"tree":["Lval",[["Mem",["Lval",[["Var","stream"],null]]],["Field","numOutputSamples",null]]],"text":"*stream.numOutputSamples","abs_text":"X"},"Exp-124256":{"tree":["Lval",[["Mem",["Lval",[["Var","stream"],null]]],["Field","numOutputSamples",null]]],"text":"*stream.numOutputSamples","abs_text":"X"},"Exp-124267":{"tree":["Lval",[["Mem",["Lval",[["Var","stream"],null]]],["Field","numOutputSamples",null]]],"text":"*stream.numOutputSamples","abs_text":"X"},"Exp-124309":{"tree":["Lval",[["Mem",["Lval",[["Var","stream"],null]]],["Field","numOutputSamples",null]]],"text":"*stream.numOutputSamples","abs_text":"X"},"Exp-124378":{"tree":["Lval",[["Mem",["Lval",[["Var","stream"],null]]],["Field","numOutputSamples",null]]],"text":"*stream.numOutputSamples","abs_text":"X"},"Exp-124396":{"tree":["Lval",[["Mem",["Lval",[["Var","stream"],null]]],["Field","numOutputSamples",null]]],"text":"*stream.numOutputSamples","abs_text":"X"},"Exp-124412":{"tree":["Lval",[["Mem",["Lval",[["Var","stream"],null]]],["Field","numOutputSamples",null]]],"text":"*stream.numOutputSamples","abs_text":"X"},"Exp-124274":{"tree":["Lval",[["Var","pVal"],null]],"text":"pVal","abs_text":"X"},"Exp-123939":{"tree":["OtherExp"],"text":"!(t<numSamples)","abs_text":"!X<X"},"Exp-124052":{"tree":["OtherExp"],"text":"!(t<separation)","abs_text":"!X<X"},"Exp-124430":{"tree":["OtherExp"],"text":"!(t<numSamples)","abs_text":"!X<X"},"Exp-124573":{"tree":["OtherExp"],"text":"!(!(period<=maxPeriod))","abs_text":"!!X<=X"},"Exp-123974":{"tree":["Lval",[["Var","numSamples"],null]],"text":"numSamples","abs_text":"X"},"Exp-124233":{"tree":["Lval",[["Var","u"],null]],"text":"u","abs_text":"X"},"Exp-124049":{"tree":["Lval",[["Var","stream"],null]],"text":"stream","abs_text":"X"},"Exp-124085":{"tree":["Lval",[["Var","samples"],null]],"text":"samples","abs_text":"X"},"Exp-124712":{"tree":["OtherExp"],"text":"buffer+1","abs_text":"X+C"},"Exp-124439":{"tree":["Lval",[["Var","minPeriod"],null]],"text":"minPeriod","abs_text":"X"},"Exp-124073":{"tree":["OtherExp"],"text":"newSampleRate>(1<<14)","abs_text":"X>C<<C"},"Exp-124306":{"tree":["OtherExp"],"text":"oldSampleRate>(1<<14)","abs_text":"X>C<<C"},"Exp-124565":{"tree":["Lval",[["Var","readBytes"],null]],"text":"@readBytes","abs_text":"X"},"Exp-124146":{"tree":["Lval",[["Var","speed"],null]],"text":"speed","abs_text":"X"},"Exp-124257":{"tree":["OtherExp"],"text":"value/samplesPerValue","abs_text":"X/X"},"Exp-124093":{"tree":["OtherExp"],"text":"*stream.numChannels*skip","abs_text":"X*X"},"Exp-124239":{"tree":["OtherExp"],"text":"maxPeriod>*stream.maxPeriod","abs_text":"X>X"},"Exp-124273":{"tree":["Lval",[["Var","sVal"],null]],"text":"sVal","abs_text":"X"},"Exp-124328":{"tree":["Lval",[["Var","rightPosition"],null]],"text":"rightPosition","abs_text":"X"},"Exp-123927":{"tree":["Lval",[["Var","numChannels"],null]],"text":"numChannels","abs_text":"X"},"Exp-124259":{"tree":["Lval",[["Var","originalNumOutputSamples"],null]],"text":"originalNumOutputSamples","abs_text":"X"},"Exp-123996":{"tree":["Lval",[["Var","stream"],null]],"text":"stream","abs_text":"X"},"Exp-124069":{"tree":["Lval",[["Var","numChannels"],null]],"text":"numChannels","abs_text":"X"},"Exp-124352":{"tree":["Lval",[["Var","minPeriod"],null]],"text":"minPeriod","abs_text":"X"},"Exp-124325":{"tree":["Lval",[["Var","sonicWriteShortToStream"],null]],"text":"@sonicWriteShortToStream","abs_text":"X"},"Exp-123965":{"tree":["OtherExp"],"text":"remainingSamples>0","abs_text":"X>C"},"Exp-124202":{"tree":["OtherExp"],"text":"remainingSamples>0","abs_text":"X>C"},"Exp-124322":{"tree":["OtherExp"],"text":"*stream.inputBuffer!=0","abs_text":"X!=C"},"Exp-124477":{"tree":["OtherExp"],"text":"skip==1","abs_text":"X==C"},"Exp-124090":{"tree":["Lval",[["Var","minDiff"],null]],"text":"minDiff","abs_text":"X"},"Exp-124531":{"tree":["OtherExp"],"text":"*stream.numOutputSamples*numChannels","abs_text":"X*X"},"Exp-124600":{"tree":["OtherExp"],"text":"*stream.numOutputSamples*numChannels","abs_text":"X*X"},"Exp-124628":{"tree":["OtherExp"],"text":"*stream.numOutputSamples*numChannels","abs_text":"X*X"},"Exp-124648":{"tree":["OtherExp"],"text":"*stream.numOutputSamples*numChannels","abs_text":"X*X"},"Exp-124219":{"tree":["Lval",[["Mem",["Lval",[["Var","stream"],null]]],["Field","outputBuffer",null]]],"text":"*stream.outputBuffer","abs_text":"X"},"Exp-124360":{"tree":["Lval",[["Mem",["Lval",[["Var","stream"],null]]],["Field","outputBuffer",null]]],"text":"*stream.outputBuffer","abs_text":"X"},"Exp-124404":{"tree":["Lval",[["Mem",["Lval",[["Var","stream"],null]]],["Field","outputBuffer",null]]],"text":"*stream.outputBuffer","abs_text":"X"},"Exp-124454":{"tree":["Lval",[["Mem",["Lval",[["Var","stream"],null]]],["Field","outputBuffer",null]]],"text":"*stream.outputBuffer","abs_text":"X"},"Exp-124520":{"tree":["Lval",[["Mem",["Lval",[["Var","stream"],null]]],["Field","outputBuffer",null]]],"text":"*stream.outputBuffer","abs_text":"X"},"Exp-124554":{"tree":["Lval",[["Mem",["Lval",[["Var","stream"],null]]],["Field","outputBuffer",null]]],"text":"*stream.outputBuffer","abs_text":"X"},"Exp-124599":{"tree":["Lval",[["Mem",["Lval",[["Var","stream"],null]]],["Field","outputBuffer",null]]],"text":"*stream.outputBuffer","abs_text":"X"},"Exp-124627":{"tree":["Lval",[["Mem",["Lval",[["Var","stream"],null]]],["Field","outputBuffer",null]]],"text":"*stream.outputBuffer","abs_text":"X"},"Exp-124637":{"tree":["Lval",[["Mem",["Lval",[["Var","stream"],null]]],["Field","outputBuffer",null]]],"text":"*stream.outputBuffer","abs_text":"X"},"Exp-124647":{"tree":["Lval",[["Mem",["Lval",[["Var","stream"],null]]],["Field","outputBuffer",null]]],"text":"*stream.outputBuffer","abs_text":"X"},"Exp-124696":{"tree":["Lval",[["Mem",["Lval",[["Var","stream"],null]]],["Field","outputBuffer",null]]],"text":"*stream.outputBuffer","abs_text":"X"},"Exp-123946":{"tree":["Lval",[["Var","stream"],null]],"text":"stream","abs_text":"X"},"Exp-124012":{"tree":["Lval",[["Var","width"],null]],"text":"width","abs_text":"X"},"Exp-124078":{"tree":["OtherExp"],"text":"*stream.numInputSamples-position","abs_text":"X-X"},"Exp-123992":{"tree":["Lval",[["Mem",["Lval",[["Var","stream"],null]]],["Field","pitchBufferSize",null]]],"text":"*stream.pitchBufferSize","abs_text":"X"},"Exp-124655":{"tree":["Lval",[["Var","prevPeriodBetter"],null]],"text":"@prevPeriodBetter","abs_text":"X"},"Exp-124685":{"tree":["Lval",[["Var","rate"],null]],"text":"rate","abs_text":"X"},"Exp-124469":{"tree":["Lval",[["Var","file"],null]],"text":"file","abs_text":"X"},"Exp-124490":{"tree":["Lval",[["Var","sonicSetSpeed"],null]],"text":"@sonicSetSpeed","abs_text":"X"},"Exp-124572":{"tree":["Lval",[["Var","samplesRead"],null]],"text":"samplesRead","abs_text":"X"},"Exp-123978":{"tree":["Lval",[["Var","stream"],null]],"text":"stream","abs_text":"X"},"Exp-124370":{"tree":["OtherExp"],"text":"period+newSamples","abs_text":"X+X"},"Exp-124127":{"tree":["Lval",[["Mem",["Lval",[["Var","samples"],null]]],null]],"text":"*samples","abs_text":"X"},"Exp-124707":{"tree":["OtherExp"],"text":"!(*stream.oldRatePosition==oldSampleRate)","abs_text":"!X==X"},"Exp-123956":{"tree":["OtherExp"],"text":"!(value<-32767)","abs_text":"!X<C"},"Exp-124268":{"tree":["OtherExp"],"text":"*stream.numOutputSamples+1","abs_text":"X+C"},"Exp-124096":{"tree":["Lval",[["Var","skip"],null]],"text":"skip","abs_text":"X"},"Exp-124009":{"tree":["Lval",[["Var","left"],null]],"text":"left","abs_text":"X"},"Exp-124206":{"tree":["Lval",[["Mem",["Lval",[["Var","stream"],null]]],["Field","inputBufferSize",null]]],"text":"*stream.inputBufferSize","abs_text":"X"},"Exp-124668":{"tree":["Lval",[["Var","insertPitchPeriod"],null]],"text":"@insertPitchPeriod","abs_text":"X"},"Exp-124252":{"tree":["OtherExp"],"text":"*stream.oldRatePosition+1","abs_text":"X+C"},"Exp-124413":{"tree":["OtherExp"],"text":"*stream.oldRatePosition+1","abs_text":"X+C"},"Exp-124576":{"tree":["Lval",[["Var","maxPeriod"],null]],"text":"maxPeriod","abs_text":"X"},"Exp-124597":{"tree":["Lval",[["Var","__cil_tmp3"],null]],"text":"__cil_tmp3","abs_text":"X"},"Exp-124231":{"tree":["OtherExp"],"text":"*u*t","abs_text":"X*X"},"Exp-124337":{"tree":["Lval",[["Var","processStreamInput"],null]],"text":"@processStreamInput","abs_text":"X"},"Exp-124159":{"tree":["OtherExp"],"text":"*stream.pitchBuffer!=0","abs_text":"X!=C"},"Exp-124405":{"tree":["Lval",[["Var","sonicSetRate"],null]],"text":"@sonicSetRate","abs_text":"X"},"Exp-124154":{"tree":["Const",0],"text":"2","abs_text":"C"},"Exp-124389":{"tree":["Lval",[["Var","inFile"],null]],"text":"inFile","abs_text":"X"},"Exp-123936":{"tree":["Lval",[["Mem",["Lval",[["Var","stream"],null]]],["Field","remainingInputToCopy",null]]],"text":"*stream.remainingInputToCopy","abs_text":"X"},"Exp-124271":{"tree":["Lval",[["Mem",["Lval",[["Var","stream"],null]]],["Field","remainingInputToCopy",null]]],"text":"*stream.remainingInputToCopy","abs_text":"X"},"Exp-124645":{"tree":["Lval",[["Var","__cil_tmp3"],null]],"text":"__cil_tmp3","abs_text":"X"},"Exp-124574":{"tree":["OtherExp"],"text":"!(period<=maxPeriod)","abs_text":"!X<=X"},"Exp-124317":{"tree":["Lval",[["Var","pitch"],null]],"text":"pitch","abs_text":"X"},"Exp-124553":{"tree":["OtherExp"],"text":"*stream.outputBuffer+(*stream.numOutputSamples**stream.numChannels)","abs_text":"X+X*X"},"Exp-123982":{"tree":["Lval",[["Var","period"],null]],"text":"period","abs_text":"X"},"Exp-124040":{"tree":["Lval",[["Var","readExactBytes"],null]],"text":"@readExactBytes","abs_text":"X"},"Exp-124261":{"tree":["Lval",[["Var","separation"],null]],"text":"separation","abs_text":"X"},"Exp-124088":{"tree":["Lval",[["Var","originalNumOutputSamples"],null]],"text":"originalNumOutputSamples","abs_text":"X"},"Exp-123994":{"tree":["OtherExp"],"text":"SizeOf(short )","abs_text":"SizeOf"},"Exp-124495":{"tree":["OtherExp"],"text":"(*stream.numPitchSamples-numSamples)*SizeOf(short )","abs_text":"X-X*SizeOf"},"Exp-124516":{"tree":["OtherExp"],"text":"*file.numChannels*2","abs_text":"X*C"},"Exp-124229":{"tree":["Lval",[["Mem",["Lval",[["Var","d"],null]]],null]],"text":"*d","abs_text":"X"},"Exp-124484":{"tree":["OtherExp"],"text":"speed-1.f","abs_text":"X-C"},"Exp-124684":{"tree":["Lval",[["Var","pitch"],null]],"text":"pitch","abs_text":"X"},"Exp-123940":{"tree":["OtherExp"],"text":"t<numSamples","abs_text":"X<X"},"Exp-124053":{"tree":["OtherExp"],"text":"t<separation","abs_text":"X<X"},"Exp-124392":{"tree":["OtherExp"],"text":"t<numSamples","abs_text":"X<X"},"Exp-124164":{"tree":["OtherExp"],"text":"outFile==0","abs_text":"X==C"},"Exp-124129":{"tree":["Lval",[["Var","fixedPointVolume"],null]],"text":"fixedPointVolume","abs_text":"X"},"Exp-124312":{"tree":["Lval",[["Var","outFileName"],null]],"text":"outFileName","abs_text":"X"},"Exp-124634":{"tree":["OtherExp"],"text":"*stream.pitchBuffer+(*stream.numPitchSamples*numChannels)","abs_text":"X+X*X"},"Exp-123972":{"tree":["OtherExp"],"text":"!(numSamples==0)","abs_text":"!X==C"},"Exp-124131":{"tree":["OtherExp"],"text":"!(newSamples==0)","abs_text":"!X==C"},"Exp-124163":{"tree":["OtherExp"],"text":"!(outFile==0)","abs_text":"!X==C"},"Exp-124347":{"tree":["Lval",[["Var","d"],null]],"text":"d","abs_text":"X"},"Exp-124408":{"tree":["OtherExp"],"text":"!(numSamples==0)","abs_text":"!X==C"},"Exp-124443":{"tree":["OtherExp"],"text":"!(soundFile==0)","abs_text":"!X==C"},"Exp-124586":{"tree":["OtherExp"],"text":"!(inFile==0)","abs_text":"!X==C"},"Exp-124595":{"tree":["OtherExp"],"text":"!(samplesRead==0)","abs_text":"!X==C"},"Exp-124694":{"tree":["OtherExp"],"text":"!(numSamples==0)","abs_text":"!X==C"},"Exp-124095":{"tree":["Lval",[["Var","stream"],null]],"text":"stream","abs_text":"X"},"Exp-124075":{"tree":["OtherExp"],"text":"1<<14","abs_text":"C<<C"},"Exp-124397":{"tree":["Lval",[["Var","numSamples"],null]],"text":"numSamples","abs_text":"X"},"Exp-124279":{"tree":["OtherExp"],"text":"!((*stream.numPitchSamples-position)>=*stream.maxRequired)","abs_text":"!X-X>=X"},"Exp-124046":{"tree":["Lval",[["Var","oldSampleRate"],null]],"text":"oldSampleRate","abs_text":"X"},"Exp-124673":{"tree":["Lval",[["Var","fileName"],null]],"text":"fileName","abs_text":"X"},"Exp-124656":{"tree":["Lval",[["Var","maxDiff"],null]],"text":"maxDiff","abs_text":"X"},"Exp-124536":{"tree":["OtherExp"],"text":"period*SizeOf(short )","abs_text":"X*SizeOf"},"Exp-124074":{"tree":["Lval",[["Var","newSampleRate"],null]],"text":"newSampleRate","abs_text":"X"},"Exp-124286":{"tree":["OtherExp"],"text":"(*stream.inputBufferSize>>1)+numSamples","abs_text":"X>>C+X"},"Exp-124420":{"tree":["OtherExp"],"text":"(*stream.outputBufferSize>>1)+numSamples","abs_text":"X>>C+X"},"Exp-124643":{"tree":["OtherExp"],"text":"(*stream.pitchBufferSize>>1)+numSamples","abs_text":"X>>C+X"},"Exp-124011":{"tree":["OtherExp"],"text":"width-ratio","abs_text":"X-X"},"Exp-124349":{"tree":["Lval",[["Var","__cil_tmp11"],null]],"text":"__cil_tmp11","abs_text":"X"}}