{"Exp-652":{"tree":["Const",0],"text":"1","abs_text":"C"},"Exp-643":{"tree":["Lval",[["Var","sparrow_opt"],null]],"text":"@sparrow_opt","abs_text":"X"},"Exp-657":{"tree":["Const",0],"text":"0","abs_text":"C"},"Exp-656":{"tree":["Const",0],"text":"5","abs_text":"C"},"Exp-648":{"tree":["Lval",[["Var","argv"],null]],"text":"argv","abs_text":"X"},"Exp-655":{"tree":["OtherExp"],"text":"argv+5","abs_text":"X+C"},"Exp-650":{"tree":["OtherExp"],"text":"@optind-1","abs_text":"optind-C"},"Exp-644":{"tree":["Lval",[["Var","optind"],null]],"text":"@optind","abs_text":"X"},"Exp-653":{"tree":["Lval",[["Var","strtoul"],null]],"text":"@strtoul","abs_text":"strtoul"},"Exp-658":{"tree":["Const",0],"text":"10","abs_text":"C"},"Exp-647":{"tree":["Lval",[["Var","argc"],null]],"text":"argc","abs_text":"X"},"Exp-654":{"tree":["Lval",[["Mem",["OtherExp"]],null]],"text":"*(argv+5)","abs_text":"X"},"Exp-651":{"tree":["Lval",[["Var","optind"],null]],"text":"@optind","abs_text":"optind"},"Exp-645":{"tree":["Lval",[["Var","optarg"],null]],"text":"@optarg","abs_text":"X"},"Exp-646":{"tree":["Lval",[["Var","sparrow_arg"],null]],"text":"@sparrow_arg","abs_text":"X"},"Exp-649":{"tree":["OtherExp"],"text":"argv+(@optind-1)","abs_text":"X+optind-C"}}